Workbook

Sheet Customer_Dim
A1: Customer_ID | B1: Name | C1: Age | D1: Gender | E1: City | F1: State | G1: Country | H1: Loyalty_Level
A2: CUST1000 | B2: sheena bonilla | C2: 55 | D2: Male | E2: Donaldton | F2: North Carolina | G2: USA
A3: CUST1001 | B3: Eugene Nelson | C3: 26 | D3: Female | E3: Phillipsmouth | F3: North Dakota | G3: USA | H3: Platinum
A4: CUST1002 | B4: dr. Benjamin Price | C4: 29 | D4: Female | E4: Kylebury | F4: Alabama | G4: USA | H4: Platinum
A5: CUST1003 | B5: jeremy harris | C5: 59 | D5: Female | E5: Thomastown | F5: Ohio | G5: USA | H5: Bronze
A6: CUST1004 | B6: Caroline Collins | C6: 64 | D6: Female | E6: Nicholasshire | F6: California | G6: USA | H6: Silver
A7: CUST1005 | B7: Christine Vaughn | C7: 24 | D7: Male | E7: East Amandamouth | F7: Oregon | G7: USA | H7: Bronze
A8: CUST1006 | B8: Amber Jackson | C8: 29 | D8: Female | E8: Deborahborough | F8: South Dakota | G8: USA | H8: Platinum
A9: CUST1007 | B9: Daniel Boyd | C9: 29 | D9: Female | E9: West Pamelafurt | F9: West Virginia | G9: USA | H9: Bronze
A10: CUST1008 | B10: Melissa Howard | C10: 53 | D10: Female | E10: Maynardton | F10: New Hampshire | G10: USA | H10: Gold
A11: CUST1009 | B11: Ms. Maria Leach | C11: 64 | D11: Male | E11: Melissashire | F11: Pennsylvania | G11: USA | H11: Platinum
A12: CUST1010 | B12: Dominic Page | C12: 53 | D12: Male | E12: Port Michaelburgh | F12: Pennsylvania | G12: USA | H12: Bronze
A13: CUST1011 | B13: Brian Lopez | C13: 28 | D13: Female | E13: East Krista | F13: New York | G13: USA | H13: Gold
A14: CUST1012 | B14: Kenneth Lambert | C14: 55 | D14: Female | E14: North Kathryn | F14: Kansas | G14: USA | H14: Platinum
... A19: CUST1017 | B19: Adam Cruz | C19: 60 | D19: Female | E19: Brandonville | F19: Georgia | G19: USA | H19: Platinum
A20: CUST1018 | B20: Rhonda Moss | C20: 43 | D20: Male | E20: South William | F20: Kansas | G20: USA
A21: CUST1019 | B21: Michael Torres | C21: 46 | D21: Female | E21: Gonzalezfort | F21: New Jersey | G21: USA | H21: Platinum
A22: CUST1020 | B22: Bridget Allen | C22: 59 | D22: Male | E22: Lake Shaneburgh | F22: Delaware | G22: USA | H22: Silver
A23: CUST1021 | B23: Jeff Martinez | C23: 36 | D23: Female | E23: Smithburgh | F23: Oklahoma | G23: USA | H23: Gold
A24: CUST1022 | B24: paul fox | C24: 33 | D24: Female | E24: Michaelton | F24: Hawaii | G24: USA | H24: Silver
A25: CUST1023 | B25: Jonathan Steele | C25: 52 | D25: Female | E25: Molinabury | F25: Oregon | G25: USA | H25: Silver
A26: CUST1024 | B26: Heather Collins | C26: 40 | D26: Male | E26: Rogerschester | F26: Idaho | G26: USA | H26: Platinum
A27: CUST1025 | B27: Diana Taylor | C27: 59 | D27: Female | E27: Vasqueztown | F27: California | G27: USA | H27: Bronze
A28: CUST1026 | B28: Amber Carlson | C28: 18 | D28: Female | E28: East Michellemouth | F28: Missouri | G28: USA | H28: Gold
A29: CUST1027 | B29: Leslie Johnson | C29: 31 | D29: Male | E29: Mollyshire | F29: Utah | G29: USA
A30: CUST1028 | B30: Joshua Ryan | C30: 27 | D30: Female | E30: New David | F30: New Jersey | G30: USA | H30: Platinum
A31: CUST1029 | B31: David Arnold | C31: 54 | D31: Female | E31: East Jennifer | F31: California | G31: USA | H31: Silver
A32: CUST1030 | B32: Jessica Acevedo | C32: 64 | D32: Female | E32: Amybury | F32: Pennsylvania | G32: USA | H32: Bronze
A33: CUST1031 | B33: Sarah Vance | C33: 41 | D33: Male | E33: Johnsonville | F33: Oregon | G33: USA | H33: Silver
A34: CUST1032 | B34: Mike Jennings | C34: 48 | D34: Female | E34: Fostermouth | F34: Arizona | G34: USA | H34: Gold
A35: CUST1033 | B35: Robert Jones DDS | C35: 25 | D35: Male | E35: Tristanton | F35: Oklahoma | G35: USA | H35: Platinum
A36: CUST1034 | B36: Christopher Olson | C36: 27 | D36: Female | E36: West Richard | F36: Maryland | G36: USA | H36: Platinum
A37: CUST1035 | B37: Rachel Myers | C37: 52 | D37: Male | E37: Robertberg | F37: North Dakota | G37: USA | H37: Silver
A38: CUST1036 | B38: Thomas Phillips | C38: 20 | D38: Female | E38: Luisfurt | F38: Georgia | G38: USA | H38: Gold
A39: CUST1037 | B39: Christopher Carter | C39: 27 | D39: Female | E39: Brendastad | F39: South Dakota | G39: USA
A40: CUST1038 | B40: Deanna Simpson | C40: 35 | D40: Female | E40: Brownport | F40: North Dakota | G40: USA | H40: Bronze
A41: CUST1039 | B41: Tonya Reynolds | C41: 55 | D41: Female | E41: Darleneton | F41: Michigan | G41: USA | H41: Gold
A42: CUST1040 | B42: Eric Vega | C42: 50 | D42: Male | E42: Williamsonland | F42: Kansas | G42: USA | H42: Gold
A43: CUST1041 | B43: James Gibbs | C43: 21 | D43: Male | E43: Mooneyshire | F43: Alaska | G43: USA | H43: Platinum
A44: CUST1042 | B44: William Martin | C44: 19 | D44: Male | E44: Ryanburgh | F44: Connecticut | G44: USA | H44: Platinum
A45: CUST1043 | B45: Joseph Snow | C45: 45 | D45: Male | E45: South Michaelfort | F45: Vermont | G45: USA | H45: Gold
A46: CUST1044 | B46: Denise Williams | C46: 34 | D46: Male | E46: Christianstad | F46: Hawaii | G46: USA | H46: Bronze
A47: CUST1045 | B47: Jordan Jackson DDS | C47: 54 | D47: Male | E47: North Johnview | F47: Arizona | G47: USA | H47: Gold
A48: CUST1046 | B48: Michelle Garcia DDS | C48: 55 | D48: Female | E48: Perezbury | F48: Ohio | G48: USA | H48: Platinum
A49: CUST1047 | B49: Gina Knight | C49: 54 | D49: Female | E49: Lake Roberthaven | F49: Nevada | G49: USA | H49: Silver
A50: CUST1048 | B50: April Mullins | C50: 54 | D50: Male | E50: Dawsonbury | F50: North Carolina | G50: USA | H50: Platinum
A51: CUST1049 | B51: Timothy Weaver | C51: 45 | D51: Female | E51: New Amy | F51: Ohio | G51: USA | H51: Gold
... A501: C-1499 | B501: Philip Pennington | C501: 27 | D501: Female | E501: East Valerieview | F501: Oregon | G501: USA | H501: Platinum

Sheet Product_Dim
A1: Product_ID | B1: Product_Name | C1: Category | D1: Sub_Category | E1: Brand | F1: Cost | G1: Stock
A2: PROD0 | B2: Brother Laser Printer | C2: Electronics | D2: Computer | E2: Hunt Inc | F2: 112.42 | G2: 416
A3: PROD1 | B3: Men's Graphic T-Shirt | C3: Clothing | D3: Tops | E3: Terry-Moore | F3: 342.56 | G3: 181
A4: PROD2 | B4: Women's Casual Hoodie | C4: Clothing | D4: Outerwear | E4: Sims Inc | G4: 352
A5: P-3 | B5: Men's Running Jacket | C5: Clothing | D5: Outerwear | E5: Pineda Ltd | F5: 364.67 | G5: 452
A6: PROD4 | B6: Women's Yoga Pants | C6: Clothing | D6: Bottoms | E6: Gonzales-Davis | F6: 306.46 | G6: 487
A7: PROD5 | B7: Men's Leather Belt | C7: Clothing | D7: Accessories | E7: Baldwin, Garza and Gonzalez | F7: 261 | G7: 59
A8: PROD6 | B8: Herbal Face Moisturizer | C8: Beauty | D8: Skincare | E8: Davidson PLC | F8: 312.8 | G8: 350
A9: PROD7 | B9: LED Table Lamp | C9: Home | D9: Lighting | E9: Harrell LLC | F9: 218.86 | G9: 170
A10: PROD8 | B10: Wireless Bluetooth Earbuds | C10: Electronics | D10: Audio | E10: Perez-Johnston | F10: 439.07 | G10: 142
A11: PROD9 | B11: Adjustable Dumbbell Set | C11: Sports | D11: Fitness | E11: Hill PLC | F11: 495.72 | G11: 323
A12: PROD10 | B12: Ceramic Kitchen Bowl Set | C12: Home | D12: Kitchen | E12: Hamilton Group | F12: 298.86 | G12: 308
A13: PROD11 | B13: HD Smart TV Stick | C13: Electronics | D13: Accessories | E13: Gibson, Hobbs and Weaver | F13: 449.4
A14: PROD12 | B14: Hair Strengthening Shampoo | C14: Beauty | D14: Haircare | E14: Rice LLC | F14: 115.82 | G14: 460
A15: PROD13 | B15: USB-C Fast Charger | C15: Electronics | D15: Accessories | E15: Dawson-Perkins | F15: 242.23 | G15: 453
A16: PROD14 | B16: Decorative Wall Mirror | C16: Home | D16: Decor | E16: Luna, Anderson and Bowman | F16: 48.01 | G16: 439
A17: PROD15 | B17: 4K Home Projector | C17: Electronics | D17: Appliances | E17: Thomas LLC | F17: 465.34 | G17: 301
A18: P-16 | B18: Beard Grooming Kit | C18: Beauty | D18: Grooming | E18: Erickson-Green | F18: 337.42 | G18: 256
A19: PROD17 | B19: Soccer Training Cone Set | C19: Sports | D19: Accessories | E19: Ford, Murphy and Wilson | F19: 144.53 | G19: 367
A20: PROD18 | B20: Women's Denim Jeans | C20: Clothing | D20: Bottoms | E20: Guerra-Hendrix | G20: 343
A21: PROD19 | B21: Knee Support Brace | C21: Sports | D21: Equipment | E21: May-Reese | F21: 21.34 | G21: 65
A22: PROD20 | B22: Outdoor Sports Water Bottle | C22: Sports | D22: Accessories | E22: Soto-Ellis | F22: 131.51
A23: PROD21 | B23: Multi-Purpose Storage Box | C23: Home | D23: Storage | E23: Gardner-Montes | F23: 123.46 | G23: 76
A24: PROD22 | B24: Carbon Fiber Tennis Racket | C24: Sports | D24: Equipment | E24: Flores, Pineda and Rodriguez | F24: 484.62 | G24: 432
A25: PROD23 | B25: Men's Formal Shirt | C25: Clothing | D25: Tops | E25: Moon, Mora and Santos | G25: 360
A26: PROD24 | B26: Foldable Camping Chair | C26: Sports | D26: Outdoor | E26: Cook Ltd | F26: 166.06 | G26: 340
A27: PROD25 | B27: Women's Scarf Set | C27: Clothing | D27: Accessories | E27: Brown and Sons | F27: 174.02 | G27: 268
A28: PROD26 | B28: Wireless Bluetooth Speaker | C28: Electronics | D28: Audio | E28: Reed-Schmidt | F28: 322.41 | G28: 213
A29: PROD27 | B29: Decorative Floor Vase | C29: Home | D29: Decor | E29: Khan, Jones and Paul | G29: 378
A30: PROD28 | B30: Sports Stopwatch Timer | C30: Sports | D30: Accessories | E30: Burns-Hansen | F30: 38.76 | G30: 137
A31: PROD29 | B31: Fabric Sofa Throw Blanket | C31: Home | D31: Decor | E31: Hoffman Group | F31: 218.48 | G31: 276
A32: PROD30 | B32: Stainless Steel Cutlery Set | C32: Home | D32: Kitchen | E32: Stevens, Fernandez and Martin | F32: 19.52 | G32: 57
A33: PROD31 | B33: Basketball | C33: Sports | D33: Team Sports | E33: Nolan-Snow | F33: 204.39 | G33: 281
A34: PROD32 | B34: Vitamin C Face Serum | C34: Beauty | D34: Skincare | E34: Griffin Ltd | F34: 283.83 | G34: 244
A35: PROD33 | B35: Modern Wall Clock | C35: Home | D35: Decor | E35: Weiss-Watson | F35: 179.77 | G35: 305
A36: PROD34 | B36: Gaming Mechanical Keyboard | C36: Electronics | D36: Computer | E36: Lucero LLC | F36: 419.28 | G36: 86
A37: PROD35 | B37: Bedroom Table Lamp | C37: Home | D37: Lighting | E37: Jones LLC | F37: 382.22 | G37: 329
A38: PROD36 | B38: Women's Summer Dress | C38: Clothing | D38: Tops | E38: Smith-Mills | F38: 223.43 | G38: 154
A39: PROD37 | B39: Men's Casual Sneakers | C39: Clothing | D39: Footwear | E39: Hogan-Lee | F39: 353.47 | G39: 214
A40: PROD38 | B40: Sports Water Hydration Pack | C40: Sports | D40: Outdoor | E40: Sims-Smith | F40: 135.61 | G40: 394
A41: PROD39 | B41: Portable Power Bank | C41: Electronics | D41: Mobile | E41: Cummings and Sons | F41: 326.06 | G41: 301
... A48: PROD46 | B48: Men's Winter Jacket | C48: Clothing | D48: Outerwear | E48: Kelly, Smith and Perez | F48: 167.34 | G48: 296
A49: PROD47 | B49: Makeup Brush Set | C49: Beauty | D49: Makeup | E49: Cook Inc | G49: 431
A50: PROD48 | B50: Car Dashboard Phone Holder | C50: Electronics | D50: Accessories | E50: Byrd, Stewart and Valdez | F50: 177.98 | G50: 103
A51: PROD49 | B51: Men's Roll-On Perfume | C51: Beauty | D51: Fragrance | E51: Sullivan and Sons | F51: 43.29 | G51: 267
A52: PROD50 | B52: Boxing Hand Wraps | C52: Sports | D52: Fitness | E52: Smith-King | F52: 190.29 | G52: 260
A53: PROD51 | B53: HDMI Cable – 2m | C53: Electronics | D53: Accessories | E53: Bautista, Green and Hale | F53: 88.49 | G53: 246
A54: PROD52 | B54: Rugby Ball | C54: Sports | D54: Team Sports | E54: Harris Inc | F54: 212.26 | G54: 82
A55: PROD53 | B55: Men's Track Pants | C55: Clothing | D55: Bottoms | E55: Hamilton, Woods and Walker | F55: 386.56 | G55: 125
A56: PROD54 | B56: Sports Stopwatch Pro | C56: Sports | D56: Accessories | E56: Thompson-French | F56: 434.84 | G56: 185
A57: PROD55 | B57: Ceramic Plant Pot | C57: Home | D57: Decor | E57: Hatfield, Baird and Torres | F57: 81.75
A58: PROD56 | B58: Premium Blanket Throw | C58: Home | D58: Decor | E58: Hernandez, Kennedy and Porter | F58: 461.47 | G58: 190
A59: PROD57 | B59: Foam Roller | C59: Sports | D59: Fitness | E59: Atkinson, Camacho and Oliver | F59: 30.62 | G59: 138
A60: PROD58 | B60: Womens Cotton Scarf | C60: Clothing | D60: Accessories | E60: Shepherd-Gould | F60: 113.83 | G60: 485
A61: PROD59 | B61: Men's Hair Styling Gel | C61: Beauty | D61: Haircare | E61: Cline-Mccarthy | F61: 17.31 | G61: 399
A62: PROD60 | B62: Luxury Perfume Spray | C62: Beauty | D62: Fragrance | E62: Gibson, Green and Lopez | F62: 482.75 | G62: 444
A63: PROD61 | B63: Tennis Ball 3-Pack | C63: Sports | D63: Equipment | E63: Lopez LLC | F63: 103.45 | G63: 465
A64: PROD62 | B64: Laptop Cooling Pad | C64: Electronics | D64: Computer | E64: Murray, Gould and Ware | F64: 86.42 | G64: 222
A65: PROD63 | B65: Organic Sunscreen Lotion | C65: Beauty | D65: Skincare | E65: Anderson-Riley | F65: 266.86 | G65: 458
A66: PROD64 | B66: Matte Lipstick Set | C66: Beauty | D66: Makeup | E66: Zhang Inc | F66: 299.11 | G66: 118
A67: PROD65 | B67: Adjustable Dumbbells 20kg | C67: Sports | D67: Fitness | E67: Montgomery, Benton and Miller | F67: 240.63 | G67: 423
A68: PROD66 | B68: Women's Hair Dryer Brush | C68: Beauty | D68: Haircare | E68: Torres, Spencer and Potter | F68: 340.39 | G68: 177
A69: PROD67 | B69: Smart LED Light Strip | C69: Electronics | D69: Accessories | E69: Flores-Davis | F69: 349.17 | G69: 476
... A84: PROD82 | B84: Fitness Resistance Bands | C84: Sports | D84: Fitness | E84: Reese-Watson | F84: 152.92 | G84: 281
A85: PROD83 | B85: Hydrating Face Cleanser | C85: Beauty | D85: Skincare | E85: Butler Group | G85: 159
A86: PROD84 | B86: Wooden Bookshelf | C86: Home | D86: Furniture | E86: Collins-Stephenson | F86: 388.46 | G86: 208
A87: PROD85 | B87: Women's Beanie Hat | C87: Clothing | D87: Accessories | E87: Richardson-Carrillo | F87: 119.57 | G87: 210
A88: PROD86 | B88: Kitchen Cutting Board | C88: Home | D88: Kitchen | E88: Taylor, Dodson and Johnston | F88: 176.07 | G88: 82
A89: PROD87 | B89: LED Bedside Lamp | C89: Home | D89: Lighting | E89: Aguilar, Horton and Lewis | F89: 371.38 | G89: 220
A90: PROD88 | B90: Sports Wrist Sweatbands | C90: Sports | D90: Accessories | E90: Olsen-Daniels | F90: 131.24 | G90: 232
A91: PROD89 | B91: Face Foundation Kit | C91: Beauty | D91: Makeup | E91: Taylor-Elliott | F91: 183.04 | G91: 457
A92: PROD90 | B92: Gaming Mouse Pad XL | C92: Electronics | D92: Accessories | E92: Sharp, Taylor and Rodriguez | F92: 340.14 | G92: 361
A93: PROD91 | B93: Women's High Heels | C93: Clothing | D93: Footwear | E93: Smith-Charles | F93: 438.25 | G93: 496
A94: PROD92 | B94: Microwave Oven | C94: Home | D94: Appliances | E94: Green, Powell and Palmer | F94: 447.43 | G94: 191
A95: PROD93 | B95: USB-C Laptop Charger | C95: Electronics | D95: Computer | E95: Martin LLC | F95: 377.52 | G95: 485
A96: PROD94 | B96: Vitamin E Body Lotion | C96: Beauty | D96: Skincare | E96: Hoffman-Williams | F96: 358.47 | G96: 213
A97: PROD95 | B97: Sports Stopwatch Basic | C97: Sports | D97: Accessories | E97: Wilson Group | F97: 60.65 | G97: 75
... A101: PROD99 | B101: Stainless Steel Cookware Set | C101: Home | D101: Kitchen | E101: Campbell Ltd | F101: 201.41 | G101: 146

Sheet Store_Dim
A1: Store_ID | B1: Store_Name | C1: Region | D1: City | E1: Store_Type
A2: STORE0 | B2: Rivera-Warner | C2: East | D2: Washingtonfurt | E2: Flagship
A3: STORE1 | B3: Martinez, Adkins and Johnson | C3: North | D3: Danielmouth | E3: Flagship
A4: STORE2 | B4: Black-Horn | C4: South | D4: North Nancyview | E4: Outlet
A5: STORE3 | B5: Johnson-Wright | C5: North | D5: Hoodberg | E5: Outlet
A6: STORE4 | B6: Alexander Group | C6: South | D6: Port Sharon | E6: Online
A7: STORE5 | B7: Gray Ltd | C7: North | D7: New Michaelchester | E7: Outlet
A8: STORE6 | B8: Benson-Elliott | C8: East | D8: Port Josephberg | E8: Online
A9: STORE7 | B9: Martinez-Mullins | C9: South | D9: Williamsfurt | E9: Online
A10: STORE8 | B10: Bean, Jones and Park | C10: West | D10: Thompsonborough | E10: Online
A11: STORE9 | B11: Moore, Padilla and Butler | C11: South | D11: East Johnstad | E11: Flagship
A12: STORE10 | B12: Hill, Wagner and Ballard | C12: East | D12: East Davidville | E12: Online
... A21: STORE19 | B21: Mann-Austin | C21: East | D21: Vasquezborough | E21: Online

Sheet Sales_Fact
A1: Sales_ID | B1: Order_Date | C1: Customer_ID | D1: Product_ID | E1: Store_ID | F1: Quantity | G1: Unit_Price | H1: Discount | I1: Payment_Type | J1: Total_Amount
A2: SALE0 | B2: 45480 | C2: CUST1409 | D2: PROD97 | E2: STORE3 | F2: 1 | G2: 218.04 | H2: 0.09 | I2: Credit Card | J2: 198.4164
A3: SALE1 | B3: 45285 | C3: CUST1467 | D3: PROD74 | E3: STORE17 | F3: 3 | G3: 104.47 | H3: 0.27 | I3: PayPal | J3: 228.7893
A4: SALE2 | B4: 45446 | C4: CUST1056 | D4: PROD49 | E4: STORE8 | F4: 4 | G4: 914.05 | H4: 0.25 | I4: Credit Card | J4: 2742.15
A5: SALE3 | B5: 45259 | C5: CUST1346 | D5: PROD76 | E5: STORE8 | F5: 1 | G5: 921.51 | H5: 0.16 | I5: COD | J5: 774.0684
A6: SALE4 | B6: 45297 | C6: CUST1493 | D6: PROD59 | E6: STORE5 | F6: 3 | G6: 745.3 | H6: 0.18 | I6: Credit Card | J6: 1833.438
A7: SALE5 | B7: 45499 | C7: CUST1116 | D7: PROD15 | E7: STORE7 | F7: 3 | G7: 147.01 | H7: 0.19 | I7: COD | J7: 357.2343
A8: SALE6 | B8: 45850 | C8: CUST1016 | D8: PROD56 | E8: STORE4 | F8: 2 | G8: 785.31 | H8: 0.15 | I8: PayPal | J8: 1335.027
A9: SALE7 | B9: 45248 | C9: CUST1152 | D9: PROD70 | E9: STORE8 | F9: 4 | G9: 342.39 | H9: 0.23 | I9: PayPal | J9: 1054.5612
A10: SALE8 | B10: 45781 | C10: CUST1187 | D10: PROD99 | E10: STORE5 | G10: 448.25 | H10: 0.07 | I10: PayPal | J10: 1250.6175
A11: SALE9 | B11: 45869 | C11: CUST1464 | D11: PROD33 | E11: STORE0 | F11: 2 | G11: 873.17 | H11: 0.23 | I11: PayPal | J11: 1344.6818
A12: SALE10 | B12: 45335 | C12: CUST1065 | D12: PROD24 | E12: STORE14 | F12: 1 | G12: 278.63 | H12: 0.07 | I12: Credit Card | J12: 259.1259
A13: SALE11 | B13: 45801 | C13: CUST1320 | D13: PROD39 | E13: STORE1 | F13: 4 | G13: 286.92 | H13: 0.17 | I13: Credit Card | J13: 952.5744
A14: SALE12 | B14: 45528 | C14: CUST1237 | D14: PROD88 | E14: STORE4 | F14: 4 | G14: 644.58 | H14: 0.01 | I14: Credit Card | J14: 2552.5368
A15: SALE13 | B15: 45875 | C15: CUST1443 | D15: PROD34 | E15: STORE16 | F15: 2 | G15: 316.9 | H15: 0.3 | I15: PayPal | J15: 443.66
A16: SALE14 | B16: 45829 | C16: CUST1348 | D16: PROD24 | E16: STORE15 | F16: 4 | G16: 403.47 | H16: 0.29 | I16: PayPal | J16: 1145.8548
A17: SALE15 | B17: 45636 | C17: CUST1435 | D17: PROD36 | E17: STORE9 | G17: 871.34 | H17: 0.04 | I17: COD | J17: 2509.4592
A18: SALE16 | B18: 45913 | C18: CUST1276 | D18: PROD65 | E18: STORE19 | F18: 2 | G18: 451.98 | H18: 0.25 | I18: Credit Card | J18: 677.97
A19: SALE17 | B19: 45637 | C19: CUST1079 | D19: PROD27 | E19: STORE4 | F19: 2 | G19: 502.69 | H19: 0.23 | I19: Credit Card | J19: 774.1426
A20: SALE18 | B20: 45517 | C20: CUST1094 | D20: PROD39 | E20: STORE4 | F20: 2 | G20: 559.23 | H20: 0.25 | I20: COD | J20: 838.845
A21: SALE19 | B21: 45369 | C21: CUST1239 | D21: PROD60 | E21: STORE13 | F21: 4 | H21: 0.04 | I21: COD | J21: 1782.4512
A22: SALE20 | B22: 45843 | C22: CUST1144 | D22: PROD72 | E22: STORE17 | F22: 3 | G22: 986.04 | H22: 0.27 | I22: COD | J22: 2159.4276
A23: SALE21 | B23: 45447 | C23: CUST1396 | D23: PROD43 | E23: STORE18 | F23: 1 | G23: 589.56 | H23: 0.22 | I23: Credit Card | J23: 459.8568
A24: SALE22 | B24: 45394 | C24: CUST1476 | D24: PROD69 | E24: STORE10 | F24: 3 | G24: 979.42 | H24: 0.03 | I24: PayPal | J24: 2850.1122
A25: SALE23 | B25: 45466 | C25: CUST1368 | D25: PROD12 | E25: STORE8 | F25: 1 | G25: 719.28 | H25: 0.08 | I25: Credit Card | J25: 661.7376
A26: SALE24 | B26: 45908 | C26: CUST1186 | D26: PROD67 | E26: STORE6 | F26: 3 | G26: 77.6 | H26: 0.07 | I26: Credit Card | J26: 216.504
A27: SALE25 | B27: 45552 | C27: CUST1381 | D27: PROD5 | E27: STORE3 | F27: 4 | G27: 852.71 | H27: 0.14 | I27: PayPal | J27: 2933.3224
A28: SALE26 | B28: 45294 | C28: CUST1213 | D28: PROD98 | E28: STORE8 | F28: 4 | G28: 156.16 | I28: Credit Card | J28: 599.6544
A29: SALE27 | B29: 45710 | C29: CUST1200 | D29: PROD77 | E29: STORE8 | F29: 3 | G29: 815.49 | H29: 0.17 | I29: Credit Card | J29: 2030.5701
A30: SALE28 | B30: 45923 | C30: CUST1148 | D30: PROD13 | E30: STORE2 | F30: 2 | G30: 74.21 | H30: 0.11 | I30: PayPal | J30: 132.0938
A31: SALE29 | B31: 45302 | C31: CUST1348 | D31: PROD99 | E31: STORE3 | G31: 451.67 | H31: 0.15 | I31: Credit Card | J31: 1535.678
A32: SALE30 | B32: 45217 | C32: CUST1028 | D32: PROD5 | E32: STORE19 | F32: 1 | G32: 429.38 | H32: 0.13 | I32: PayPal | J32: 373.5606
A33: SALE31 | B33: 45593 | C33: CUST1412 | D33: PROD53 | E33: STORE12 | F33: 2 | G33: 148.96 | H33: 0.03 | I33: COD | J33: 288.9824
A34: SALE32 | B34: 45597 | C34: CUST1398 | D34: PROD75 | E34: STORE8 | F34: 4 | G34: 313.83 | H34: 0.08 | I34: Credit Card | J34: 1154.8944
A35: SALE33 | B35: 45620 | C35: CUST1453 | D35: PROD12 | E35: STORE6 | F35: 2 | G35: 717.31 | H35: 0.15 | I35: Credit Card | J35: 1219.427
A36: SALE34 | B36: 45215 | C36: CUST1344 | D36: PROD79 | E36: STORE1 | G36: 873.22 | H36: 0.18 | I36: Credit Card | J36: 2148.1212
A37: SALE35 | B37: 45878 | C37: CUST1218 | D37: PROD16 | E37: STORE3 | F37: 4 | G37: 109.36 | H37: 0.19 | I37: COD | J37: 354.3264
A38: SALE36 | B38: 45635 | C38: CUST1086 | D38: PROD5 | E38: STORE7 | F38: 3 | G38: 559.52 | H38: 0.16 | I38: PayPal | J38: 1409.9904
A39: SALE37 | B39: 45329 | C39: CUST1492 | D39: PROD10 | E39: STORE17 | F39: 3 | G39: 121.76 | H39: 0.27 | I39: PayPal | J39: 266.6544
A40: SALE38 | B40: 45378 | C40: CUST1189 | D40: PROD33 | E40: STORE13 | F40: 4 | G40: 735.32 | H40: 0.06 | I40: COD | J40: 2764.8032
A41: SALE39 | B41: 45264 | C41: CUST1431 | D41: PROD94 | E41: STORE3 | F41: 2 | G41: 600.73 | H41: 0.08 | I41: Credit Card | J41: 1105.3432
A42: SALE40 | B42: 45486 | C42: CUST1072 | D42: PROD26 | E42: STORE19 | F42: 2 | G42: 873.86 | H42: 0.07 | I42: COD | J42: 1625.3796
A43: SALE41 | B43: 45241 | C43: CUST1302 | D43: PROD23 | E43: STORE8 | F43: 3 | G43: 342.47 | H43: 0.08 | I43: PayPal | J43: 945.2172
A44: SALE42 | B44: 45649 | C44: CUST1335 | D44: PROD29 | E44: STORE9 | F44: 2 | G44: 915.15 | H44: 0.16 | I44: PayPal | J44: 1537.452
A45: SALE43 | B45: 45677 | C45: CUST1084 | D45: PROD33 | E45: STORE17 | G45: 863.11 | H45: 0.28 | I45: PayPal | J45: 1864.3176
A46: SALE44 | B46: 45538 | C46: CUST1203 | D46: PROD43 | E46: STORE12 | F46: 2 | G46: 209.32 | H46: 0.23 | I46: COD | J46: 322.3528
A47: SALE45 | B47: 45606 | C47: CUST1470 | D47: PROD59 | E47: STORE8 | F47: 4 | G47: 288.6 | H47: 0.09 | I47: PayPal | J47: 1050.504
A48: SALE46 | B48: 45570 | C48: CUST1070 | D48: PROD78 | E48: STORE16 | F48: 1 | G48: 418.69 | H48: 0.06 | I48: PayPal | J48: 393.5686
A49: SALE47 | B49: 45466 | C49: CUST1008 | D49: PROD30 | E49: STORE11 | F49: 1 | G49: 135.78 | H49: 0.14 | I49: PayPal | J49: 116.7708
A50: SALE48 | B50: 45218 | C50: CUST1203 | D50: PROD44 | E50: STORE17 | F50: 1 | G50: 517.13 | H50: 0.28 | I50: Credit Card | J50: 372.3336
A51: SALE49 | B51: 45607 | C51: CUST1420 | D51: PROD21 | E51: STORE16 | F51: 2 | G51: 384.66 | H51: 0.08 | I51: COD | J51: 707.7744
A52: SALE50 | B52: 45291 | C52: CUST1070 | D52: PROD52 | E52: STORE9 | F52: 3 | G52: 83.7 | H52: 0.24 | I52: PayPal | J52: 190.836
A53: SALE51 | B53: 45689 | C53: CUST1142 | D53: PROD69 | E53: STORE7 | F53: 3 | G53: 76.57 | H53: 0.26 | I53: Credit Card | J53: 169.9854
A54: SALE52 | B54: 45894 | C54: CUST1148 | D54: PROD89 | E54: STORE6 | F54: 3 | I54: Credit Card | J54: 486.0633
A55: SALE53 | B55: 45677 | C55: CUST1324 | D55: PROD20 | E55: STORE8 | F55: 1 | G55: 900.35 | H55: 0.13 | I55: COD | J55: 783.3045
A56: SALE54 | B56: 45706 | C56: CUST1095 | D56: PROD40 | E56: STORE10 | F56: 4 | G56: 428.09 | H56: 0.07 | I56: Credit Card | J56: 1592.4948
A57: SALE55 | B57: 45589 | C57: CUST1416 | D57: PROD49 | E57: STORE11 | F57: 2 | G57: 559.71 | H57: 0.3 | I57: COD | J57: 783.594
A58: SALE56 | B58: 45282 | C58: CUST1080 | D58: PROD34 | E58: STORE6 | F58: 2 | G58: 833.7 | H58: 0.06 | I58: PayPal | J58: 1567.356
A59: SALE57 | B59: 45462 | C59: CUST1467 | D59: PROD47 | E59: STORE14 | F59: 2 | G59: 680.16 | H59: 0.28 | I59: Credit Card | J59: 979.4304
A60: SALE58 | B60: 45633 | C60: CUST1404 | D60: PROD15 | E60: STORE7 | F60: 4 | G60: 733.42 | I60: PayPal | J60: 2552.3016
A61: SALE59 | B61: 45257 | C61: CUST1367 | D61: PROD89 | E61: STORE11 | F61: 1 | G61: 996.33 | H61: 0.23 | I61: PayPal | J61: 767.1741
A62: SALE60 | B62: 45854 | C62: CUST1408 | D62: PROD31 | E62: STORE10 | F62: 1 | G62: 198.83 | H62: 0.09 | I62: COD | J62: 180.9353
A63: SALE61 | B63: 45716 | C63: CUST1239 | D63: PROD19 | E63: STORE7 | F63: 1 | G63: 374.92 | H63: 0.18 | I63: PayPal | J63: 307.4344
A64: SALE62 | B64: 45515 | C64: CUST1464 | D64: PROD93 | E64: STORE16 | F64: 1 | G64: 468.94 | H64: 0.12 | I64: Credit Card | J64: 412.6672
A65: SALE63 | B65: 45927 | C65: CUST1126 | D65: PROD89 | E65: STORE12 | F65: 2 | G65: 121.37 | H65: 0.05 | I65: Credit Card | J65: 230.603
A66: SALE64 | B66: 45914 | C66: CUST1255 | D66: PROD53 | E66: STORE10 | F66: 3 | G66: 480.06 | H66: 0.01 | I66: Credit Card
A67: SALE65 | B67: 45290 | C67: CUST1162 | D67: PROD99 | E67: STORE17 | F67: 2 | G67: 856.57 | H67: 0.24 | I67: Credit Card | J67: 1301.9864
A68: SALE66 | B68: 45213 | C68: CUST1269 | D68: PROD77 | E68: STORE2 | F68: 4 | G68: 814.25 | H68: 0.18 | I68: Credit Card | J68: 2670.74
A69: SALE67 | B69: 45255 | C69: CUST1483 | D69: PROD12 | E69: STORE2 | F69: 1 | G69: 989.17 | H69: 0.2 | I69: PayPal | J69: 791.336
A70: SALE68 | B70: 45270 | C70: CUST1372 | D70: PROD72 | E70: STORE10 | F70: 4 | G70: 62.48 | H70: 0.18 | I70: Credit Card | J70: 204.9344
A71: SALE69 | B71: 45897 | C71: CUST1423 | D71: PROD13 | E71: STORE16 | F71: 4 | G71: 561.24 | H71: 0.24 | I71: Credit Card | J71: 1706.1696
A72: SALE70 | B72: 45849 | C72: CUST1058 | D72: PROD60 | E72: STORE5 | F72: 3 | G72: 92.24 | H72: 0.28 | I72: COD
A73: SALE71 | B73: 45889 | C73: CUST1168 | D73: PROD72 | E73: STORE1 | F73: 2 | G73: 668.3 | H73: 0.07 | I73: Credit Card | J73: 1243.038
A74: SALE72 | B74: 45533 | C74: CUST1409 | D74: PROD38 | E74: STORE5 | F74: 1 | G74: 553.82 | H74: 0.09 | I74: Credit Card | J74: 503.9762
A75: SALE73 | B75: 45626 | C75: CUST1037 | D75: PROD45 | E75: STORE11 | F75: 2 | G75: 556.43 | H75: 0.13 | I75: Credit Card | J75: 968.1882
A76: SALE74 | B76: 45942 | C76: CUST1273 | D76: PROD20 | E76: STORE8 | F76: 1 | G76: 184.98 | H76: 0.1 | I76: COD | J76: 166.482
A77: SALE75 | B77: 45500 | C77: CUST1035 | D77: PROD97 | E77: STORE12 | F77: 4 | G77: 700.18 | H77: 0.23 | I77: Credit Card | J77: 2156.5544
A78: SALE76 | B78: 45285 | C78: CUST1019 | D78: PROD76 | E78: STORE10 | F78: 2 | G78: 686.31 | H78: 0.25 | I78: Credit Card | J78: 1029.465
A79: SALE77 | B79: 45800 | C79: CUST1007 | D79: PROD67 | E79: STORE15 | F79: 1 | G79: 687.82 | H79: 0.27 | I79: COD | J79: 502.1086
A80: SALE78 | B80: 45609 | C80: CUST1221 | D80: PROD83 | E80: STORE8 | F80: 2 | G80: 900.55 | H80: 0.16 | I80: Credit Card | J80: 1512.924
A81: SALE79 | B81: 45268 | C81: CUST1115 | D81: PROD21 | E81: STORE2 | F81: 1 | G81: 341.17 | H81: 0.15 | I81: Credit Card | J81: 289.9945
A82: SALE80 | B82: 45885 | C82: CUST1176 | D82: PROD52 | E82: STORE8 | F82: 1 | G82: 442.27 | H82: 0.06 | I82: COD | J82: 415.7338
A83: SALE81 | B83: 45616 | C83: CUST1253 | D83: PROD71 | E83: STORE9 | F83: 1 | G83: 363.73 | H83: 0.25 | I83: PayPal | J83: 272.7975
A84: SALE82 | B84: 45518 | C84: CUST1378 | D84: PROD91 | E84: STORE17 | F84: 2 | G84: 601.33 | H84: 0.16 | I84: PayPal | J84: 1010.2344
A85: SALE83 | B85: 45427 | C85: CUST1403 | D85: PROD17 | E85: STORE18 | F85: 4 | G85: 34.39 | H85: 0.03 | I85: PayPal | J85: 133.4332
A86: SALE84 | B86: 45268 | C86: CUST1423 | D86: PROD46 | E86: STORE17 | F86: 1 | G86: 773.57 | H86: 0.05 | I86: COD
A87: SALE85 | B87: 45282 | C87: CUST1054 | D87: PROD88 | E87: STORE7 | F87: 4 | G87: 127.1 | H87: 0.24 | I87: COD | J87: 386.384
A88: SALE86 | B88: 45545 | C88: CUST1303 | D88: PROD20 | E88: STORE3 | F88: 3 | G88: 899.58 | H88: 0.28 | I88: PayPal | J88: 1943.0928
A89: SALE87 | B89: 45755 | C89: CUST1327 | D89: PROD1 | E89: STORE10 | F89: 3 | G89: 964.39 | H89: 0.04 | I89: Credit Card | J89: 2777.4432
A90: SALE88 | B90: 45588 | C90: CUST1183 | D90: PROD38 | E90: STORE0 | F90: 2 | G90: 217.83 | H90: 0.14 | I90: PayPal | J90: 374.6676
A91: SALE89 | B91: 45848 | C91: CUST1143 | D91: PROD17 | E91: STORE1 | F91: 4 | G91: 187.71 | H91: 0.06 | I91: COD | J91: 705.7896
A92: SALE90 | B92: 45577 | C92: CUST1010 | D92: PROD33 | E92: STORE18 | F92: 2 | G92: 350.12 | H92: 0.12 | I92: COD | J92: 616.2112
A93: SALE91 | B93: 45312 | C93: CUST1406 | D93: PROD16 | E93: STORE1 | F93: 4 | G93: 102.19 | H93: 0.17 | I93: PayPal | J93: 339.2708
A94: SALE92 | B94: 45350 | C94: CUST1007 | D94: PROD86 | E94: STORE4 | F94: 1 | G94: 696.53 | H94: 0.17 | I94: Credit Card | J94: 578.1199
A95: SALE93 | B95: 45657 | C95: CUST1065 | D95: PROD19 | E95: STORE4 | F95: 2 | G95: 327.52 | H95: 0.15 | I95: PayPal | J95: 556.784
A96: SALE94 | B96: 45530 | C96: CUST1298 | D96: PROD97 | E96: STORE19 | F96: 2 | G96: 569.36 | H96: 0.01 | I96: PayPal
A97: SALE95 | B97: 45556 | C97: CUST1321 | D97: PROD99 | E97: STORE6 | F97: 2 | G97: 68.29 | H97: 0.14 | I97: COD | J97: 117.4588
A98: SALE96 | B98: 45523 | C98: CUST1244 | D98: PROD50 | E98: STORE10 | F98: 1 | G98: 842.9 | H98: 0.06 | I98: COD | J98: 792.326
A99: SALE97 | B99: 45587 | C99: CUST1287 | D99: PROD3 | E99: STORE3 | F99: 3 | G99: 751.94 | H99: 0.26 | I99: PayPal | J99: 1669.3068
A100: SALE98 | B100: 45580 | C100: CUST1131 | D100: PROD56 | E100: STORE7 | F100: 4 | G100: 476.28 | H100: 0.17 | I100: Credit Card | J100: 1581.2496
...

Sheet Observations
A2: Table/Sheet | B2: Observations | C2: Transformation Applied
A3: Customer_Dim/Product_Dim/Store_Dim/Sales_Fact | B3: Dataset
A4: Customer | B4: Some Customer Id was not in proper Formet | C4: Replaced CUST for C-
B5: Name Column was not in proper formet | C5: Used Captalized Each word using Power query
B6: Some datas spelled wrongly in Country Column | C6: Replaced with correct data
B7: Some Loyalty levels are blank | C7: Replaced blanks with unknown
B8: Descriptive Statistics | C8: Descriptive Statistics was applied using Analysys ToolPak
B9: Customer level Column added | C9: Customer level Column added using IFS condition
A10: Product | B10: Some Product Id was not in proper Formet | C10: Replaced PROD for P-
B11: Missing Datas in Cost and Stock Column | C11: Filled by calculating Average using Power query
B12: Descriptive Statistics | C12: Descriptive Statistics was applied using Analysys ToolPak
B13: Product Name Colum Splitted | C13: Product Name Colum Splitted into Description and type
A14: Store | B14: Store Category Column added | C14: Store Category Column added with IF Condition
A15: Sales | B15: Missing Datas in Total Amount Column | C15: Filled by using formula by creating a new column Amount Paid
B16: Descriptive Statistics | C16: Descriptive Statistics was applied using Analysys ToolPak
B17: Price Range Column added | C17: Price Range Column added using IFS Condition
A18: VLOOKUP | C18: Merged all 4 Tables using VLOOKUP
A19: PIVOT_LOOKUP PIVOT_LOOKUP2 | C19: Used Pivot Table for creating Charts from the VLOOKUP Sheet
A20: PIVOT TABLE_PRODUCT,STORE | C20: Used Pivot Table for creating Charts from Product and Store table
A21: PIVOT TABLE_CUST | C21: Used Pivot Table for creating Charts from Customer Table
A22: DASHBOARD | C22: All the Pivot Charts are pasted here to form a dashboard

Sheet DASHBOARD

Sheet Customer
A1: Customer_ID | B1: Name | C1: Age | D1: Gender | E1: City | F1: State | G1: Country | H1: Loyalty_Level | M1: Customer_ID | N1: Name | O1: Age | P1: Gender | Q1: City | R1: State | S1: Country | T1: Loyalty_Level | U1: Customer Level
A2: CUST1000 | B2: sheena bonilla | C2: 55 | D2: Male | E2: Donaldton | F2: North Carolina | G2: USA | M2: CUST1000 | N2: Sheena Bonilla | O2: 55 | P2: Male | Q2: Donaldton | R2: North Carolina | S2: USA | T2: unknown | U2: =_xlfn.IFS(Table1__2[[#This Row],[Age]]<=19,"Teenage",Table1__2[[#This Row],[Age]]<=24,"Students",Table1__2[[#This Row],[Age]]<=30,"Entry level Professionel",Table1__2[[#This Row],[Age]]<=60,"Experienced",Table1__2[[#This Row],[Age]]>60,"Retired") -> Experienced
A3: CUST1001 | B3: Eugene Nelson | C3: 26 | D3: Female | E3: Phillipsmouth | F3: North Dakota | G3: USA | H3: Platinum | M3: CUST1001 | N3: Eugene Nelson | O3: 26 | P3: Female | Q3: Phillipsmouth | R3: North Dakota | S3: USA | T3: Platinum | U3: =_xlfn.IFS(Table1__2[[#This Row],[Age]]<=19,"Teenage",Table1__2[[#This Row],[Age]]<=24,"Students",Table1__2[[#This Row],[Age]]<=30,"Entry level Professionel",Table1__2[[#This Row],[Age]]<=60,"Experienced",Table1__2[[#This Row],[Age]]>60,"Retired") -> Entry level Professionel | W3: Descriptive Statistics
A4: CUST1002 | B4: dr. Benjamin Price | C4: 29 | D4: Female | E4: Kylebury | F4: Alabama | G4: USA | H4: Platinum | M4: CUST1002 | N4: Dr. Benjamin Price | O4: 29 | P4: Female | Q4: Kylebury | R4: Alabama | S4: USA | T4: Platinum | U4: =_xlfn.IFS(Table1__2[[#This Row],[Age]]<=19,"Teenage",Table1__2[[#This Row],[Age]]<=24,"Students",Table1__2[[#This Row],[Age]]<=30,"Entry level Professionel",Table1__2[[#This Row],[Age]]<=60,"Experienced",Table1__2[[#This Row],[Age]]>60,"Retired") -> Entry level Professionel | W4: Age
A5: CUST1003 | B5: jeremy harris | C5: 59 | D5: Female | E5: Thomastown | F5: Ohio | G5: USA | H5: Bronze | M5: CUST1003 | N5: Jeremy Harris | O5: 59 | P5: Female | Q5: Thomastown | R5: Ohio | S5: USA | T5: Bronze | U5: =_xlfn.IFS(Table1__2[[#This Row],[Age]]<=19,"Teenage",Table1__2[[#This Row],[Age]]<=24,"Students",Table1__2[[#This Row],[Age]]<=30,"Entry level Professionel",Table1__2[[#This Row],[Age]]<=60,"Experienced",Table1__2[[#This Row],[Age]]>60,"Retired") -> Experienced
A6: CUST1004 | B6: Caroline Collins | C6: 64 | D6: Female | E6: Nicholasshire | F6: California | G6: USA | H6: Silver | M6: CUST1004 | N6: Caroline Collins | O6: 64 | P6: Female | Q6: Nicholasshire | R6: California | S6: USA | T6: Silver | U6: =_xlfn.IFS(Table1__2[[#This Row],[Age]]<=19,"Teenage",Table1__2[[#This Row],[Age]]<=24,"Students",Table1__2[[#This Row],[Age]]<=30,"Entry level Professionel",Table1__2[[#This Row],[Age]]<=60,"Experienced",Table1__2[[#This Row],[Age]]>60,"Retired") -> Retired | W6: Mean | X6: 41.562
A7: CUST1005 | B7: Christine Vaughn | C7: 24 | D7: Male | E7: East Amandamouth | F7: Oregon | G7: USA | H7: Bronze | M7: CUST1005 | N7: Christine Vaughn | O7: 24 | P7: Male | Q7: East Amandamouth | R7: Oregon | S7: USA | T7: Bronze | U7: =_xlfn.IFS(Table1__2[[#This Row],[Age]]<=19,"Teenage",Table1__2[[#This Row],[Age]]<=24,"Students",Table1__2[[#This Row],[Age]]<=30,"Entry level Professionel",Table1__2[[#This Row],[Age]]<=60,"Experienced",Table1__2[[#This Row],[Age]]>60,"Retired") -> Students | W7: Standard Error | X7: 0.61138523
A8: CUST1006 | B8: Amber Jackson | C8: 29 | D8: Female | E8: Deborahborough | F8: South Dakota | G8: USA | H8: Platinum | M8: CUST1006 | N8: Amber Jackson | O8: 29 | P8: Female | Q8: Deborahborough | R8: South Dakota | S8: USA | T8: Platinum | U8: =_xlfn.IFS(Table1__2[[#This Row],[Age]]<=19,"Teenage",Table1__2[[#This Row],[Age]]<=24,"Students",Table1__2[[#This Row],[Age]]<=30,"Entry level Professionel",Table1__2[[#This Row],[Age]]<=60,"Experienced",Table1__2[[#This Row],[Age]]>60,"Retired") -> Entry level Professionel | W8: Median | X8: 42
A9: CUST1007 | B9: Daniel Boyd | C9: 29 | D9: Female | E9: West Pamelafurt | F9: West Virginia | G9: USA | H9: Bronze | M9: CUST1007 | N9: Daniel Boyd | O9: 29 | P9: Female | Q9: West Pamelafurt | R9: West Virginia | S9: USA | T9: Bronze | U9: =_xlfn.IFS(Table1__2[[#This Row],[Age]]<=19,"Teenage",Table1__2[[#This Row],[Age]]<=24,"Students",Table1__2[[#This Row],[Age]]<=30,"Entry level Professionel",Table1__2[[#This Row],[Age]]<=60,"Experienced",Table1__2[[#This Row],[Age]]>60,"Retired") -> Entry level Professionel | W9: Mode | X9: 46
A10: CUST1008 | B10: Melissa Howard | C10: 53 | D10: Female | E10: Maynardton | F10: New Hampshire | G10: USA | H10: Gold | M10: CUST1008 | N10: Melissa Howard | O10: 53 | P10: Female | Q10: Maynardton | R10: New Hampshire | S10: USA | T10: Gold | U10: =_xlfn.IFS(Table1__2[[#This Row],[Age]]<=19,"Teenage",Table1__2[[#This Row],[Age]]<=24,"Students",Table1__2[[#This Row],[Age]]<=30,"Entry level Professionel",Table1__2[[#This Row],[Age]]<=60,"Experienced",Table1__2[[#This Row],[Age]]>60,"Retired") -> Experienced | W10: Standard Deviation | X10: 13.670989
A11: CUST1009 | B11: Ms. Maria Leach | C11: 64 | D11: Male | E11: Melissashire | F11: Pennsylvania | G11: USA | H11: Platinum | M11: CUST1009 | N11: Ms. Maria Leach | O11: 64 | P11: Male | Q11: Melissashire | R11: Pennsylvania | S11: USA | T11: Platinum | U11: =_xlfn.IFS(Table1__2[[#This Row],[Age]]<=19,"Teenage",Table1__2[[#This Row],[Age]]<=24,"Students",Table1__2[[#This Row],[Age]]<=30,"Entry level Professionel",Table1__2[[#This Row],[Age]]<=60,"Experienced",Table1__2[[#This Row],[Age]]>60,"Retired") -> Retired | W11: Sample Variance | X11: 186.89595
A12: CUST1010 | B12: Dominic Page | C12: 53 | D12: Male | E12: Port Michaelburgh | F12: Pennsylvania | G12: USA | H12: Bronze | M12: CUST1010 | N12: Dominic Page | O12: 53 | P12: Male | Q12: Port Michaelburgh | R12: Pennsylvania | S12: USA | T12: Bronze | U12: =_xlfn.IFS(Table1__2[[#This Row],[Age]]<=19,"Teenage",Table1__2[[#This Row],[Age]]<=24,"Students",Table1__2[[#This Row],[Age]]<=30,"Entry level Professionel",Table1__2[[#This Row],[Age]]<=60,"Experienced",Table1__2[[#This Row],[Age]]>60,"Retired") -> Experienced | W12: Kurtosis | X12: -1.219392
A13: CUST1011 | B13: Brian Lopez | C13: 28 | D13: Female | E13: East Krista | F13: New York | G13: USA | H13: Gold | M13: CUST1011 | N13: Brian Lopez | O13: 28 | P13: Female | Q13: East Krista | R13: New York | S13: USA | T13: Gold | U13: =_xlfn.IFS(Table1__2[[#This Row],[Age]]<=19,"Teenage",Table1__2[[#This Row],[Age]]<=24,"Students",Table1__2[[#This Row],[Age]]<=30,"Entry level Professionel",Table1__2[[#This Row],[Age]]<=60,"Experienced",Table1__2[[#This Row],[Age]]>60,"Retired") -> Entry level Professionel | W13: Skewness | X13: -0.03654853
A14: CUST1012 | B14: Kenneth Lambert | C14: 55 | D14: Female | E14: North Kathryn | F14: Kansas | G14: USA | H14: Platinum | M14: CUST1012 | N14: Kenneth Lambert | O14: 55 | P14: Female | Q14: North Kathryn | R14: Kansas | S14: USA | T14: Platinum | U14: =_xlfn.IFS(Table1__2[[#This Row],[Age]]<=19,"Teenage",Table1__2[[#This Row],[Age]]<=24,"Students",Table1__2[[#This Row],[Age]]<=30,"Entry level Professionel",Table1__2[[#This Row],[Age]]<=60,"Experienced",Table1__2[[#This Row],[Age]]>60,"Retired") -> Experienced | W14: Range | X14: 46
A15: CUST1013 | B15: Nathan Hernandez | C15: 32 | D15: Female | E15: New Becky | F15: Montana | G15: USA | H15: Silver | M15: CUST1013 | N15: Nathan Hernandez | O15: 32 | P15: Female | Q15: New Becky | R15: Montana | S15: USA | T15: Silver | U15: =_xlfn.IFS(Table1__2[[#This Row],[Age]]<=19,"Teenage",Table1__2[[#This Row],[Age]]<=24,"Students",Table1__2[[#This Row],[Age]]<=30,"Entry level Professionel",Table1__2[[#This Row],[Age]]<=60,"Experienced",Table1__2[[#This Row],[Age]]>60,"Retired") -> Experienced | W15: Minimum | X15: 18
A16: CUST1014 | B16: Ashley Cohen | C16: 53 | D16: Female | E16: Lake Kristamouth | F16: Nebraska | G16: USA | H16: Silver | M16: CUST1014 | N16: Ashley Cohen | O16: 53 | P16: Female | Q16: Lake Kristamouth | R16: Nebraska | S16: USA | T16: Silver | U16: =_xlfn.IFS(Table1__2[[#This Row],[Age]]<=19,"Teenage",Table1__2[[#This Row],[Age]]<=24,"Students",Table1__2[[#This Row],[Age]]<=30,"Entry level Professionel",Table1__2[[#This Row],[Age]]<=60,"Experienced",Table1__2[[#This Row],[Age]]>60,"Retired") -> Experienced | W16: Maximum | X16: 64
A17: CUST1015 | B17: Laura Alvarez | C17: 49 | D17: Female | E17: Lawsonhaven | F17: Washington | G17: USA | H17: Platinum | M17: CUST1015 | N17: Laura Alvarez | O17: 49 | P17: Female | Q17: Lawsonhaven | R17: Washington | S17: USA | T17: Platinum | U17: =_xlfn.IFS(Table1__2[[#This Row],[Age]]<=19,"Teenage",Table1__2[[#This Row],[Age]]<=24,"Students",Table1__2[[#This Row],[Age]]<=30,"Entry level Professionel",Table1__2[[#This Row],[Age]]<=60,"Experienced",Table1__2[[#This Row],[Age]]>60,"Retired") -> Experienced | W17: Sum | X17: 20781
A18: CUST1016 | B18: John Scott | C18: 24 | D18: Female | E18: South Christopher | F18: Pennsylvania | G18: USA | H18: Bronze | M18: CUST1016 | N18: John Scott | O18: 24 | P18: Female | Q18: South Christopher | R18: Pennsylvania | S18: USA | T18: Bronze | U18: =_xlfn.IFS(Table1__2[[#This Row],[Age]]<=19,"Teenage",Table1__2[[#This Row],[Age]]<=24,"Students",Table1__2[[#This Row],[Age]]<=30,"Entry level Professionel",Table1__2[[#This Row],[Age]]<=60,"Experienced",Table1__2[[#This Row],[Age]]>60,"Retired") -> Students | W18: Count | X18: 500
A19: CUST1017 | B19: Adam Cruz | C19: 60 | D19: Female | E19: Brandonville | F19: Georgia | G19: USA | H19: Platinum | M19: CUST1017 | N19: Adam Cruz | O19: 60 | P19: Female | Q19: Brandonville | R19: Georgia | S19: USA | T19: Platinum | U19: =_xlfn.IFS(Table1__2[[#This Row],[Age]]<=19,"Teenage",Table1__2[[#This Row],[Age]]<=24,"Students",Table1__2[[#This Row],[Age]]<=30,"Entry level Professionel",Table1__2[[#This Row],[Age]]<=60,"Experienced",Table1__2[[#This Row],[Age]]>60,"Retired") -> Experienced
A20: CUST1018 | B20: Rhonda Moss | C20: 43 | D20: Male | E20: South William | F20: Kansas | G20: USA | M20: CUST1018 | N20: Rhonda Moss | O20: 43 | P20: Male | Q20: South William | R20: Kansas | S20: USA | T20: unknown | U20: =_xlfn.IFS(Table1__2[[#This Row],[Age]]<=19,"Teenage",Table1__2[[#This Row],[Age]]<=24,"Students",Table1__2[[#This Row],[Age]]<=30,"Entry level Professionel",Table1__2[[#This Row],[Age]]<=60,"Experienced",Table1__2[[#This Row],[Age]]>60,"Retired") -> Experienced
A21: CUST1019 | B21: Michael Torres | C21: 46 | D21: Female | E21: Gonzalezfort | F21: New Jersey | G21: USA | H21: Platinum | M21: CUST1019 | N21: Michael Torres | O21: 46 | P21: Female | Q21: Gonzalezfort | R21: New Jersey | S21: USA | T21: Platinum | U21: =_xlfn.IFS(Table1__2[[#This Row],[Age]]<=19,"Teenage",Table1__2[[#This Row],[Age]]<=24,"Students",Table1__2[[#This Row],[Age]]<=30,"Entry level Professionel",Table1__2[[#This Row],[Age]]<=60,"Experienced",Table1__2[[#This Row],[Age]]>60,"Retired") -> Experienced
A22: CUST1020 | B22: Bridget Allen | C22: 59 | D22: Male | E22: Lake Shaneburgh | F22: Delaware | G22: USA | H22: Silver | M22: CUST1020 | N22: Bridget Allen | O22: 59 | P22: Male | Q22: Lake Shaneburgh | R22: Delaware | S22: USA | T22: Silver | U22: =_xlfn.IFS(Table1__2[[#This Row],[Age]]<=19,"Teenage",Table1__2[[#This Row],[Age]]<=24,"Students",Table1__2[[#This Row],[Age]]<=30,"Entry level Professionel",Table1__2[[#This Row],[Age]]<=60,"Experienced",Table1__2[[#This Row],[Age]]>60,"Retired") -> Experienced
A23: CUST1021 | B23: Jeff Martinez | C23: 36 | D23: Female | E23: Smithburgh | F23: Oklahoma | G23: USA | H23: Gold | M23: CUST1021 | N23: Jeff Martinez | O23: 36 | P23: Female | Q23: Smithburgh | R23: Oklahoma | S23: USA | T23: Gold | U23: =_xlfn.IFS(Table1__2[[#This Row],[Age]]<=19,"Teenage",Table1__2[[#This Row],[Age]]<=24,"Students",Table1__2[[#This Row],[Age]]<=30,"Entry level Professionel",Table1__2[[#This Row],[Age]]<=60,"Experienced",Table1__2[[#This Row],[Age]]>60,"Retired") -> Experienced
A24: CUST1022 | B24: paul fox | C24: 33 | D24: Female | E24: Michaelton | F24: Hawaii | G24: USA | H24: Silver | M24: CUST1022 | N24: Paul Fox | O24: 33 | P24: Female | Q24: Michaelton | R24: Hawaii | S24: USA | T24: Silver | U24: =_xlfn.IFS(Table1__2[[#This Row],[Age]]<=19,"Teenage",Table1__2[[#This Row],[Age]]<=24,"Students",Table1__2[[#This Row],[Age]]<=30,"Entry level Professionel",Table1__2[[#This Row],[Age]]<=60,"Experienced",Table1__2[[#This Row],[Age]]>60,"Retired") -> Experienced
A25: CUST1023 | B25: Jonathan Steele | C25: 52 | D25: Female | E25: Molinabury | F25: Oregon | G25: USA | H25: Silver | M25: CUST1023 | N25: Jonathan Steele | O25: 52 | P25: Female | Q25: Molinabury | R25: Oregon | S25: USA | T25: Silver | U25: =_xlfn.IFS(Table1__2[[#This Row],[Age]]<=19,"Teenage",Table1__2[[#This Row],[Age]]<=24,"Students",Table1__2[[#This Row],[Age]]<=30,"Entry level Professionel",Table1__2[[#This Row],[Age]]<=60,"Experienced",Table1__2[[#This Row],[Age]]>60,"Retired") -> Experienced
A26: CUST1024 | B26: Heather Collins | C26: 40 | D26: Male | E26: Rogerschester | F26: Idaho | G26: USA | H26: Platinum | M26: CUST1024 | N26: Heather Collins | O26: 40 | P26: Male | Q26: Rogerschester | R26: Idaho | S26: USA | T26: Platinum | U26: =_xlfn.IFS(Table1__2[[#This Row],[Age]]<=19,"Teenage",Table1__2[[#This Row],[Age]]<=24,"Students",Table1__2[[#This Row],[Age]]<=30,"Entry level Professionel",Table1__2[[#This Row],[Age]]<=60,"Experienced",Table1__2[[#This Row],[Age]]>60,"Retired") -> Experienced
A27: CUST1025 | B27: Diana Taylor | C27: 59 | D27: Female | E27: Vasqueztown | F27: California | G27: USA | H27: Bronze | M27: CUST1025 | N27: Diana Taylor | O27: 59 | P27: Female | Q27: Vasqueztown | R27: California | S27: USA | T27: Bronze | U27: =_xlfn.IFS(Table1__2[[#This Row],[Age]]<=19,"Teenage",Table1__2[[#This Row],[Age]]<=24,"Students",Table1__2[[#This Row],[Age]]<=30,"Entry level Professionel",Table1__2[[#This Row],[Age]]<=60,"Experienced",Table1__2[[#This Row],[Age]]>60,"Retired") -> Experienced
A28: CUST1026 | B28: Amber Carlson | C28: 18 | D28: Female | E28: East Michellemouth | F28: Missouri | G28: USA | H28: Gold | M28: CUST1026 | N28: Amber Carlson | O28: 18 | P28: Female | Q28: East Michellemouth | R28: Missouri | S28: USA | T28: Gold | U28: =_xlfn.IFS(Table1__2[[#This Row],[Age]]<=19,"Teenage",Table1__2[[#This Row],[Age]]<=24,"Students",Table1__2[[#This Row],[Age]]<=30,"Entry level Professionel",Table1__2[[#This Row],[Age]]<=60,"Experienced",Table1__2[[#This Row],[Age]]>60,"Retired") -> Teenage
A29: CUST1027 | B29: Leslie Johnson | C29: 31 | D29: Male | E29: Mollyshire | F29: Utah | G29: USA | M29: CUST1027 | N29: Leslie Johnson | O29: 31 | P29: Male | Q29: Mollyshire | R29: Utah | S29: USA | T29: unknown | U29: =_xlfn.IFS(Table1__2[[#This Row],[Age]]<=19,"Teenage",Table1__2[[#This Row],[Age]]<=24,"Students",Table1__2[[#This Row],[Age]]<=30,"Entry level Professionel",Table1__2[[#This Row],[Age]]<=60,"Experienced",Table1__2[[#This Row],[Age]]>60,"Retired") -> Experienced
A30: CUST1028 | B30: Joshua Ryan | C30: 27 | D30: Female | E30: New David | F30: New Jersey | G30: USA | H30: Platinum | M30: CUST1028 | N30: Joshua Ryan | O30: 27 | P30: Female | Q30: New David | R30: New Jersey | S30: USA | T30: Platinum | U30: =_xlfn.IFS(Table1__2[[#This Row],[Age]]<=19,"Teenage",Table1__2[[#This Row],[Age]]<=24,"Students",Table1__2[[#This Row],[Age]]<=30,"Entry level Professionel",Table1__2[[#This Row],[Age]]<=60,"Experienced",Table1__2[[#This Row],[Age]]>60,"Retired") -> Entry level Professionel
A31: CUST1029 | B31: David Arnold | C31: 54 | D31: Female | E31: East Jennifer | F31: California | G31: USA | H31: Silver | M31: CUST1029 | N31: David Arnold | O31: 54 | P31: Female | Q31: East Jennifer | R31: California | S31: USA | T31: Silver | U31: =_xlfn.IFS(Table1__2[[#This Row],[Age]]<=19,"Teenage",Table1__2[[#This Row],[Age]]<=24,"Students",Table1__2[[#This Row],[Age]]<=30,"Entry level Professionel",Table1__2[[#This Row],[Age]]<=60,"Experienced",Table1__2[[#This Row],[Age]]>60,"Retired") -> Experienced
A32: CUST1030 | B32: Jessica Acevedo | C32: 64 | D32: Female | E32: Amybury | F32: Pennsylvania | G32: USA | H32: Bronze | M32: CUST1030 | N32: Jessica Acevedo | O32: 64 | P32: Female | Q32: Amybury | R32: Pennsylvania | S32: USA | T32: Bronze | U32: =_xlfn.IFS(Table1__2[[#This Row],[Age]]<=19,"Teenage",Table1__2[[#This Row],[Age]]<=24,"Students",Table1__2[[#This Row],[Age]]<=30,"Entry level Professionel",Table1__2[[#This Row],[Age]]<=60,"Experienced",Table1__2[[#This Row],[Age]]>60,"Retired") -> Retired
A33: CUST1031 | B33: Sarah Vance | C33: 41 | D33: Male | E33: Johnsonville | F33: Oregon | G33: USA | H33: Silver | M33: CUST1031 | N33: Sarah Vance | O33: 41 | P33: Male | Q33: Johnsonville | R33: Oregon | S33: USA | T33: Silver | U33: =_xlfn.IFS(Table1__2[[#This Row],[Age]]<=19,"Teenage",Table1__2[[#This Row],[Age]]<=24,"Students",Table1__2[[#This Row],[Age]]<=30,"Entry level Professionel",Table1__2[[#This Row],[Age]]<=60,"Experienced",Table1__2[[#This Row],[Age]]>60,"Retired") -> Experienced
A34: CUST1032 | B34: Mike Jennings | C34: 48 | D34: Female | E34: Fostermouth | F34: Arizona | G34: USA | H34: Gold | M34: CUST1032 | N34: Mike Jennings | O34: 48 | P34: Female | Q34: Fostermouth | R34: Arizona | S34: USA | T34: Gold | U34: =_xlfn.IFS(Table1__2[[#This Row],[Age]]<=19,"Teenage",Table1__2[[#This Row],[Age]]<=24,"Students",Table1__2[[#This Row],[Age]]<=30,"Entry level Professionel",Table1__2[[#This Row],[Age]]<=60,"Experienced",Table1__2[[#This Row],[Age]]>60,"Retired") -> Experienced
A35: CUST1033 | B35: Robert Jones DDS | C35: 25 | D35: Male | E35: Tristanton | F35: Oklahoma | G35: USA | H35: Platinum | M35: CUST1033 | N35: Robert Jones Dds | O35: 25 | P35: Male | Q35: Tristanton | R35: Oklahoma | S35: USA | T35: Platinum | U35: =_xlfn.IFS(Table1__2[[#This Row],[Age]]<=19,"Teenage",Table1__2[[#This Row],[Age]]<=24,"Students",Table1__2[[#This Row],[Age]]<=30,"Entry level Professionel",Table1__2[[#This Row],[Age]]<=60,"Experienced",Table1__2[[#This Row],[Age]]>60,"Retired") -> Entry level Professionel
A36: CUST1034 | B36: Christopher Olson | C36: 27 | D36: Female | E36: West Richard | F36: Maryland | G36: USA | H36: Platinum | M36: CUST1034 | N36: Christopher Olson | O36: 27 | P36: Female | Q36: West Richard | R36: Maryland | S36: USA | T36: Platinum | U36: =_xlfn.IFS(Table1__2[[#This Row],[Age]]<=19,"Teenage",Table1__2[[#This Row],[Age]]<=24,"Students",Table1__2[[#This Row],[Age]]<=30,"Entry level Professionel",Table1__2[[#This Row],[Age]]<=60,"Experienced",Table1__2[[#This Row],[Age]]>60,"Retired") -> Entry level Professionel
A37: CUST1035 | B37: Rachel Myers | C37: 52 | D37: Male | E37: Robertberg | F37: North Dakota | G37: USA | H37: Silver | M37: CUST1035 | N37: Rachel Myers | O37: 52 | P37: Male | Q37: Robertberg | R37: North Dakota | S37: USA | T37: Silver | U37: =_xlfn.IFS(Table1__2[[#This Row],[Age]]<=19,"Teenage",Table1__2[[#This Row],[Age]]<=24,"Students",Table1__2[[#This Row],[Age]]<=30,"Entry level Professionel",Table1__2[[#This Row],[Age]]<=60,"Experienced",Table1__2[[#This Row],[Age]]>60,"Retired") -> Experienced
A38: CUST1036 | B38: Thomas Phillips | C38: 20 | D38: Female | E38: Luisfurt | F38: Georgia | G38: USA | H38: Gold | M38: CUST1036 | N38: Thomas Phillips | O38: 20 | P38: Female | Q38: Luisfurt | R38: Georgia | S38: USA | T38: Gold | U38: =_xlfn.IFS(Table1__2[[#This Row],[Age]]<=19,"Teenage",Table1__2[[#This Row],[Age]]<=24,"Students",Table1__2[[#This Row],[Age]]<=30,"Entry level Professionel",Table1__2[[#This Row],[Age]]<=60,"Experienced",Table1__2[[#This Row],[Age]]>60,"Retired") -> Students
A39: CUST1037 | B39: Christopher Carter | C39: 27 | D39: Female | E39: Brendastad | F39: South Dakota | G39: USA | M39: CUST1037 | N39: Christopher Carter | O39: 27 | P39: Female | Q39: Brendastad | R39: South Dakota | S39: USA | T39: unknown | U39: =_xlfn.IFS(Table1__2[[#This Row],[Age]]<=19,"Teenage",Table1__2[[#This Row],[Age]]<=24,"Students",Table1__2[[#This Row],[Age]]<=30,"Entry level Professionel",Table1__2[[#This Row],[Age]]<=60,"Experienced",Table1__2[[#This Row],[Age]]>60,"Retired") -> Entry level Professionel
A40: CUST1038 | B40: Deanna Simpson | C40: 35 | D40: Female | E40: Brownport | F40: North Dakota | G40: USA | H40: Bronze | M40: CUST1038 | N40: Deanna Simpson | O40: 35 | P40: Female | Q40: Brownport | R40: North Dakota | S40: USA | T40: Bronze | U40: =_xlfn.IFS(Table1__2[[#This Row],[Age]]<=19,"Teenage",Table1__2[[#This Row],[Age]]<=24,"Students",Table1__2[[#This Row],[Age]]<=30,"Entry level Professionel",Table1__2[[#This Row],[Age]]<=60,"Experienced",Table1__2[[#This Row],[Age]]>60,"Retired") -> Experienced
A41: CUST1039 | B41: Tonya Reynolds | C41: 55 | D41: Female | E41: Darleneton | F41: Michigan | G41: USA | H41: Gold | M41: CUST1039 | N41: Tonya Reynolds | O41: 55 | P41: Female | Q41: Darleneton | R41: Michigan | S41: USA | T41: Gold | U41: =_xlfn.IFS(Table1__2[[#This Row],[Age]]<=19,"Teenage",Table1__2[[#This Row],[Age]]<=24,"Students",Table1__2[[#This Row],[Age]]<=30,"Entry level Professionel",Table1__2[[#This Row],[Age]]<=60,"Experienced",Table1__2[[#This Row],[Age]]>60,"Retired") -> Experienced
A42: CUST1040 | B42: Eric Vega | C42: 50 | D42: Male | E42: Williamsonland | F42: Kansas | G42: USA | H42: Gold | M42: CUST1040 | N42: Eric Vega | O42: 50 | P42: Male | Q42: Williamsonland | R42: Kansas | S42: USA | T42: Gold | U42: =_xlfn.IFS(Table1__2[[#This Row],[Age]]<=19,"Teenage",Table1__2[[#This Row],[Age]]<=24,"Students",Table1__2[[#This Row],[Age]]<=30,"Entry level Professionel",Table1__2[[#This Row],[Age]]<=60,"Experienced",Table1__2[[#This Row],[Age]]>60,"Retired") -> Experienced
A43: CUST1041 | B43: James Gibbs | C43: 21 | D43: Male | E43: Mooneyshire | F43: Alaska | G43: USA | H43: Platinum | M43: CUST1041 | N43: James Gibbs | O43: 21 | P43: Male | Q43: Mooneyshire | R43: Alaska | S43: USA | T43: Platinum | U43: =_xlfn.IFS(Table1__2[[#This Row],[Age]]<=19,"Teenage",Table1__2[[#This Row],[Age]]<=24,"Students",Table1__2[[#This Row],[Age]]<=30,"Entry level Professionel",Table1__2[[#This Row],[Age]]<=60,"Experienced",Table1__2[[#This Row],[Age]]>60,"Retired") -> Students
A44: CUST1042 | B44: William Martin | C44: 19 | D44: Male | E44: Ryanburgh | F44: Connecticut | G44: USA | H44: Platinum | M44: CUST1042 | N44: William Martin | O44: 19 | P44: Male | Q44: Ryanburgh | R44: Connecticut | S44: USA | T44: Platinum | U44: =_xlfn.IFS(Table1__2[[#This Row],[Age]]<=19,"Teenage",Table1__2[[#This Row],[Age]]<=24,"Students",Table1__2[[#This Row],[Age]]<=30,"Entry level Professionel",Table1__2[[#This Row],[Age]]<=60,"Experienced",Table1__2[[#This Row],[Age]]>60,"Retired") -> Teenage
A45: CUST1043 | B45: Joseph Snow | C45: 45 | D45: Male | E45: South Michaelfort | F45: Vermont | G45: USA | H45: Gold | M45: CUST1043 | N45: Joseph Snow | O45: 45 | P45: Male | Q45: South Michaelfort | R45: Vermont | S45: USA | T45: Gold | U45: =_xlfn.IFS(Table1__2[[#This Row],[Age]]<=19,"Teenage",Table1__2[[#This Row],[Age]]<=24,"Students",Table1__2[[#This Row],[Age]]<=30,"Entry level Professionel",Table1__2[[#This Row],[Age]]<=60,"Experienced",Table1__2[[#This Row],[Age]]>60,"Retired") -> Experienced
A46: CUST1044 | B46: Denise Williams | C46: 34 | D46: Male | E46: Christianstad | F46: Hawaii | G46: USA | H46: Bronze | M46: CUST1044 | N46: Denise Williams | O46: 34 | P46: Male | Q46: Christianstad | R46: Hawaii | S46: USA | T46: Bronze | U46: =_xlfn.IFS(Table1__2[[#This Row],[Age]]<=19,"Teenage",Table1__2[[#This Row],[Age]]<=24,"Students",Table1__2[[#This Row],[Age]]<=30,"Entry level Professionel",Table1__2[[#This Row],[Age]]<=60,"Experienced",Table1__2[[#This Row],[Age]]>60,"Retired") -> Experienced
A47: CUST1045 | B47: Jordan Jackson DDS | C47: 54 | D47: Male | E47: North Johnview | F47: Arizona | G47: USA | H47: Gold | M47: CUST1045 | N47: Jordan Jackson Dds | O47: 54 | P47: Male | Q47: North Johnview | R47: Arizona | S47: USA | T47: Gold | U47: =_xlfn.IFS(Table1__2[[#This Row],[Age]]<=19,"Teenage",Table1__2[[#This Row],[Age]]<=24,"Students",Table1__2[[#This Row],[Age]]<=30,"Entry level Professionel",Table1__2[[#This Row],[Age]]<=60,"Experienced",Table1__2[[#This Row],[Age]]>60,"Retired") -> Experienced
A48: CUST1046 | B48: Michelle Garcia DDS | C48: 55 | D48: Female | E48: Perezbury | F48: Ohio | G48: USA | H48: Platinum | M48: CUST1046 | N48: Michelle Garcia Dds | O48: 55 | P48: Female | Q48: Perezbury | R48: Ohio | S48: USA | T48: Platinum | U48: =_xlfn.IFS(Table1__2[[#This Row],[Age]]<=19,"Teenage",Table1__2[[#This Row],[Age]]<=24,"Students",Table1__2[[#This Row],[Age]]<=30,"Entry level Professionel",Table1__2[[#This Row],[Age]]<=60,"Experienced",Table1__2[[#This Row],[Age]]>60,"Retired") -> Experienced
A49: CUST1047 | B49: Gina Knight | C49: 54 | D49: Female | E49: Lake Roberthaven | F49: Nevada | G49: USA | H49: Silver | M49: CUST1047 | N49: Gina Knight | O49: 54 | P49: Female | Q49: Lake Roberthaven | R49: Nevada | S49: USA | T49: Silver | U49: =_xlfn.IFS(Table1__2[[#This Row],[Age]]<=19,"Teenage",Table1__2[[#This Row],[Age]]<=24,"Students",Table1__2[[#This Row],[Age]]<=30,"Entry level Professionel",Table1__2[[#This Row],[Age]]<=60,"Experienced",Table1__2[[#This Row],[Age]]>60,"Retired") -> Experienced
A50: CUST1048 | B50: April Mullins | C50: 54 | D50: Male | E50: Dawsonbury | F50: North Carolina | G50: USA | H50: Platinum | M50: CUST1048 | N50: April Mullins | O50: 54 | P50: Male | Q50: Dawsonbury | R50: North Carolina | S50: USA | T50: Platinum | U50: =_xlfn.IFS(Table1__2[[#This Row],[Age]]<=19,"Teenage",Table1__2[[#This Row],[Age]]<=24,"Students",Table1__2[[#This Row],[Age]]<=30,"Entry level Professionel",Table1__2[[#This Row],[Age]]<=60,"Experienced",Table1__2[[#This Row],[Age]]>60,"Retired") -> Experienced
A51: CUST1049 | B51: Timothy Weaver | C51: 45 | D51: Female | E51: New Amy | F51: Ohio | G51: USA | H51: Gold | M51: CUST1049 | N51: Timothy Weaver | O51: 45 | P51: Female | Q51: New Amy | R51: Ohio | S51: USA | T51: Gold | U51: =_xlfn.IFS(Table1__2[[#This Row],[Age]]<=19,"Teenage",Table1__2[[#This Row],[Age]]<=24,"Students",Table1__2[[#This Row],[Age]]<=30,"Entry level Professionel",Table1__2[[#This Row],[Age]]<=60,"Experienced",Table1__2[[#This Row],[Age]]>60,"Retired") -> Experienced
... A501: CUST1499 | B501: Philip Pennington | C501: 27 | D501: Female | E501: East Valerieview | F501: Oregon | G501: USA | H501: Platinum | M501: CUST1499 | N501: Philip Pennington | O501: 27 | P501: Female | Q501: East Valerieview | R501: Oregon | S501: USA | T501: Platinum | U501: =_xlfn.IFS(Table1__2[[#This Row],[Age]]<=19,"Teenage",Table1__2[[#This Row],[Age]]<=24,"Students",Table1__2[[#This Row],[Age]]<=30,"Entry level Professionel",Table1__2[[#This Row],[Age]]<=60,"Experienced",Table1__2[[#This Row],[Age]]>60,"Retired") -> Entry level Professionel

Sheet Product
A1: Product_ID | B1: Product_Name | C1: Category | D1: Sub_Category | E1: Brand | F1: Cost | G1: Stock | K1: Product_ID | L1: Product_Description | M1: Product_Type | N1: Category | O1: Sub_Category | P1: Brand | Q1: Cost | R1: Stock
A2: PROD0 | B2: Brother Laser Printer | C2: Electronics | D2: Computer | E2: Hunt Inc | F2: 112.42 | G2: 416 | K2: PROD0 | L2: Brother Laser | M2: Printer | N2: Electronics | O2: Computer | P2: Hunt Inc | Q2: 112.42 | R2: 416
A3: PROD1 | B3: Men's Graphic T-Shirt | C3: Clothing | D3: Tops | E3: Terry-Moore | F3: 342.56 | G3: 181 | K3: PROD1 | L3: Men's Graphic | M3: T-Shirt | N3: Clothing | O3: Tops | P3: Terry-Moore | Q3: 342.56 | R3: 181
A4: PROD2 | B4: Women's Casual Hoodie | C4: Clothing | D4: Outerwear | E4: Sims Inc | G4: 352 | K4: PROD2 | L4: Women's Casual | M4: Hoodie | N4: Clothing | O4: Outerwear | P4: Sims Inc | Q4: 254.04 | R4: 352
A5: P-3 | B5: Men's Running Jacket | C5: Clothing | D5: Outerwear | E5: Pineda Ltd | F5: 364.67 | G5: 452 | K5: PROD3 | L5: Men's Running | M5: Jacket | N5: Clothing | O5: Outerwear | P5: Pineda Ltd | Q5: 364.67 | R5: 452
A6: PROD4 | B6: Women's Yoga Pants | C6: Clothing | D6: Bottoms | E6: Gonzales-Davis | F6: 306.46 | G6: 487 | K6: PROD4 | L6: Women's Yoga | M6: Pants | N6: Clothing | O6: Bottoms | P6: Gonzales-Davis | Q6: 306.46 | R6: 487
A7: PROD5 | B7: Men's Leather Belt | C7: Clothing | D7: Accessories | E7: Baldwin, Garza and Gonzalez | F7: 261 | G7: 59 | K7: PROD5 | L7: Men's Leather | M7: Belt | N7: Clothing | O7: Accessories | P7: Baldwin, Garza and Gonzalez | Q7: 261 | R7: 59
A8: PROD6 | B8: Herbal Face Moisturizer | C8: Beauty | D8: Skincare | E8: Davidson PLC | F8: 312.8 | G8: 350 | K8: PROD6 | L8: Herbal Face | M8: Moisturizer | N8: Beauty | O8: Skincare | P8: Davidson PLC | Q8: 312.8 | R8: 350 | T8: Descriptive Statistics | U8: Cost | V8: Stock
A9: PROD7 | B9: LED Table Lamp | C9: Home | D9: Lighting | E9: Harrell LLC | F9: 218.86 | G9: 170 | K9: PROD7 | L9: LED Table | M9: Lamp | N9: Home | O9: Lighting | P9: Harrell LLC | Q9: 218.86 | R9: 170
A10: PROD8 | B10: Wireless Bluetooth Earbuds | C10: Electronics | D10: Audio | E10: Perez-Johnston | F10: 439.07 | G10: 142 | K10: PROD8 | L10: Wireless Bluetooth | M10: Earbuds | N10: Electronics | O10: Audio | P10: Perez-Johnston | Q10: 439.07 | R10: 142 | T10: Mean | U10: 254.0434 | V10: 273.48
A11: PROD9 | B11: Adjustable Dumbbell Set | C11: Sports | D11: Fitness | E11: Hill PLC | F11: 495.72 | G11: 323 | K11: PROD9 | L11: Adjustable Dumbbell | M11: Set | N11: Sports | O11: Fitness | P11: Hill PLC | Q11: 495.72 | R11: 323 | T11: Standard Error | U11: 13.082031 | V11: 12.995046
A12: PROD10 | B12: Ceramic Kitchen Bowl Set | C12: Home | D12: Kitchen | E12: Hamilton Group | F12: 298.86 | G12: 308 | K12: PROD10 | L12: Ceramic Kitchen Bowl | M12: Set | N12: Home | O12: Kitchen | P12: Hamilton Group | Q12: 298.86 | R12: 308 | T12: Median | U12: 253.685 | V12: 273
A13: PROD11 | B13: HD Smart TV Stick | C13: Electronics | D13: Accessories | E13: Gibson, Hobbs and Weaver | F13: 449.4 | K13: PROD11 | L13: HD Smart TV | M13: Stick | N13: Electronics | O13: Accessories | P13: Gibson, Hobbs and Weaver | Q13: 449.4 | R13: 273 | T13: Mode | U13: 254.04 | V13: 273
A14: PROD12 | B14: Hair Strengthening Shampoo | C14: Beauty | D14: Haircare | E14: Rice LLC | F14: 115.82 | G14: 460 | K14: PROD12 | L14: Hair Strengthening | M14: Shampoo | N14: Beauty | O14: Haircare | P14: Rice LLC | Q14: 115.82 | R14: 460 | T14: Standard Deviation | U14: 130.82031 | V14: 129.95046
A15: PROD13 | B15: USB-C Fast Charger | C15: Electronics | D15: Accessories | E15: Dawson-Perkins | F15: 242.23 | G15: 453 | K15: PROD13 | L15: USB-C Fast | M15: Charger | N15: Electronics | O15: Accessories | P15: Dawson-Perkins | Q15: 242.23 | R15: 453 | T15: Sample Variance | U15: 17113.953 | V15: 16887.121
A16: PROD14 | B16: Decorative Wall Mirror | C16: Home | D16: Decor | E16: Luna, Anderson and Bowman | F16: 48.01 | G16: 439 | K16: PROD14 | L16: Decorative Wall | M16: Mirror | N16: Home | O16: Decor | P16: Luna, Anderson and Bowman | Q16: 48.01 | R16: 439 | T16: Kurtosis | U16: -0.94910609 | V16: -1.1529465
A17: PROD15 | B17: 4K Home Projector | C17: Electronics | D17: Appliances | E17: Thomas LLC | F17: 465.34 | G17: 301 | K17: PROD15 | L17: 4K Home | M17: Projector | N17: Electronics | O17: Appliances | P17: Thomas LLC | Q17: 465.34 | R17: 301 | T17: Skewness | U17: 0.052323422 | V17: -0.0073416277
A18: P-16 | B18: Beard Grooming Kit | C18: Beauty | D18: Grooming | E18: Erickson-Green | F18: 337.42 | G18: 256 | K18: PROD16 | L18: Beard Grooming | M18: Kit | N18: Beauty | O18: Grooming | P18: Erickson-Green | Q18: 337.42 | R18: 256 | T18: Range | U18: 478.41 | V18: 439
A19: PROD17 | B19: Soccer Training Cone Set | C19: Sports | D19: Accessories | E19: Ford, Murphy and Wilson | F19: 144.53 | G19: 367 | K19: PROD17 | L19: Soccer Training Cone | M19: Set | N19: Sports | O19: Accessories | P19: Ford, Murphy and Wilson | Q19: 144.53 | R19: 367 | T19: Minimum | U19: 17.31 | V19: 57
A20: PROD18 | B20: Women's Denim Jeans | C20: Clothing | D20: Bottoms | E20: Guerra-Hendrix | G20: 343 | K20: PROD18 | L20: Women's Denim | M20: Jeans | N20: Clothing | O20: Bottoms | P20: Guerra-Hendrix | Q20: 254.04 | R20: 343 | T20: Maximum | U20: 495.72 | V20: 496
A21: PROD19 | B21: Knee Support Brace | C21: Sports | D21: Equipment | E21: May-Reese | F21: 21.34 | G21: 65 | K21: PROD19 | L21: Knee Support | M21: Brace | N21: Sports | O21: Equipment | P21: May-Reese | Q21: 21.34 | R21: 65 | T21: Sum | U21: 25404.34 | V21: 27348
A22: PROD20 | B22: Outdoor Sports Water Bottle | C22: Sports | D22: Accessories | E22: Soto-Ellis | F22: 131.51 | K22: PROD20 | L22: Outdoor Sports Water | M22: Bottle | N22: Sports | O22: Accessories | P22: Soto-Ellis | Q22: 131.51 | R22: 273 | T22: Count | U22: 100 | V22: 100
A23: PROD21 | B23: Multi-Purpose Storage Box | C23: Home | D23: Storage | E23: Gardner-Montes | F23: 123.46 | G23: 76 | K23: PROD21 | L23: Multi-Purpose Storage | M23: Box | N23: Home | O23: Storage | P23: Gardner-Montes | Q23: 123.46 | R23: 76
A24: PROD22 | B24: Carbon Fiber Tennis Racket | C24: Sports | D24: Equipment | E24: Flores, Pineda and Rodriguez | F24: 484.62 | G24: 432 | K24: PROD22 | L24: Carbon Fiber Tennis | M24: Racket | N24: Sports | O24: Equipment | P24: Flores, Pineda and Rodriguez | Q24: 484.62 | R24: 432
A25: PROD23 | B25: Men's Formal Shirt | C25: Clothing | D25: Tops | E25: Moon, Mora and Santos | G25: 360 | K25: PROD23 | L25: Men's Formal | M25: Shirt | N25: Clothing | O25: Tops | P25: Moon, Mora and Santos | Q25: 254.04 | R25: 360
A26: PROD24 | B26: Foldable Camping Chair | C26: Sports | D26: Outdoor | E26: Cook Ltd | F26: 166.06 | G26: 340 | K26: PROD24 | L26: Foldable Camping | M26: Chair | N26: Sports | O26: Outdoor | P26: Cook Ltd | Q26: 166.06 | R26: 340
A27: PROD25 | B27: Women's Scarf Set | C27: Clothing | D27: Accessories | E27: Brown and Sons | F27: 174.02 | G27: 268 | K27: PROD25 | L27: Women's Scarf | M27: Set | N27: Clothing | O27: Accessories | P27: Brown and Sons | Q27: 174.02 | R27: 268
A28: PROD26 | B28: Wireless Bluetooth Speaker | C28: Electronics | D28: Audio | E28: Reed-Schmidt | F28: 322.41 | G28: 213 | K28: PROD26 | L28: Wireless Bluetooth | M28: Speaker | N28: Electronics | O28: Audio | P28: Reed-Schmidt | Q28: 322.41 | R28: 213
A29: PROD27 | B29: Decorative Floor Vase | C29: Home | D29: Decor | E29: Khan, Jones and Paul | G29: 378 | K29: PROD27 | L29: Decorative Floor | M29: Vase | N29: Home | O29: Decor | P29: Khan, Jones and Paul | Q29: 254.04 | R29: 378
A30: PROD28 | B30: Sports Stopwatch Timer | C30: Sports | D30: Accessories | E30: Burns-Hansen | F30: 38.76 | G30: 137 | K30: PROD28 | L30: Sports Stopwatch | M30: Timer | N30: Sports | O30: Accessories | P30: Burns-Hansen | Q30: 38.76 | R30: 137
A31: PROD29 | B31: Fabric Sofa Throw Blanket | C31: Home | D31: Decor | E31: Hoffman Group | F31: 218.48 | G31: 276 | K31: PROD29 | L31: Fabric Sofa Throw | M31: Blanket | N31: Home | O31: Decor | P31: Hoffman Group | Q31: 218.48 | R31: 276
A32: PROD30 | B32: Stainless Steel Cutlery Set | C32: Home | D32: Kitchen | E32: Stevens, Fernandez and Martin | F32: 19.52 | G32: 57 | K32: PROD30 | L32: Stainless Steel Cutlery | M32: Set | N32: Home | O32: Kitchen | P32: Stevens, Fernandez and Martin | Q32: 19.52 | R32: 57
A33: PROD31 | B33: Basketball | C33: Sports | D33: Team Sports | E33: Nolan-Snow | F33: 204.39 | G33: 281 | K33: PROD31 | L33: Basketball | M33: Ball | N33: Sports | O33: Team Sports | P33: Nolan-Snow | Q33: 204.39 | R33: 281
A34: PROD32 | B34: Vitamin C Face Serum | C34: Beauty | D34: Skincare | E34: Griffin Ltd | F34: 283.83 | G34: 244 | K34: PROD32 | L34: Vitamin C Face | M34: Serum | N34: Beauty | O34: Skincare | P34: Griffin Ltd | Q34: 283.83 | R34: 244
A35: PROD33 | B35: Modern Wall Clock | C35: Home | D35: Decor | E35: Weiss-Watson | F35: 179.77 | G35: 305 | K35: PROD33 | L35: Modern Wall | M35: Clock | N35: Home | O35: Decor | P35: Weiss-Watson | Q35: 179.77 | R35: 305
A36: PROD34 | B36: Gaming Mechanical Keyboard | C36: Electronics | D36: Computer | E36: Lucero LLC | F36: 419.28 | G36: 86 | K36: PROD34 | L36: Gaming Mechanical | M36: Keyboard | N36: Electronics | O36: Computer | P36: Lucero LLC | Q36: 419.28 | R36: 86
A37: PROD35 | B37: Bedroom Table Lamp | C37: Home | D37: Lighting | E37: Jones LLC | F37: 382.22 | G37: 329 | K37: PROD35 | L37: Bedroom Table | M37: Lamp | N37: Home | O37: Lighting | P37: Jones LLC | Q37: 382.22 | R37: 329
A38: PROD36 | B38: Women's Summer Dress | C38: Clothing | D38: Tops | E38: Smith-Mills | F38: 223.43 | G38: 154 | K38: PROD36 | L38: Women's Summer | M38: Dress | N38: Clothing | O38: Tops | P38: Smith-Mills | Q38: 223.43 | R38: 154
A39: PROD37 | B39: Men's Casual Sneakers | C39: Clothing | D39: Footwear | E39: Hogan-Lee | F39: 353.47 | G39: 214 | K39: PROD37 | L39: Men's Casual | M39: Sneakers | N39: Clothing | O39: Footwear | P39: Hogan-Lee | Q39: 353.47 | R39: 214
A40: PROD38 | B40: Sports Water Hydration Pack | C40: Sports | D40: Outdoor | E40: Sims-Smith | F40: 135.61 | G40: 394 | K40: PROD38 | L40: Sports Water Hydration | M40: Pack | N40: Sports | O40: Outdoor | P40: Sims-Smith | Q40: 135.61 | R40: 394
A41: PROD39 | B41: Portable Power Bank | C41: Electronics | D41: Mobile | E41: Cummings and Sons | F41: 326.06 | G41: 301 | K41: PROD39 | L41: Portable Power | M41: Bank | N41: Electronics | O41: Mobile | P41: Cummings and Sons | Q41: 326.06 | R41: 301
... A48: PROD46 | B48: Men's Winter Jacket | C48: Clothing | D48: Outerwear | E48: Kelly, Smith and Perez | F48: 167.34 | G48: 296 | K48: PROD46 | L48: Men's Winter | M48: Jacket | N48: Clothing | O48: Outerwear | P48: Kelly, Smith and Perez | Q48: 167.34 | R48: 296
A49: PROD47 | B49: Makeup Brush Set | C49: Beauty | D49: Makeup | E49: Cook Inc | G49: 431 | K49: PROD47 | L49: Makeup Brush | M49: Set | N49: Beauty | O49: Makeup | P49: Cook Inc | Q49: 254.04 | R49: 431
A50: PROD48 | B50: Car Dashboard Phone Holder | C50: Electronics | D50: Accessories | E50: Byrd, Stewart and Valdez | F50: 177.98 | G50: 103 | K50: PROD48 | L50: Car Dashboard Phone | M50: Holder | N50: Electronics | O50: Accessories | P50: Byrd, Stewart and Valdez | Q50: 177.98 | R50: 103
A51: PROD49 | B51: Men's Roll-On Perfume | C51: Beauty | D51: Fragrance | E51: Sullivan and Sons | F51: 43.29 | G51: 267 | K51: PROD49 | L51: Men's Roll-On | M51: Perfume | N51: Beauty | O51: Fragrance | P51: Sullivan and Sons | Q51: 43.29 | R51: 267
A52: PROD50 | B52: Boxing Hand Wraps | C52: Sports | D52: Fitness | E52: Smith-King | F52: 190.29 | G52: 260 | K52: PROD50 | L52: Boxing Hand | M52: Wraps | N52: Sports | O52: Fitness | P52: Smith-King | Q52: 190.29 | R52: 260
A53: PROD51 | B53: HDMI Cable – 2m | C53: Electronics | D53: Accessories | E53: Bautista, Green and Hale | F53: 88.49 | G53: 246 | K53: PROD51 | L53: HDMI Cable – | M53: 2m | N53: Electronics | O53: Accessories | P53: Bautista, Green and Hale | Q53: 88.49 | R53: 246
A54: PROD52 | B54: Rugby Ball | C54: Sports | D54: Team Sports | E54: Harris Inc | F54: 212.26 | G54: 82 | K54: PROD52 | L54: Rugby | M54: Ball | N54: Sports | O54: Team Sports | P54: Harris Inc | Q54: 212.26 | R54: 82
A55: PROD53 | B55: Men's Track Pants | C55: Clothing | D55: Bottoms | E55: Hamilton, Woods and Walker | F55: 386.56 | G55: 125 | K55: PROD53 | L55: Men's Track | M55: Pants | N55: Clothing | O55: Bottoms | P55: Hamilton, Woods and Walker | Q55: 386.56 | R55: 125
A56: PROD54 | B56: Sports Stopwatch Pro | C56: Sports | D56: Accessories | E56: Thompson-French | F56: 434.84 | G56: 185 | K56: PROD54 | L56: Sports Stopwatch | M56: Pro | N56: Sports | O56: Accessories | P56: Thompson-French | Q56: 434.84 | R56: 185
A57: PROD55 | B57: Ceramic Plant Pot | C57: Home | D57: Decor | E57: Hatfield, Baird and Torres | F57: 81.75 | K57: PROD55 | L57: Ceramic Plant | M57: Pot | N57: Home | O57: Decor | P57: Hatfield, Baird and Torres | Q57: 81.75 | R57: 273
A58: PROD56 | B58: Premium Blanket Throw | C58: Home | D58: Decor | E58: Hernandez, Kennedy and Porter | F58: 461.47 | G58: 190 | K58: PROD56 | L58: Premium Blanket | M58: Throw | N58: Home | O58: Decor | P58: Hernandez, Kennedy and Porter | Q58: 461.47 | R58: 190
A59: PROD57 | B59: Foam Roller | C59: Sports | D59: Fitness | E59: Atkinson, Camacho and Oliver | F59: 30.62 | G59: 138 | K59: PROD57 | L59: Foam | M59: Roller | N59: Sports | O59: Fitness | P59: Atkinson, Camacho and Oliver | Q59: 30.62 | R59: 138
A60: PROD58 | B60: Womens Cotton Scarf | C60: Clothing | D60: Accessories | E60: Shepherd-Gould | F60: 113.83 | G60: 485 | K60: PROD58 | L60: Womens Cotton | M60: Scarf | N60: Clothing | O60: Accessories | P60: Shepherd-Gould | Q60: 113.83 | R60: 485
A61: PROD59 | B61: Men's Hair Styling Gel | C61: Beauty | D61: Haircare | E61: Cline-Mccarthy | F61: 17.31 | G61: 399 | K61: PROD59 | L61: Men's Hair Styling | M61: Gel | N61: Beauty | O61: Haircare | P61: Cline-Mccarthy | Q61: 17.31 | R61: 399
A62: PROD60 | B62: Luxury Perfume Spray | C62: Beauty | D62: Fragrance | E62: Gibson, Green and Lopez | F62: 482.75 | G62: 444 | K62: PROD60 | L62: Luxury Perfume | M62: Spray | N62: Beauty | O62: Fragrance | P62: Gibson, Green and Lopez | Q62: 482.75 | R62: 444
A63: PROD61 | B63: Tennis Ball 3-Pack | C63: Sports | D63: Equipment | E63: Lopez LLC | F63: 103.45 | G63: 465 | K63: PROD61 | L63: Tennis Ball | M63: 3-Pack | N63: Sports | O63: Equipment | P63: Lopez LLC | Q63: 103.45 | R63: 465
A64: PROD62 | B64: Laptop Cooling Pad | C64: Electronics | D64: Computer | E64: Murray, Gould and Ware | F64: 86.42 | G64: 222 | K64: PROD62 | L64: Laptop Cooling | M64: Pad | N64: Electronics | O64: Computer | P64: Murray, Gould and Ware | Q64: 86.42 | R64: 222
A65: PROD63 | B65: Organic Sunscreen Lotion | C65: Beauty | D65: Skincare | E65: Anderson-Riley | F65: 266.86 | G65: 458 | K65: PROD63 | L65: Organic Sunscreen | M65: Lotion | N65: Beauty | O65: Skincare | P65: Anderson-Riley | Q65: 266.86 | R65: 458
A66: PROD64 | B66: Matte Lipstick Set | C66: Beauty | D66: Makeup | E66: Zhang Inc | F66: 299.11 | G66: 118 | K66: PROD64 | L66: Matte Lipstick | M66: Set | N66: Beauty | O66: Makeup | P66: Zhang Inc | Q66: 299.11 | R66: 118
A67: PROD65 | B67: Adjustable Dumbbells 20kg | C67: Sports | D67: Fitness | E67: Montgomery, Benton and Miller | F67: 240.63 | G67: 423 | K67: PROD65 | L67: Adjustable Dumbbells | M67: 20kg | N67: Sports | O67: Fitness | P67: Montgomery, Benton and Miller | Q67: 240.63 | R67: 423
A68: PROD66 | B68: Women's Hair Dryer Brush | C68: Beauty | D68: Haircare | E68: Torres, Spencer and Potter | F68: 340.39 | G68: 177 | K68: PROD66 | L68: Women's Hair Dryer | M68: Brush | N68: Beauty | O68: Haircare | P68: Torres, Spencer and Potter | Q68: 340.39 | R68: 177
A69: PROD67 | B69: Smart LED Light Strip | C69: Electronics | D69: Accessories | E69: Flores-Davis | F69: 349.17 | G69: 476 | K69: PROD67 | L69: Smart LED Light | M69: Strip | N69: Electronics | O69: Accessories | P69: Flores-Davis | Q69: 349.17 | R69: 476
... A84: PROD82 | B84: Fitness Resistance Bands | C84: Sports | D84: Fitness | E84: Reese-Watson | F84: 152.92 | G84: 281 | K84: PROD82 | L84: Fitness Resistance | M84: Bands | N84: Sports | O84: Fitness | P84: Reese-Watson | Q84: 152.92 | R84: 281
A85: PROD83 | B85: Hydrating Face Cleanser | C85: Beauty | D85: Skincare | E85: Butler Group | G85: 159 | K85: PROD83 | L85: Hydrating Face | M85: Cleanser | N85: Beauty | O85: Skincare | P85: Butler Group | Q85: 254.04 | R85: 159
A86: PROD84 | B86: Wooden Bookshelf | C86: Home | D86: Furniture | E86: Collins-Stephenson | F86: 388.46 | G86: 208 | K86: PROD84 | L86: Wooden | M86: Bookshelf | N86: Home | O86: Furniture | P86: Collins-Stephenson | Q86: 388.46 | R86: 208
A87: PROD85 | B87: Women's Beanie Hat | C87: Clothing | D87: Accessories | E87: Richardson-Carrillo | F87: 119.57 | G87: 210 | K87: PROD85 | L87: Women's Beanie | M87: Hat | N87: Clothing | O87: Accessories | P87: Richardson-Carrillo | Q87: 119.57 | R87: 210
A88: PROD86 | B88: Kitchen Cutting Board | C88: Home | D88: Kitchen | E88: Taylor, Dodson and Johnston | F88: 176.07 | G88: 82 | K88: PROD86 | L88: Kitchen Cutting | M88: Board | N88: Home | O88: Kitchen | P88: Taylor, Dodson and Johnston | Q88: 176.07 | R88: 82
A89: PROD87 | B89: LED Bedside Lamp | C89: Home | D89: Lighting | E89: Aguilar, Horton and Lewis | F89: 371.38 | G89: 220 | K89: PROD87 | L89: LED Bedside | M89: Lamp | N89: Home | O89: Lighting | P89: Aguilar, Horton and Lewis | Q89: 371.38 | R89: 220
A90: PROD88 | B90: Sports Wrist Sweatbands | C90: Sports | D90: Accessories | E90: Olsen-Daniels | F90: 131.24 | G90: 232 | K90: PROD88 | L90: Sports Wrist | M90: Sweatbands | N90: Sports | O90: Accessories | P90: Olsen-Daniels | Q90: 131.24 | R90: 232
A91: PROD89 | B91: Face Foundation Kit | C91: Beauty | D91: Makeup | E91: Taylor-Elliott | F91: 183.04 | G91: 457 | K91: PROD89 | L91: Face Foundation | M91: Kit | N91: Beauty | O91: Makeup | P91: Taylor-Elliott | Q91: 183.04 | R91: 457
A92: PROD90 | B92: Gaming Mouse Pad XL | C92: Electronics | D92: Accessories | E92: Sharp, Taylor and Rodriguez | F92: 340.14 | G92: 361 | K92: PROD90 | L92: Gaming Mouse Pad | M92: XL | N92: Electronics | O92: Accessories | P92: Sharp, Taylor and Rodriguez | Q92: 340.14 | R92: 361
A93: PROD91 | B93: Women's High Heels | C93: Clothing | D93: Footwear | E93: Smith-Charles | F93: 438.25 | G93: 496 | K93: PROD91 | L93: Women's High | M93: Heels | N93: Clothing | O93: Footwear | P93: Smith-Charles | Q93: 438.25 | R93: 496
A94: PROD92 | B94: Microwave Oven | C94: Home | D94: Appliances | E94: Green, Powell and Palmer | F94: 447.43 | G94: 191 | K94: PROD92 | L94: Microwave | M94: Oven | N94: Home | O94: Appliances | P94: Green, Powell and Palmer | Q94: 447.43 | R94: 191
A95: PROD93 | B95: USB-C Laptop Charger | C95: Electronics | D95: Computer | E95: Martin LLC | F95: 377.52 | G95: 485 | K95: PROD93 | L95: USB-C Laptop | M95: Charger | N95: Electronics | O95: Computer | P95: Martin LLC | Q95: 377.52 | R95: 485
A96: PROD94 | B96: Vitamin E Body Lotion | C96: Beauty | D96: Skincare | E96: Hoffman-Williams | F96: 358.47 | G96: 213 | K96: PROD94 | L96: Vitamin E Body | M96: Lotion | N96: Beauty | O96: Skincare | P96: Hoffman-Williams | Q96: 358.47 | R96: 213
A97: PROD95 | B97: Sports Stopwatch Basic | C97: Sports | D97: Accessories | E97: Wilson Group | F97: 60.65 | G97: 75 | K97: PROD95 | L97: Sports Stopwatch | M97: Basic | N97: Sports | O97: Accessories | P97: Wilson Group | Q97: 60.65 | R97: 75
... A101: PROD99 | B101: Stainless Steel Cookware Set | C101: Home | D101: Kitchen | E101: Campbell Ltd | F101: 201.41 | G101: 146 | K101: PROD99 | L101: Stainless Steel Cookware | M101: Set | N101: Home | O101: Kitchen | P101: Campbell Ltd | Q101: 201.41 | R101: 146

Sheet Store
A1: Store_ID | B1: Store_Name | C1: Region | D1: City | E1: Store_Type | F1: Store Category
A2: STORE0 | B2: Rivera-Warner | C2: East | D2: Washingtonfurt | E2: Flagship | F2: =IF(Table7[[#This Row],[Store_Type]]="Online","Digital Store","Physical Store") -> Physical Store
A3: STORE1 | B3: Martinez, Adkins and Johnson | C3: North | D3: Danielmouth | E3: Flagship | F3: =IF(Table7[[#This Row],[Store_Type]]="Online","Digital Store","Physical Store") -> Physical Store
A4: STORE2 | B4: Black-Horn | C4: South | D4: North Nancyview | E4: Outlet | F4: =IF(Table7[[#This Row],[Store_Type]]="Online","Digital Store","Physical Store") -> Physical Store
A5: STORE3 | B5: Johnson-Wright | C5: North | D5: Hoodberg | E5: Outlet | F5: =IF(Table7[[#This Row],[Store_Type]]="Online","Digital Store","Physical Store") -> Physical Store
A6: STORE4 | B6: Alexander Group | C6: South | D6: Port Sharon | E6: Online | F6: =IF(Table7[[#This Row],[Store_Type]]="Online","Digital Store","Physical Store") -> Digital Store
A7: STORE5 | B7: Gray Ltd | C7: North | D7: New Michaelchester | E7: Outlet | F7: =IF(Table7[[#This Row],[Store_Type]]="Online","Digital Store","Physical Store") -> Physical Store
A8: STORE6 | B8: Benson-Elliott | C8: East | D8: Port Josephberg | E8: Online | F8: =IF(Table7[[#This Row],[Store_Type]]="Online","Digital Store","Physical Store") -> Digital Store
A9: STORE7 | B9: Martinez-Mullins | C9: South | D9: Williamsfurt | E9: Online | F9: =IF(Table7[[#This Row],[Store_Type]]="Online","Digital Store","Physical Store") -> Digital Store
A10: STORE8 | B10: Bean, Jones and Park | C10: West | D10: Thompsonborough | E10: Online | F10: =IF(Table7[[#This Row],[Store_Type]]="Online","Digital Store","Physical Store") -> Digital Store
A11: STORE9 | B11: Moore, Padilla and Butler | C11: South | D11: East Johnstad | E11: Flagship | F11: =IF(Table7[[#This Row],[Store_Type]]="Online","Digital Store","Physical Store") -> Physical Store
A12: STORE10 | B12: Hill, Wagner and Ballard | C12: East | D12: East Davidville | E12: Online | F12: =IF(Table7[[#This Row],[Store_Type]]="Online","Digital Store","Physical Store") -> Digital Store
A13: STORE11 | B13: Aguirre-Keller | C13: South | D13: Lake Michael | E13: Online | F13: =IF(Table7[[#This Row],[Store_Type]]="Online","Digital Store","Physical Store") -> Digital Store
... A21: STORE19 | B21: Mann-Austin | C21: East | D21: Vasquezborough | E21: Online | F21: =IF(Table7[[#This Row],[Store_Type]]="Online","Digital Store","Physical Store") -> Digital Store

Sheet Sales
A1: Sales_ID | B1: Order_Date | C1: Customer_ID | D1: Product_ID | E1: Store_ID | F1: Quantity | G1: Unit_Price | H1: Discount | I1: Payment_Type | J1: Total_Amount | O1: Sales_ID | P1: Order_Date | Q1: Customer_ID | R1: Product_ID | S1: Store_ID | T1: Quantity | U1: Unit_Price | V1: Discount | W1: Payment_Type | X1: Total_Amount | Y1: Amount_Paid | Z1: Price Range
A2: SALE0 | B2: 45480 | C2: CUST1409 | D2: PROD97 | E2: STORE3 | F2: 1 | G2: 218.04 | H2: 0.09 | I2: Credit Card | J2: 198.4164 | O2: SALE0 | P2: 45480 | Q2: CUST1409 | R2: PROD97 | S2: STORE3 | T2: 1 | U2: 218.04 | V2: 0.09 | W2: Credit Card | X2: 198.4164 | Y2: 198.4164 | Z2: =_xlfn.IFS(Table8_1[[#This Row],[Unit_Price]]<500,"Low Price",Table8_1[[#This Row],[Unit_Price]]<2000,"Medium Price",Table8_1[[#This Row],[Unit_Price]]>=2000, "High Price") -> Low Price
A3: SALE1 | B3: 45285 | C3: CUST1467 | D3: PROD74 | E3: STORE17 | F3: 3 | G3: 104.47 | H3: 0.27 | I3: PayPal | J3: 228.7893 | O3: SALE1 | P3: 45285 | Q3: CUST1467 | R3: PROD74 | S3: STORE17 | T3: 3 | U3: 104.47 | V3: 0.27 | W3: PayPal | X3: 228.7893 | Y3: 228.7893 | Z3: =_xlfn.IFS(Table8_1[[#This Row],[Unit_Price]]<500,"Low Price",Table8_1[[#This Row],[Unit_Price]]<2000,"Medium Price",Table8_1[[#This Row],[Unit_Price]]>=2000, "High Price") -> Low Price
A4: SALE2 | B4: 45446 | C4: CUST1056 | D4: PROD49 | E4: STORE8 | F4: 4 | G4: 914.05 | H4: 0.25 | I4: Credit Card | J4: 2742.15 | O4: SALE2 | P4: 45446 | Q4: CUST1056 | R4: PROD49 | S4: STORE8 | T4: 4 | U4: 914.05 | V4: 0.25 | W4: Credit Card | X4: 2742.15 | Y4: 2742.15 | Z4: =_xlfn.IFS(Table8_1[[#This Row],[Unit_Price]]<500,"Low Price",Table8_1[[#This Row],[Unit_Price]]<2000,"Medium Price",Table8_1[[#This Row],[Unit_Price]]>=2000, "High Price") -> Medium Price
A5: SALE3 | B5: 45259 | C5: CUST1346 | D5: PROD76 | E5: STORE8 | F5: 1 | G5: 921.51 | H5: 0.16 | I5: COD | J5: 774.0684 | O5: SALE3 | P5: 45259 | Q5: CUST1346 | R5: PROD76 | S5: STORE8 | T5: 1 | U5: 921.51 | V5: 0.16 | W5: COD | X5: 774.0684 | Y5: 774.0684 | Z5: =_xlfn.IFS(Table8_1[[#This Row],[Unit_Price]]<500,"Low Price",Table8_1[[#This Row],[Unit_Price]]<2000,"Medium Price",Table8_1[[#This Row],[Unit_Price]]>=2000, "High Price") -> Medium Price
A6: SALE4 | B6: 45297 | C6: CUST1493 | D6: PROD59 | E6: STORE5 | F6: 3 | G6: 745.3 | H6: 0.18 | I6: Credit Card | J6: 1833.438 | O6: SALE4 | P6: 45297 | Q6: CUST1493 | R6: PROD59 | S6: STORE5 | T6: 3 | U6: 745.3 | V6: 0.18 | W6: Credit Card | X6: 1833.438 | Y6: 1833.438 | Z6: =_xlfn.IFS(Table8_1[[#This Row],[Unit_Price]]<500,"Low Price",Table8_1[[#This Row],[Unit_Price]]<2000,"Medium Price",Table8_1[[#This Row],[Unit_Price]]>=2000, "High Price") -> Medium Price | AB6: Descriptive Statistics | AC6: Unit Price | AD6: Amount_Paid
A7: SALE5 | B7: 45499 | C7: CUST1116 | D7: PROD15 | E7: STORE7 | F7: 3 | G7: 147.01 | H7: 0.19 | I7: COD | J7: 357.2343 | O7: SALE5 | P7: 45499 | Q7: CUST1116 | R7: PROD15 | S7: STORE7 | T7: 3 | U7: 147.01 | V7: 0.19 | W7: COD | X7: 357.2343 | Y7: 357.2343 | Z7: =_xlfn.IFS(Table8_1[[#This Row],[Unit_Price]]<500,"Low Price",Table8_1[[#This Row],[Unit_Price]]<2000,"Medium Price",Table8_1[[#This Row],[Unit_Price]]>=2000, "High Price") -> Low Price
A8: SALE6 | B8: 45850 | C8: CUST1016 | D8: PROD56 | E8: STORE4 | F8: 2 | G8: 785.31 | H8: 0.15 | I8: PayPal | J8: 1335.027 | O8: SALE6 | P8: 45850 | Q8: CUST1016 | R8: PROD56 | S8: STORE4 | T8: 2 | U8: 785.31 | V8: 0.15 | W8: PayPal | X8: 1335.027 | Y8: 1335.027 | Z8: =_xlfn.IFS(Table8_1[[#This Row],[Unit_Price]]<500,"Low Price",Table8_1[[#This Row],[Unit_Price]]<2000,"Medium Price",Table8_1[[#This Row],[Unit_Price]]>=2000, "High Price") -> Medium Price | AB8: Mean | AC8: 513.98476 | AD8: 1086.5655
A9: SALE7 | B9: 45248 | C9: CUST1152 | D9: PROD70 | E9: STORE8 | F9: 4 | G9: 342.39 | H9: 0.23 | I9: PayPal | J9: 1054.5612 | O9: SALE7 | P9: 45248 | Q9: CUST1152 | R9: PROD70 | S9: STORE8 | T9: 4 | U9: 342.39 | V9: 0.23 | W9: PayPal | X9: 1054.5612 | Y9: 1054.5612 | Z9: =_xlfn.IFS(Table8_1[[#This Row],[Unit_Price]]<500,"Low Price",Table8_1[[#This Row],[Unit_Price]]<2000,"Medium Price",Table8_1[[#This Row],[Unit_Price]]>=2000, "High Price") -> Low Price | AB9: Standard Error | AC9: 6.3077953 | AD9: 18.301042
A10: SALE8 | B10: 45781 | C10: CUST1187 | D10: PROD99 | E10: STORE5 | G10: 448.25 | H10: 0.07 | I10: PayPal | J10: 1250.6175 | O10: SALE8 | P10: 45781 | Q10: CUST1187 | R10: PROD99 | S10: STORE5 | T10: 2 | U10: 448.25 | V10: 0.07 | W10: PayPal | X10: 1250.6175 | Y10: 833.745 | Z10: =_xlfn.IFS(Table8_1[[#This Row],[Unit_Price]]<500,"Low Price",Table8_1[[#This Row],[Unit_Price]]<2000,"Medium Price",Table8_1[[#This Row],[Unit_Price]]>=2000, "High Price") -> Low Price | AB10: Median | AC10: 522.43 | AD10: 868.7182
A11: SALE9 | B11: 45869 | C11: CUST1464 | D11: PROD33 | E11: STORE0 | F11: 2 | G11: 873.17 | H11: 0.23 | I11: PayPal | J11: 1344.6818 | O11: SALE9 | P11: 45869 | Q11: CUST1464 | R11: PROD33 | S11: STORE0 | T11: 2 | U11: 873.17 | V11: 0.23 | W11: PayPal | X11: 1344.6818 | Y11: 1344.6818 | Z11: =_xlfn.IFS(Table8_1[[#This Row],[Unit_Price]]<500,"Low Price",Table8_1[[#This Row],[Unit_Price]]<2000,"Medium Price",Table8_1[[#This Row],[Unit_Price]]>=2000, "High Price") -> Medium Price | AB11: Mode | AC11: 513.98 | AD11: #N/A
A12: SALE10 | B12: 45335 | C12: CUST1065 | D12: PROD24 | E12: STORE14 | F12: 1 | G12: 278.63 | H12: 0.07 | I12: Credit Card | J12: 259.1259 | O12: SALE10 | P12: 45335 | Q12: CUST1065 | R12: PROD24 | S12: STORE14 | T12: 1 | U12: 278.63 | V12: 0.07 | W12: Credit Card | X12: 259.1259 | Y12: 259.1259 | Z12: =_xlfn.IFS(Table8_1[[#This Row],[Unit_Price]]<500,"Low Price",Table8_1[[#This Row],[Unit_Price]]<2000,"Medium Price",Table8_1[[#This Row],[Unit_Price]]>=2000, "High Price") -> Low Price | AB12: Standard Deviation | AC12: 282.09318 | AD12: 818.4475
A13: SALE11 | B13: 45801 | C13: CUST1320 | D13: PROD39 | E13: STORE1 | F13: 4 | G13: 286.92 | H13: 0.17 | I13: Credit Card | J13: 952.5744 | O13: SALE11 | P13: 45801 | Q13: CUST1320 | R13: PROD39 | S13: STORE1 | T13: 4 | U13: 286.92 | V13: 0.17 | W13: Credit Card | X13: 952.5744 | Y13: 952.5744 | Z13: =_xlfn.IFS(Table8_1[[#This Row],[Unit_Price]]<500,"Low Price",Table8_1[[#This Row],[Unit_Price]]<2000,"Medium Price",Table8_1[[#This Row],[Unit_Price]]>=2000, "High Price") -> Low Price | AB13: Sample Variance | AC13: 79576.564 | AD13: 669856.3
A14: SALE12 | B14: 45528 | C14: CUST1237 | D14: PROD88 | E14: STORE4 | F14: 4 | G14: 644.58 | H14: 0.01 | I14: Credit Card | J14: 2552.5368 | O14: SALE12 | P14: 45528 | Q14: CUST1237 | R14: PROD88 | S14: STORE4 | T14: 4 | U14: 644.58 | V14: 0.01 | W14: Credit Card | X14: 2552.5368 | Y14: 2552.5368 | Z14: =_xlfn.IFS(Table8_1[[#This Row],[Unit_Price]]<500,"Low Price",Table8_1[[#This Row],[Unit_Price]]<2000,"Medium Price",Table8_1[[#This Row],[Unit_Price]]>=2000, "High Price") -> Medium Price | AB14: Kurtosis | AC14: -1.1897064 | AD14: 0.059308206
A15: SALE13 | B15: 45875 | C15: CUST1443 | D15: PROD34 | E15: STORE16 | F15: 2 | G15: 316.9 | H15: 0.3 | I15: PayPal | J15: 443.66 | O15: SALE13 | P15: 45875 | Q15: CUST1443 | R15: PROD34 | S15: STORE16 | T15: 2 | U15: 316.9 | V15: 0.3 | W15: PayPal | X15: 443.66 | Y15: 443.66 | Z15: =_xlfn.IFS(Table8_1[[#This Row],[Unit_Price]]<500,"Low Price",Table8_1[[#This Row],[Unit_Price]]<2000,"Medium Price",Table8_1[[#This Row],[Unit_Price]]>=2000, "High Price") -> Low Price | AB15: Skewness | AC15: -0.036768714 | AD15: 0.88189426
A16: SALE14 | B16: 45829 | C16: CUST1348 | D16: PROD24 | E16: STORE15 | F16: 4 | G16: 403.47 | H16: 0.29 | I16: PayPal | J16: 1145.8548 | O16: SALE14 | P16: 45829 | Q16: CUST1348 | R16: PROD24 | S16: STORE15 | T16: 4 | U16: 403.47 | V16: 0.29 | W16: PayPal | X16: 1145.8548 | Y16: 1145.8548 | Z16: =_xlfn.IFS(Table8_1[[#This Row],[Unit_Price]]<500,"Low Price",Table8_1[[#This Row],[Unit_Price]]<2000,"Medium Price",Table8_1[[#This Row],[Unit_Price]]>=2000, "High Price") -> Low Price | AB16: Range | AC16: 979.8 | AD16: 3889.7838
A17: SALE15 | B17: 45636 | C17: CUST1435 | D17: PROD36 | E17: STORE9 | G17: 871.34 | H17: 0.04 | I17: COD | J17: 2509.4592 | O17: SALE15 | P17: 45636 | Q17: CUST1435 | R17: PROD36 | S17: STORE9 | T17: 2 | U17: 871.34 | V17: 0.04 | W17: COD | X17: 2509.4592 | Y17: 1672.9728 | Z17: =_xlfn.IFS(Table8_1[[#This Row],[Unit_Price]]<500,"Low Price",Table8_1[[#This Row],[Unit_Price]]<2000,"Medium Price",Table8_1[[#This Row],[Unit_Price]]>=2000, "High Price") -> Medium Price | AB17: Minimum | AC17: 20.09 | AD17: 18.459
A18: SALE16 | B18: 45913 | C18: CUST1276 | D18: PROD65 | E18: STORE19 | F18: 2 | G18: 451.98 | H18: 0.25 | I18: Credit Card | J18: 677.97 | O18: SALE16 | P18: 45913 | Q18: CUST1276 | R18: PROD65 | S18: STORE19 | T18: 2 | U18: 451.98 | V18: 0.25 | W18: Credit Card | X18: 677.97 | Y18: 677.97 | Z18: =_xlfn.IFS(Table8_1[[#This Row],[Unit_Price]]<500,"Low Price",Table8_1[[#This Row],[Unit_Price]]<2000,"Medium Price",Table8_1[[#This Row],[Unit_Price]]>=2000, "High Price") -> Low Price | AB18: Maximum | AC18: 999.89 | AD18: 3908.2428
A19: SALE17 | B19: 45637 | C19: CUST1079 | D19: PROD27 | E19: STORE4 | F19: 2 | G19: 502.69 | H19: 0.23 | I19: Credit Card | J19: 774.1426 | O19: SALE17 | P19: 45637 | Q19: CUST1079 | R19: PROD27 | S19: STORE4 | T19: 2 | U19: 502.69 | V19: 0.23 | W19: Credit Card | X19: 774.1426 | Y19: 774.1426 | Z19: =_xlfn.IFS(Table8_1[[#This Row],[Unit_Price]]<500,"Low Price",Table8_1[[#This Row],[Unit_Price]]<2000,"Medium Price",Table8_1[[#This Row],[Unit_Price]]>=2000, "High Price") -> Medium Price | AB19: Sum | AC19: 1027969.5 | AD19: 2173131
A20: SALE18 | B20: 45517 | C20: CUST1094 | D20: PROD39 | E20: STORE4 | F20: 2 | G20: 559.23 | H20: 0.25 | I20: COD | J20: 838.845 | O20: SALE18 | P20: 45517 | Q20: CUST1094 | R20: PROD39 | S20: STORE4 | T20: 2 | U20: 559.23 | V20: 0.25 | W20: COD | X20: 838.845 | Y20: 838.845 | Z20: =_xlfn.IFS(Table8_1[[#This Row],[Unit_Price]]<500,"Low Price",Table8_1[[#This Row],[Unit_Price]]<2000,"Medium Price",Table8_1[[#This Row],[Unit_Price]]>=2000, "High Price") -> Medium Price | AB20: Count | AC20: 2000 | AD20: 2000
A21: SALE19 | B21: 45369 | C21: CUST1239 | D21: PROD60 | E21: STORE13 | F21: 4 | H21: 0.04 | I21: COD | J21: 1782.4512 | O21: SALE19 | P21: 45369 | Q21: CUST1239 | R21: PROD60 | S21: STORE13 | T21: 4 | U21: 513.98 | V21: 0.04 | W21: COD | X21: 1782.4512 | Y21: 1973.6832 | Z21: =_xlfn.IFS(Table8_1[[#This Row],[Unit_Price]]<500,"Low Price",Table8_1[[#This Row],[Unit_Price]]<2000,"Medium Price",Table8_1[[#This Row],[Unit_Price]]>=2000, "High Price") -> Medium Price
A22: SALE20 | B22: 45843 | C22: CUST1144 | D22: PROD72 | E22: STORE17 | F22: 3 | G22: 986.04 | H22: 0.27 | I22: COD | J22: 2159.4276 | O22: SALE20 | P22: 45843 | Q22: CUST1144 | R22: PROD72 | S22: STORE17 | T22: 3 | U22: 986.04 | V22: 0.27 | W22: COD | X22: 2159.4276 | Y22: 2159.4276 | Z22: =_xlfn.IFS(Table8_1[[#This Row],[Unit_Price]]<500,"Low Price",Table8_1[[#This Row],[Unit_Price]]<2000,"Medium Price",Table8_1[[#This Row],[Unit_Price]]>=2000, "High Price") -> Medium Price
A23: SALE21 | B23: 45447 | C23: CUST1396 | D23: PROD43 | E23: STORE18 | F23: 1 | G23: 589.56 | H23: 0.22 | I23: Credit Card | J23: 459.8568 | O23: SALE21 | P23: 45447 | Q23: CUST1396 | R23: PROD43 | S23: STORE18 | T23: 1 | U23: 589.56 | V23: 0.22 | W23: Credit Card | X23: 459.8568 | Y23: 459.8568 | Z23: =_xlfn.IFS(Table8_1[[#This Row],[Unit_Price]]<500,"Low Price",Table8_1[[#This Row],[Unit_Price]]<2000,"Medium Price",Table8_1[[#This Row],[Unit_Price]]>=2000, "High Price") -> Medium Price
A24: SALE22 | B24: 45394 | C24: CUST1476 | D24: PROD69 | E24: STORE10 | F24: 3 | G24: 979.42 | H24: 0.03 | I24: PayPal | J24: 2850.1122 | O24: SALE22 | P24: 45394 | Q24: CUST1476 | R24: PROD69 | S24: STORE10 | T24: 3 | U24: 979.42 | V24: 0.03 | W24: PayPal | X24: 2850.1122 | Y24: 2850.1122 | Z24: =_xlfn.IFS(Table8_1[[#This Row],[Unit_Price]]<500,"Low Price",Table8_1[[#This Row],[Unit_Price]]<2000,"Medium Price",Table8_1[[#This Row],[Unit_Price]]>=2000, "High Price") -> Medium Price
A25: SALE23 | B25: 45466 | C25: CUST1368 | D25: PROD12 | E25: STORE8 | F25: 1 | G25: 719.28 | H25: 0.08 | I25: Credit Card | J25: 661.7376 | O25: SALE23 | P25: 45466 | Q25: CUST1368 | R25: PROD12 | S25: STORE8 | T25: 1 | U25: 719.28 | V25: 0.08 | W25: Credit Card | X25: 661.7376 | Y25: 661.7376 | Z25: =_xlfn.IFS(Table8_1[[#This Row],[Unit_Price]]<500,"Low Price",Table8_1[[#This Row],[Unit_Price]]<2000,"Medium Price",Table8_1[[#This Row],[Unit_Price]]>=2000, "High Price") -> Medium Price
A26: SALE24 | B26: 45908 | C26: CUST1186 | D26: PROD67 | E26: STORE6 | F26: 3 | G26: 77.6 | H26: 0.07 | I26: Credit Card | J26: 216.504 | O26: SALE24 | P26: 45908 | Q26: CUST1186 | R26: PROD67 | S26: STORE6 | T26: 3 | U26: 77.6 | V26: 0.07 | W26: Credit Card | X26: 216.504 | Y26: 216.504 | Z26: =_xlfn.IFS(Table8_1[[#This Row],[Unit_Price]]<500,"Low Price",Table8_1[[#This Row],[Unit_Price]]<2000,"Medium Price",Table8_1[[#This Row],[Unit_Price]]>=2000, "High Price") -> Low Price
A27: SALE25 | B27: 45552 | C27: CUST1381 | D27: PROD5 | E27: STORE3 | F27: 4 | G27: 852.71 | H27: 0.14 | I27: PayPal | J27: 2933.3224 | O27: SALE25 | P27: 45552 | Q27: CUST1381 | R27: PROD5 | S27: STORE3 | T27: 4 | U27: 852.71 | V27: 0.14 | W27: PayPal | X27: 2933.3224 | Y27: 2933.3224 | Z27: =_xlfn.IFS(Table8_1[[#This Row],[Unit_Price]]<500,"Low Price",Table8_1[[#This Row],[Unit_Price]]<2000,"Medium Price",Table8_1[[#This Row],[Unit_Price]]>=2000, "High Price") -> Medium Price
A28: SALE26 | B28: 45294 | C28: CUST1213 | D28: PROD98 | E28: STORE8 | F28: 4 | G28: 156.16 | I28: Credit Card | J28: 599.6544 | O28: SALE26 | P28: 45294 | Q28: CUST1213 | R28: PROD98 | S28: STORE8 | T28: 4 | U28: 156.16 | V28: 0.14 | W28: Credit Card | X28: 599.6544 | Y28: 537.1904 | Z28: =_xlfn.IFS(Table8_1[[#This Row],[Unit_Price]]<500,"Low Price",Table8_1[[#This Row],[Unit_Price]]<2000,"Medium Price",Table8_1[[#This Row],[Unit_Price]]>=2000, "High Price") -> Low Price
A29: SALE27 | B29: 45710 | C29: CUST1200 | D29: PROD77 | E29: STORE8 | F29: 3 | G29: 815.49 | H29: 0.17 | I29: Credit Card | J29: 2030.5701 | O29: SALE27 | P29: 45710 | Q29: CUST1200 | R29: PROD77 | S29: STORE8 | T29: 3 | U29: 815.49 | V29: 0.17 | W29: Credit Card | X29: 2030.5701 | Y29: 2030.5701 | Z29: =_xlfn.IFS(Table8_1[[#This Row],[Unit_Price]]<500,"Low Price",Table8_1[[#This Row],[Unit_Price]]<2000,"Medium Price",Table8_1[[#This Row],[Unit_Price]]>=2000, "High Price") -> Medium Price
A30: SALE28 | B30: 45923 | C30: CUST1148 | D30: PROD13 | E30: STORE2 | F30: 2 | G30: 74.21 | H30: 0.11 | I30: PayPal | J30: 132.0938 | O30: SALE28 | P30: 45923 | Q30: CUST1148 | R30: PROD13 | S30: STORE2 | T30: 2 | U30: 74.21 | V30: 0.11 | W30: PayPal | X30: 132.0938 | Y30: 132.0938 | Z30: =_xlfn.IFS(Table8_1[[#This Row],[Unit_Price]]<500,"Low Price",Table8_1[[#This Row],[Unit_Price]]<2000,"Medium Price",Table8_1[[#This Row],[Unit_Price]]>=2000, "High Price") -> Low Price
A31: SALE29 | B31: 45302 | C31: CUST1348 | D31: PROD99 | E31: STORE3 | G31: 451.67 | H31: 0.15 | I31: Credit Card | J31: 1535.678 | O31: SALE29 | P31: 45302 | Q31: CUST1348 | R31: PROD99 | S31: STORE3 | T31: 2 | U31: 451.67 | V31: 0.15 | W31: Credit Card | X31: 1535.678 | Y31: 767.839 | Z31: =_xlfn.IFS(Table8_1[[#This Row],[Unit_Price]]<500,"Low Price",Table8_1[[#This Row],[Unit_Price]]<2000,"Medium Price",Table8_1[[#This Row],[Unit_Price]]>=2000, "High Price") -> Low Price
A32: SALE30 | B32: 45217 | C32: CUST1028 | D32: PROD5 | E32: STORE19 | F32: 1 | G32: 429.38 | H32: 0.13 | I32: PayPal | J32: 373.5606 | O32: SALE30 | P32: 45217 | Q32: CUST1028 | R32: PROD5 | S32: STORE19 | T32: 1 | U32: 429.38 | V32: 0.13 | W32: PayPal | X32: 373.5606 | Y32: 373.5606 | Z32: =_xlfn.IFS(Table8_1[[#This Row],[Unit_Price]]<500,"Low Price",Table8_1[[#This Row],[Unit_Price]]<2000,"Medium Price",Table8_1[[#This Row],[Unit_Price]]>=2000, "High Price") -> Low Price
A33: SALE31 | B33: 45593 | C33: CUST1412 | D33: PROD53 | E33: STORE12 | F33: 2 | G33: 148.96 | H33: 0.03 | I33: COD | J33: 288.9824 | O33: SALE31 | P33: 45593 | Q33: CUST1412 | R33: PROD53 | S33: STORE12 | T33: 2 | U33: 148.96 | V33: 0.03 | W33: COD | X33: 288.9824 | Y33: 288.9824 | Z33: =_xlfn.IFS(Table8_1[[#This Row],[Unit_Price]]<500,"Low Price",Table8_1[[#This Row],[Unit_Price]]<2000,"Medium Price",Table8_1[[#This Row],[Unit_Price]]>=2000, "High Price") -> Low Price
A34: SALE32 | B34: 45597 | C34: CUST1398 | D34: PROD75 | E34: STORE8 | F34: 4 | G34: 313.83 | H34: 0.08 | I34: Credit Card | J34: 1154.8944 | O34: SALE32 | P34: 45597 | Q34: CUST1398 | R34: PROD75 | S34: STORE8 | T34: 4 | U34: 313.83 | V34: 0.08 | W34: Credit Card | X34: 1154.8944 | Y34: 1154.8944 | Z34: =_xlfn.IFS(Table8_1[[#This Row],[Unit_Price]]<500,"Low Price",Table8_1[[#This Row],[Unit_Price]]<2000,"Medium Price",Table8_1[[#This Row],[Unit_Price]]>=2000, "High Price") -> Low Price
A35: SALE33 | B35: 45620 | C35: CUST1453 | D35: PROD12 | E35: STORE6 | F35: 2 | G35: 717.31 | H35: 0.15 | I35: Credit Card | J35: 1219.427 | O35: SALE33 | P35: 45620 | Q35: CUST1453 | R35: PROD12 | S35: STORE6 | T35: 2 | U35: 717.31 | V35: 0.15 | W35: Credit Card | X35: 1219.427 | Y35: 1219.427 | Z35: =_xlfn.IFS(Table8_1[[#This Row],[Unit_Price]]<500,"Low Price",Table8_1[[#This Row],[Unit_Price]]<2000,"Medium Price",Table8_1[[#This Row],[Unit_Price]]>=2000, "High Price") -> Medium Price
A36: SALE34 | B36: 45215 | C36: CUST1344 | D36: PROD79 | E36: STORE1 | G36: 873.22 | H36: 0.18 | I36: Credit Card | J36: 2148.1212 | O36: SALE34 | P36: 45215 | Q36: CUST1344 | R36: PROD79 | S36: STORE1 | T36: 2 | U36: 873.22 | V36: 0.18 | W36: Credit Card | X36: 2148.1212 | Y36: 1432.0808 | Z36: =_xlfn.IFS(Table8_1[[#This Row],[Unit_Price]]<500,"Low Price",Table8_1[[#This Row],[Unit_Price]]<2000,"Medium Price",Table8_1[[#This Row],[Unit_Price]]>=2000, "High Price") -> Medium Price
A37: SALE35 | B37: 45878 | C37: CUST1218 | D37: PROD16 | E37: STORE3 | F37: 4 | G37: 109.36 | H37: 0.19 | I37: COD | J37: 354.3264 | O37: SALE35 | P37: 45878 | Q37: CUST1218 | R37: PROD16 | S37: STORE3 | T37: 4 | U37: 109.36 | V37: 0.19 | W37: COD | X37: 354.3264 | Y37: 354.3264 | Z37: =_xlfn.IFS(Table8_1[[#This Row],[Unit_Price]]<500,"Low Price",Table8_1[[#This Row],[Unit_Price]]<2000,"Medium Price",Table8_1[[#This Row],[Unit_Price]]>=2000, "High Price") -> Low Price
A38: SALE36 | B38: 45635 | C38: CUST1086 | D38: PROD5 | E38: STORE7 | F38: 3 | G38: 559.52 | H38: 0.16 | I38: PayPal | J38: 1409.9904 | O38: SALE36 | P38: 45635 | Q38: CUST1086 | R38: PROD5 | S38: STORE7 | T38: 3 | U38: 559.52 | V38: 0.16 | W38: PayPal | X38: 1409.9904 | Y38: 1409.9904 | Z38: =_xlfn.IFS(Table8_1[[#This Row],[Unit_Price]]<500,"Low Price",Table8_1[[#This Row],[Unit_Price]]<2000,"Medium Price",Table8_1[[#This Row],[Unit_Price]]>=2000, "High Price") -> Medium Price
A39: SALE37 | B39: 45329 | C39: CUST1492 | D39: PROD10 | E39: STORE17 | F39: 3 | G39: 121.76 | H39: 0.27 | I39: PayPal | J39: 266.6544 | O39: SALE37 | P39: 45329 | Q39: CUST1492 | R39: PROD10 | S39: STORE17 | T39: 3 | U39: 121.76 | V39: 0.27 | W39: PayPal | X39: 266.6544 | Y39: 266.6544 | Z39: =_xlfn.IFS(Table8_1[[#This Row],[Unit_Price]]<500,"Low Price",Table8_1[[#This Row],[Unit_Price]]<2000,"Medium Price",Table8_1[[#This Row],[Unit_Price]]>=2000, "High Price") -> Low Price
A40: SALE38 | B40: 45378 | C40: CUST1189 | D40: PROD33 | E40: STORE13 | F40: 4 | G40: 735.32 | H40: 0.06 | I40: COD | J40: 2764.8032 | O40: SALE38 | P40: 45378 | Q40: CUST1189 | R40: PROD33 | S40: STORE13 | T40: 4 | U40: 735.32 | V40: 0.06 | W40: COD | X40: 2764.8032 | Y40: 2764.8032 | Z40: =_xlfn.IFS(Table8_1[[#This Row],[Unit_Price]]<500,"Low Price",Table8_1[[#This Row],[Unit_Price]]<2000,"Medium Price",Table8_1[[#This Row],[Unit_Price]]>=2000, "High Price") -> Medium Price
A41: SALE39 | B41: 45264 | C41: CUST1431 | D41: PROD94 | E41: STORE3 | F41: 2 | G41: 600.73 | H41: 0.08 | I41: Credit Card | J41: 1105.3432 | O41: SALE39 | P41: 45264 | Q41: CUST1431 | R41: PROD94 | S41: STORE3 | T41: 2 | U41: 600.73 | V41: 0.08 | W41: Credit Card | X41: 1105.3432 | Y41: 1105.3432 | Z41: =_xlfn.IFS(Table8_1[[#This Row],[Unit_Price]]<500,"Low Price",Table8_1[[#This Row],[Unit_Price]]<2000,"Medium Price",Table8_1[[#This Row],[Unit_Price]]>=2000, "High Price") -> Medium Price
A42: SALE40 | B42: 45486 | C42: CUST1072 | D42: PROD26 | E42: STORE19 | F42: 2 | G42: 873.86 | H42: 0.07 | I42: COD | J42: 1625.3796 | O42: SALE40 | P42: 45486 | Q42: CUST1072 | R42: PROD26 | S42: STORE19 | T42: 2 | U42: 873.86 | V42: 0.07 | W42: COD | X42: 1625.3796 | Y42: 1625.3796 | Z42: =_xlfn.IFS(Table8_1[[#This Row],[Unit_Price]]<500,"Low Price",Table8_1[[#This Row],[Unit_Price]]<2000,"Medium Price",Table8_1[[#This Row],[Unit_Price]]>=2000, "High Price") -> Medium Price
A43: SALE41 | B43: 45241 | C43: CUST1302 | D43: PROD23 | E43: STORE8 | F43: 3 | G43: 342.47 | H43: 0.08 | I43: PayPal | J43: 945.2172 | O43: SALE41 | P43: 45241 | Q43: CUST1302 | R43: PROD23 | S43: STORE8 | T43: 3 | U43: 342.47 | V43: 0.08 | W43: PayPal | X43: 945.2172 | Y43: 945.2172 | Z43: =_xlfn.IFS(Table8_1[[#This Row],[Unit_Price]]<500,"Low Price",Table8_1[[#This Row],[Unit_Price]]<2000,"Medium Price",Table8_1[[#This Row],[Unit_Price]]>=2000, "High Price") -> Low Price
A44: SALE42 | B44: 45649 | C44: CUST1335 | D44: PROD29 | E44: STORE9 | F44: 2 | G44: 915.15 | H44: 0.16 | I44: PayPal | J44: 1537.452 | O44: SALE42 | P44: 45649 | Q44: CUST1335 | R44: PROD29 | S44: STORE9 | T44: 2 | U44: 915.15 | V44: 0.16 | W44: PayPal | X44: 1537.452 | Y44: 1537.452 | Z44: =_xlfn.IFS(Table8_1[[#This Row],[Unit_Price]]<500,"Low Price",Table8_1[[#This Row],[Unit_Price]]<2000,"Medium Price",Table8_1[[#This Row],[Unit_Price]]>=2000, "High Price") -> Medium Price
A45: SALE43 | B45: 45677 | C45: CUST1084 | D45: PROD33 | E45: STORE17 | G45: 863.11 | H45: 0.28 | I45: PayPal | J45: 1864.3176 | O45: SALE43 | P45: 45677 | Q45: CUST1084 | R45: PROD33 | S45: STORE17 | T45: 2 | U45: 863.11 | V45: 0.28 | W45: PayPal | X45: 1864.3176 | Y45: 1242.8784 | Z45: =_xlfn.IFS(Table8_1[[#This Row],[Unit_Price]]<500,"Low Price",Table8_1[[#This Row],[Unit_Price]]<2000,"Medium Price",Table8_1[[#This Row],[Unit_Price]]>=2000, "High Price") -> Medium Price
A46: SALE44 | B46: 45538 | C46: CUST1203 | D46: PROD43 | E46: STORE12 | F46: 2 | G46: 209.32 | H46: 0.23 | I46: COD | J46: 322.3528 | O46: SALE44 | P46: 45538 | Q46: CUST1203 | R46: PROD43 | S46: STORE12 | T46: 2 | U46: 209.32 | V46: 0.23 | W46: COD | X46: 322.3528 | Y46: 322.3528 | Z46: =_xlfn.IFS(Table8_1[[#This Row],[Unit_Price]]<500,"Low Price",Table8_1[[#This Row],[Unit_Price]]<2000,"Medium Price",Table8_1[[#This Row],[Unit_Price]]>=2000, "High Price") -> Low Price
A47: SALE45 | B47: 45606 | C47: CUST1470 | D47: PROD59 | E47: STORE8 | F47: 4 | G47: 288.6 | H47: 0.09 | I47: PayPal | J47: 1050.504 | O47: SALE45 | P47: 45606 | Q47: CUST1470 | R47: PROD59 | S47: STORE8 | T47: 4 | U47: 288.6 | V47: 0.09 | W47: PayPal | X47: 1050.504 | Y47: 1050.504 | Z47: =_xlfn.IFS(Table8_1[[#This Row],[Unit_Price]]<500,"Low Price",Table8_1[[#This Row],[Unit_Price]]<2000,"Medium Price",Table8_1[[#This Row],[Unit_Price]]>=2000, "High Price") -> Low Price
A48: SALE46 | B48: 45570 | C48: CUST1070 | D48: PROD78 | E48: STORE16 | F48: 1 | G48: 418.69 | H48: 0.06 | I48: PayPal | J48: 393.5686 | O48: SALE46 | P48: 45570 | Q48: CUST1070 | R48: PROD78 | S48: STORE16 | T48: 1 | U48: 418.69 | V48: 0.06 | W48: PayPal | X48: 393.5686 | Y48: 393.5686 | Z48: =_xlfn.IFS(Table8_1[[#This Row],[Unit_Price]]<500,"Low Price",Table8_1[[#This Row],[Unit_Price]]<2000,"Medium Price",Table8_1[[#This Row],[Unit_Price]]>=2000, "High Price") -> Low Price
A49: SALE47 | B49: 45466 | C49: CUST1008 | D49: PROD30 | E49: STORE11 | F49: 1 | G49: 135.78 | H49: 0.14 | I49: PayPal | J49: 116.7708 | O49: SALE47 | P49: 45466 | Q49: CUST1008 | R49: PROD30 | S49: STORE11 | T49: 1 | U49: 135.78 | V49: 0.14 | W49: PayPal | X49: 116.7708 | Y49: 116.7708 | Z49: =_xlfn.IFS(Table8_1[[#This Row],[Unit_Price]]<500,"Low Price",Table8_1[[#This Row],[Unit_Price]]<2000,"Medium Price",Table8_1[[#This Row],[Unit_Price]]>=2000, "High Price") -> Low Price
A50: SALE48 | B50: 45218 | C50: CUST1203 | D50: PROD44 | E50: STORE17 | F50: 1 | G50: 517.13 | H50: 0.28 | I50: Credit Card | J50: 372.3336 | O50: SALE48 | P50: 45218 | Q50: CUST1203 | R50: PROD44 | S50: STORE17 | T50: 1 | U50: 517.13 | V50: 0.28 | W50: Credit Card | X50: 372.3336 | Y50: 372.3336 | Z50: =_xlfn.IFS(Table8_1[[#This Row],[Unit_Price]]<500,"Low Price",Table8_1[[#This Row],[Unit_Price]]<2000,"Medium Price",Table8_1[[#This Row],[Unit_Price]]>=2000, "High Price") -> Medium Price
A51: SALE49 | B51: 45607 | C51: CUST1420 | D51: PROD21 | E51: STORE16 | F51: 2 | G51: 384.66 | H51: 0.08 | I51: COD | J51: 707.7744 | O51: SALE49 | P51: 45607 | Q51: CUST1420 | R51: PROD21 | S51: STORE16 | T51: 2 | U51: 384.66 | V51: 0.08 | W51: COD | X51: 707.7744 | Y51: 707.7744 | Z51: =_xlfn.IFS(Table8_1[[#This Row],[Unit_Price]]<500,"Low Price",Table8_1[[#This Row],[Unit_Price]]<2000,"Medium Price",Table8_1[[#This Row],[Unit_Price]]>=2000, "High Price") -> Low Price
A52: SALE50 | B52: 45291 | C52: CUST1070 | D52: PROD52 | E52: STORE9 | F52: 3 | G52: 83.7 | H52: 0.24 | I52: PayPal | J52: 190.836 | O52: SALE50 | P52: 45291 | Q52: CUST1070 | R52: PROD52 | S52: STORE9 | T52: 3 | U52: 83.7 | V52: 0.24 | W52: PayPal | X52: 190.836 | Y52: 190.836 | Z52: =_xlfn.IFS(Table8_1[[#This Row],[Unit_Price]]<500,"Low Price",Table8_1[[#This Row],[Unit_Price]]<2000,"Medium Price",Table8_1[[#This Row],[Unit_Price]]>=2000, "High Price") -> Low Price
A53: SALE51 | B53: 45689 | C53: CUST1142 | D53: PROD69 | E53: STORE7 | F53: 3 | G53: 76.57 | H53: 0.26 | I53: Credit Card | J53: 169.9854 | O53: SALE51 | P53: 45689 | Q53: CUST1142 | R53: PROD69 | S53: STORE7 | T53: 3 | U53: 76.57 | V53: 0.26 | W53: Credit Card | X53: 169.9854 | Y53: 169.9854 | Z53: =_xlfn.IFS(Table8_1[[#This Row],[Unit_Price]]<500,"Low Price",Table8_1[[#This Row],[Unit_Price]]<2000,"Medium Price",Table8_1[[#This Row],[Unit_Price]]>=2000, "High Price") -> Low Price
A54: SALE52 | B54: 45894 | C54: CUST1148 | D54: PROD89 | E54: STORE6 | F54: 3 | I54: Credit Card | J54: 486.0633 | O54: SALE52 | P54: 45894 | Q54: CUST1148 | R54: PROD89 | S54: STORE6 | T54: 3 | U54: 513.98 | V54: 0.14 | W54: Credit Card | X54: 486.0633 | Y54: 1326.0684 | Z54: =_xlfn.IFS(Table8_1[[#This Row],[Unit_Price]]<500,"Low Price",Table8_1[[#This Row],[Unit_Price]]<2000,"Medium Price",Table8_1[[#This Row],[Unit_Price]]>=2000, "High Price") -> Medium Price
A55: SALE53 | B55: 45677 | C55: CUST1324 | D55: PROD20 | E55: STORE8 | F55: 1 | G55: 900.35 | H55: 0.13 | I55: COD | J55: 783.3045 | O55: SALE53 | P55: 45677 | Q55: CUST1324 | R55: PROD20 | S55: STORE8 | T55: 1 | U55: 900.35 | V55: 0.13 | W55: COD | X55: 783.3045 | Y55: 783.3045 | Z55: =_xlfn.IFS(Table8_1[[#This Row],[Unit_Price]]<500,"Low Price",Table8_1[[#This Row],[Unit_Price]]<2000,"Medium Price",Table8_1[[#This Row],[Unit_Price]]>=2000, "High Price") -> Medium Price
A56: SALE54 | B56: 45706 | C56: CUST1095 | D56: PROD40 | E56: STORE10 | F56: 4 | G56: 428.09 | H56: 0.07 | I56: Credit Card | J56: 1592.4948 | O56: SALE54 | P56: 45706 | Q56: CUST1095 | R56: PROD40 | S56: STORE10 | T56: 4 | U56: 428.09 | V56: 0.07 | W56: Credit Card | X56: 1592.4948 | Y56: 1592.4948 | Z56: =_xlfn.IFS(Table8_1[[#This Row],[Unit_Price]]<500,"Low Price",Table8_1[[#This Row],[Unit_Price]]<2000,"Medium Price",Table8_1[[#This Row],[Unit_Price]]>=2000, "High Price") -> Low Price
A57: SALE55 | B57: 45589 | C57: CUST1416 | D57: PROD49 | E57: STORE11 | F57: 2 | G57: 559.71 | H57: 0.3 | I57: COD | J57: 783.594 | O57: SALE55 | P57: 45589 | Q57: CUST1416 | R57: PROD49 | S57: STORE11 | T57: 2 | U57: 559.71 | V57: 0.3 | W57: COD | X57: 783.594 | Y57: 783.594 | Z57: =_xlfn.IFS(Table8_1[[#This Row],[Unit_Price]]<500,"Low Price",Table8_1[[#This Row],[Unit_Price]]<2000,"Medium Price",Table8_1[[#This Row],[Unit_Price]]>=2000, "High Price") -> Medium Price
A58: SALE56 | B58: 45282 | C58: CUST1080 | D58: PROD34 | E58: STORE6 | F58: 2 | G58: 833.7 | H58: 0.06 | I58: PayPal | J58: 1567.356 | O58: SALE56 | P58: 45282 | Q58: CUST1080 | R58: PROD34 | S58: STORE6 | T58: 2 | U58: 833.7 | V58: 0.06 | W58: PayPal | X58: 1567.356 | Y58: 1567.356 | Z58: =_xlfn.IFS(Table8_1[[#This Row],[Unit_Price]]<500,"Low Price",Table8_1[[#This Row],[Unit_Price]]<2000,"Medium Price",Table8_1[[#This Row],[Unit_Price]]>=2000, "High Price") -> Medium Price
A59: SALE57 | B59: 45462 | C59: CUST1467 | D59: PROD47 | E59: STORE14 | F59: 2 | G59: 680.16 | H59: 0.28 | I59: Credit Card | J59: 979.4304 | O59: SALE57 | P59: 45462 | Q59: CUST1467 | R59: PROD47 | S59: STORE14 | T59: 2 | U59: 680.16 | V59: 0.28 | W59: Credit Card | X59: 979.4304 | Y59: 979.4304 | Z59: =_xlfn.IFS(Table8_1[[#This Row],[Unit_Price]]<500,"Low Price",Table8_1[[#This Row],[Unit_Price]]<2000,"Medium Price",Table8_1[[#This Row],[Unit_Price]]>=2000, "High Price") -> Medium Price
A60: SALE58 | B60: 45633 | C60: CUST1404 | D60: PROD15 | E60: STORE7 | F60: 4 | G60: 733.42 | I60: PayPal | J60: 2552.3016 | O60: SALE58 | P60: 45633 | Q60: CUST1404 | R60: PROD15 | S60: STORE7 | T60: 4 | U60: 733.42 | V60: 0.14 | W60: PayPal | X60: 2552.3016 | Y60: 2522.9648 | Z60: =_xlfn.IFS(Table8_1[[#This Row],[Unit_Price]]<500,"Low Price",Table8_1[[#This Row],[Unit_Price]]<2000,"Medium Price",Table8_1[[#This Row],[Unit_Price]]>=2000, "High Price") -> Medium Price
A61: SALE59 | B61: 45257 | C61: CUST1367 | D61: PROD89 | E61: STORE11 | F61: 1 | G61: 996.33 | H61: 0.23 | I61: PayPal | J61: 767.1741 | O61: SALE59 | P61: 45257 | Q61: CUST1367 | R61: PROD89 | S61: STORE11 | T61: 1 | U61: 996.33 | V61: 0.23 | W61: PayPal | X61: 767.1741 | Y61: 767.1741 | Z61: =_xlfn.IFS(Table8_1[[#This Row],[Unit_Price]]<500,"Low Price",Table8_1[[#This Row],[Unit_Price]]<2000,"Medium Price",Table8_1[[#This Row],[Unit_Price]]>=2000, "High Price") -> Medium Price
A62: SALE60 | B62: 45854 | C62: CUST1408 | D62: PROD31 | E62: STORE10 | F62: 1 | G62: 198.83 | H62: 0.09 | I62: COD | J62: 180.9353 | O62: SALE60 | P62: 45854 | Q62: CUST1408 | R62: PROD31 | S62: STORE10 | T62: 1 | U62: 198.83 | V62: 0.09 | W62: COD | X62: 180.9353 | Y62: 180.9353 | Z62: =_xlfn.IFS(Table8_1[[#This Row],[Unit_Price]]<500,"Low Price",Table8_1[[#This Row],[Unit_Price]]<2000,"Medium Price",Table8_1[[#This Row],[Unit_Price]]>=2000, "High Price") -> Low Price
A63: SALE61 | B63: 45716 | C63: CUST1239 | D63: PROD19 | E63: STORE7 | F63: 1 | G63: 374.92 | H63: 0.18 | I63: PayPal | J63: 307.4344 | O63: SALE61 | P63: 45716 | Q63: CUST1239 | R63: PROD19 | S63: STORE7 | T63: 1 | U63: 374.92 | V63: 0.18 | W63: PayPal | X63: 307.4344 | Y63: 307.4344 | Z63: =_xlfn.IFS(Table8_1[[#This Row],[Unit_Price]]<500,"Low Price",Table8_1[[#This Row],[Unit_Price]]<2000,"Medium Price",Table8_1[[#This Row],[Unit_Price]]>=2000, "High Price") -> Low Price
A64: SALE62 | B64: 45515 | C64: CUST1464 | D64: PROD93 | E64: STORE16 | F64: 1 | G64: 468.94 | H64: 0.12 | I64: Credit Card | J64: 412.6672 | O64: SALE62 | P64: 45515 | Q64: CUST1464 | R64: PROD93 | S64: STORE16 | T64: 1 | U64: 468.94 | V64: 0.12 | W64: Credit Card | X64: 412.6672 | Y64: 412.6672 | Z64: =_xlfn.IFS(Table8_1[[#This Row],[Unit_Price]]<500,"Low Price",Table8_1[[#This Row],[Unit_Price]]<2000,"Medium Price",Table8_1[[#This Row],[Unit_Price]]>=2000, "High Price") -> Low Price
A65: SALE63 | B65: 45927 | C65: CUST1126 | D65: PROD89 | E65: STORE12 | F65: 2 | G65: 121.37 | H65: 0.05 | I65: Credit Card | J65: 230.603 | O65: SALE63 | P65: 45927 | Q65: CUST1126 | R65: PROD89 | S65: STORE12 | T65: 2 | U65: 121.37 | V65: 0.05 | W65: Credit Card | X65: 230.603 | Y65: 230.603 | Z65: =_xlfn.IFS(Table8_1[[#This Row],[Unit_Price]]<500,"Low Price",Table8_1[[#This Row],[Unit_Price]]<2000,"Medium Price",Table8_1[[#This Row],[Unit_Price]]>=2000, "High Price") -> Low Price
A66: SALE64 | B66: 45914 | C66: CUST1255 | D66: PROD53 | E66: STORE10 | F66: 3 | G66: 480.06 | H66: 0.01 | I66: Credit Card | O66: SALE64 | P66: 45914 | Q66: CUST1255 | R66: PROD53 | S66: STORE10 | T66: 3 | U66: 480.06 | V66: 0.01 | W66: Credit Card | X66: 1425.7782 | Y66: 1425.7782 | Z66: =_xlfn.IFS(Table8_1[[#This Row],[Unit_Price]]<500,"Low Price",Table8_1[[#This Row],[Unit_Price]]<2000,"Medium Price",Table8_1[[#This Row],[Unit_Price]]>=2000, "High Price") -> Low Price
A67: SALE65 | B67: 45290 | C67: CUST1162 | D67: PROD99 | E67: STORE17 | F67: 2 | G67: 856.57 | H67: 0.24 | I67: Credit Card | J67: 1301.9864 | O67: SALE65 | P67: 45290 | Q67: CUST1162 | R67: PROD99 | S67: STORE17 | T67: 2 | U67: 856.57 | V67: 0.24 | W67: Credit Card | X67: 1301.9864 | Y67: 1301.9864 | Z67: =_xlfn.IFS(Table8_1[[#This Row],[Unit_Price]]<500,"Low Price",Table8_1[[#This Row],[Unit_Price]]<2000,"Medium Price",Table8_1[[#This Row],[Unit_Price]]>=2000, "High Price") -> Medium Price
A68: SALE66 | B68: 45213 | C68: CUST1269 | D68: PROD77 | E68: STORE2 | F68: 4 | G68: 814.25 | H68: 0.18 | I68: Credit Card | J68: 2670.74 | O68: SALE66 | P68: 45213 | Q68: CUST1269 | R68: PROD77 | S68: STORE2 | T68: 4 | U68: 814.25 | V68: 0.18 | W68: Credit Card | X68: 2670.74 | Y68: 2670.74 | Z68: =_xlfn.IFS(Table8_1[[#This Row],[Unit_Price]]<500,"Low Price",Table8_1[[#This Row],[Unit_Price]]<2000,"Medium Price",Table8_1[[#This Row],[Unit_Price]]>=2000, "High Price") -> Medium Price
A69: SALE67 | B69: 45255 | C69: CUST1483 | D69: PROD12 | E69: STORE2 | F69: 1 | G69: 989.17 | H69: 0.2 | I69: PayPal | J69: 791.336 | O69: SALE67 | P69: 45255 | Q69: CUST1483 | R69: PROD12 | S69: STORE2 | T69: 1 | U69: 989.17 | V69: 0.2 | W69: PayPal | X69: 791.336 | Y69: 791.336 | Z69: =_xlfn.IFS(Table8_1[[#This Row],[Unit_Price]]<500,"Low Price",Table8_1[[#This Row],[Unit_Price]]<2000,"Medium Price",Table8_1[[#This Row],[Unit_Price]]>=2000, "High Price") -> Medium Price
A70: SALE68 | B70: 45270 | C70: CUST1372 | D70: PROD72 | E70: STORE10 | F70: 4 | G70: 62.48 | H70: 0.18 | I70: Credit Card | J70: 204.9344 | O70: SALE68 | P70: 45270 | Q70: CUST1372 | R70: PROD72 | S70: STORE10 | T70: 4 | U70: 62.48 | V70: 0.18 | W70: Credit Card | X70: 204.9344 | Y70: 204.9344 | Z70: =_xlfn.IFS(Table8_1[[#This Row],[Unit_Price]]<500,"Low Price",Table8_1[[#This Row],[Unit_Price]]<2000,"Medium Price",Table8_1[[#This Row],[Unit_Price]]>=2000, "High Price") -> Low Price
A71: SALE69 | B71: 45897 | C71: CUST1423 | D71: PROD13 | E71: STORE16 | F71: 4 | G71: 561.24 | H71: 0.24 | I71: Credit Card | J71: 1706.1696 | O71: SALE69 | P71: 45897 | Q71: CUST1423 | R71: PROD13 | S71: STORE16 | T71: 4 | U71: 561.24 | V71: 0.24 | W71: Credit Card | X71: 1706.1696 | Y71: 1706.1696 | Z71: =_xlfn.IFS(Table8_1[[#This Row],[Unit_Price]]<500,"Low Price",Table8_1[[#This Row],[Unit_Price]]<2000,"Medium Price",Table8_1[[#This Row],[Unit_Price]]>=2000, "High Price") -> Medium Price
A72: SALE70 | B72: 45849 | C72: CUST1058 | D72: PROD60 | E72: STORE5 | F72: 3 | G72: 92.24 | H72: 0.28 | I72: COD | O72: SALE70 | P72: 45849 | Q72: CUST1058 | R72: PROD60 | S72: STORE5 | T72: 3 | U72: 92.24 | V72: 0.28 | W72: COD | X72: 199.2384 | Y72: 199.2384 | Z72: =_xlfn.IFS(Table8_1[[#This Row],[Unit_Price]]<500,"Low Price",Table8_1[[#This Row],[Unit_Price]]<2000,"Medium Price",Table8_1[[#This Row],[Unit_Price]]>=2000, "High Price") -> Low Price
A73: SALE71 | B73: 45889 | C73: CUST1168 | D73: PROD72 | E73: STORE1 | F73: 2 | G73: 668.3 | H73: 0.07 | I73: Credit Card | J73: 1243.038 | O73: SALE71 | P73: 45889 | Q73: CUST1168 | R73: PROD72 | S73: STORE1 | T73: 2 | U73: 668.3 | V73: 0.07 | W73: Credit Card | X73: 1243.038 | Y73: 1243.038 | Z73: =_xlfn.IFS(Table8_1[[#This Row],[Unit_Price]]<500,"Low Price",Table8_1[[#This Row],[Unit_Price]]<2000,"Medium Price",Table8_1[[#This Row],[Unit_Price]]>=2000, "High Price") -> Medium Price
A74: SALE72 | B74: 45533 | C74: CUST1409 | D74: PROD38 | E74: STORE5 | F74: 1 | G74: 553.82 | H74: 0.09 | I74: Credit Card | J74: 503.9762 | O74: SALE72 | P74: 45533 | Q74: CUST1409 | R74: PROD38 | S74: STORE5 | T74: 1 | U74: 553.82 | V74: 0.09 | W74: Credit Card | X74: 503.9762 | Y74: 503.9762 | Z74: =_xlfn.IFS(Table8_1[[#This Row],[Unit_Price]]<500,"Low Price",Table8_1[[#This Row],[Unit_Price]]<2000,"Medium Price",Table8_1[[#This Row],[Unit_Price]]>=2000, "High Price") -> Medium Price
A75: SALE73 | B75: 45626 | C75: CUST1037 | D75: PROD45 | E75: STORE11 | F75: 2 | G75: 556.43 | H75: 0.13 | I75: Credit Card | J75: 968.1882 | O75: SALE73 | P75: 45626 | Q75: CUST1037 | R75: PROD45 | S75: STORE11 | T75: 2 | U75: 556.43 | V75: 0.13 | W75: Credit Card | X75: 968.1882 | Y75: 968.1882 | Z75: =_xlfn.IFS(Table8_1[[#This Row],[Unit_Price]]<500,"Low Price",Table8_1[[#This Row],[Unit_Price]]<2000,"Medium Price",Table8_1[[#This Row],[Unit_Price]]>=2000, "High Price") -> Medium Price
A76: SALE74 | B76: 45942 | C76: CUST1273 | D76: PROD20 | E76: STORE8 | F76: 1 | G76: 184.98 | H76: 0.1 | I76: COD | J76: 166.482 | O76: SALE74 | P76: 45942 | Q76: CUST1273 | R76: PROD20 | S76: STORE8 | T76: 1 | U76: 184.98 | V76: 0.1 | W76: COD | X76: 166.482 | Y76: 166.482 | Z76: =_xlfn.IFS(Table8_1[[#This Row],[Unit_Price]]<500,"Low Price",Table8_1[[#This Row],[Unit_Price]]<2000,"Medium Price",Table8_1[[#This Row],[Unit_Price]]>=2000, "High Price") -> Low Price
A77: SALE75 | B77: 45500 | C77: CUST1035 | D77: PROD97 | E77: STORE12 | F77: 4 | G77: 700.18 | H77: 0.23 | I77: Credit Card | J77: 2156.5544 | O77: SALE75 | P77: 45500 | Q77: CUST1035 | R77: PROD97 | S77: STORE12 | T77: 4 | U77: 700.18 | V77: 0.23 | W77: Credit Card | X77: 2156.5544 | Y77: 2156.5544 | Z77: =_xlfn.IFS(Table8_1[[#This Row],[Unit_Price]]<500,"Low Price",Table8_1[[#This Row],[Unit_Price]]<2000,"Medium Price",Table8_1[[#This Row],[Unit_Price]]>=2000, "High Price") -> Medium Price
A78: SALE76 | B78: 45285 | C78: CUST1019 | D78: PROD76 | E78: STORE10 | F78: 2 | G78: 686.31 | H78: 0.25 | I78: Credit Card | J78: 1029.465 | O78: SALE76 | P78: 45285 | Q78: CUST1019 | R78: PROD76 | S78: STORE10 | T78: 2 | U78: 686.31 | V78: 0.25 | W78: Credit Card | X78: 1029.465 | Y78: 1029.465 | Z78: =_xlfn.IFS(Table8_1[[#This Row],[Unit_Price]]<500,"Low Price",Table8_1[[#This Row],[Unit_Price]]<2000,"Medium Price",Table8_1[[#This Row],[Unit_Price]]>=2000, "High Price") -> Medium Price
A79: SALE77 | B79: 45800 | C79: CUST1007 | D79: PROD67 | E79: STORE15 | F79: 1 | G79: 687.82 | H79: 0.27 | I79: COD | J79: 502.1086 | O79: SALE77 | P79: 45800 | Q79: CUST1007 | R79: PROD67 | S79: STORE15 | T79: 1 | U79: 687.82 | V79: 0.27 | W79: COD | X79: 502.1086 | Y79: 502.1086 | Z79: =_xlfn.IFS(Table8_1[[#This Row],[Unit_Price]]<500,"Low Price",Table8_1[[#This Row],[Unit_Price]]<2000,"Medium Price",Table8_1[[#This Row],[Unit_Price]]>=2000, "High Price") -> Medium Price
A80: SALE78 | B80: 45609 | C80: CUST1221 | D80: PROD83 | E80: STORE8 | F80: 2 | G80: 900.55 | H80: 0.16 | I80: Credit Card | J80: 1512.924 | O80: SALE78 | P80: 45609 | Q80: CUST1221 | R80: PROD83 | S80: STORE8 | T80: 2 | U80: 900.55 | V80: 0.16 | W80: Credit Card | X80: 1512.924 | Y80: 1512.924 | Z80: =_xlfn.IFS(Table8_1[[#This Row],[Unit_Price]]<500,"Low Price",Table8_1[[#This Row],[Unit_Price]]<2000,"Medium Price",Table8_1[[#This Row],[Unit_Price]]>=2000, "High Price") -> Medium Price
A81: SALE79 | B81: 45268 | C81: CUST1115 | D81: PROD21 | E81: STORE2 | F81: 1 | G81: 341.17 | H81: 0.15 | I81: Credit Card | J81: 289.9945 | O81: SALE79 | P81: 45268 | Q81: CUST1115 | R81: PROD21 | S81: STORE2 | T81: 1 | U81: 341.17 | V81: 0.15 | W81: Credit Card | X81: 289.9945 | Y81: 289.9945 | Z81: =_xlfn.IFS(Table8_1[[#This Row],[Unit_Price]]<500,"Low Price",Table8_1[[#This Row],[Unit_Price]]<2000,"Medium Price",Table8_1[[#This Row],[Unit_Price]]>=2000, "High Price") -> Low Price
A82: SALE80 | B82: 45885 | C82: CUST1176 | D82: PROD52 | E82: STORE8 | F82: 1 | G82: 442.27 | H82: 0.06 | I82: COD | J82: 415.7338 | O82: SALE80 | P82: 45885 | Q82: CUST1176 | R82: PROD52 | S82: STORE8 | T82: 1 | U82: 442.27 | V82: 0.06 | W82: COD | X82: 415.7338 | Y82: 415.7338 | Z82: =_xlfn.IFS(Table8_1[[#This Row],[Unit_Price]]<500,"Low Price",Table8_1[[#This Row],[Unit_Price]]<2000,"Medium Price",Table8_1[[#This Row],[Unit_Price]]>=2000, "High Price") -> Low Price
A83: SALE81 | B83: 45616 | C83: CUST1253 | D83: PROD71 | E83: STORE9 | F83: 1 | G83: 363.73 | H83: 0.25 | I83: PayPal | J83: 272.7975 | O83: SALE81 | P83: 45616 | Q83: CUST1253 | R83: PROD71 | S83: STORE9 | T83: 1 | U83: 363.73 | V83: 0.25 | W83: PayPal | X83: 272.7975 | Y83: 272.7975 | Z83: =_xlfn.IFS(Table8_1[[#This Row],[Unit_Price]]<500,"Low Price",Table8_1[[#This Row],[Unit_Price]]<2000,"Medium Price",Table8_1[[#This Row],[Unit_Price]]>=2000, "High Price") -> Low Price
A84: SALE82 | B84: 45518 | C84: CUST1378 | D84: PROD91 | E84: STORE17 | F84: 2 | G84: 601.33 | H84: 0.16 | I84: PayPal | J84: 1010.2344 | O84: SALE82 | P84: 45518 | Q84: CUST1378 | R84: PROD91 | S84: STORE17 | T84: 2 | U84: 601.33 | V84: 0.16 | W84: PayPal | X84: 1010.2344 | Y84: 1010.2344 | Z84: =_xlfn.IFS(Table8_1[[#This Row],[Unit_Price]]<500,"Low Price",Table8_1[[#This Row],[Unit_Price]]<2000,"Medium Price",Table8_1[[#This Row],[Unit_Price]]>=2000, "High Price") -> Medium Price
A85: SALE83 | B85: 45427 | C85: CUST1403 | D85: PROD17 | E85: STORE18 | F85: 4 | G85: 34.39 | H85: 0.03 | I85: PayPal | J85: 133.4332 | O85: SALE83 | P85: 45427 | Q85: CUST1403 | R85: PROD17 | S85: STORE18 | T85: 4 | U85: 34.39 | V85: 0.03 | W85: PayPal | X85: 133.4332 | Y85: 133.4332 | Z85: =_xlfn.IFS(Table8_1[[#This Row],[Unit_Price]]<500,"Low Price",Table8_1[[#This Row],[Unit_Price]]<2000,"Medium Price",Table8_1[[#This Row],[Unit_Price]]>=2000, "High Price") -> Low Price
A86: SALE84 | B86: 45268 | C86: CUST1423 | D86: PROD46 | E86: STORE17 | F86: 1 | G86: 773.57 | H86: 0.05 | I86: COD | O86: SALE84 | P86: 45268 | Q86: CUST1423 | R86: PROD46 | S86: STORE17 | T86: 1 | U86: 773.57 | V86: 0.05 | W86: COD | X86: 734.8915 | Y86: 734.8915 | Z86: =_xlfn.IFS(Table8_1[[#This Row],[Unit_Price]]<500,"Low Price",Table8_1[[#This Row],[Unit_Price]]<2000,"Medium Price",Table8_1[[#This Row],[Unit_Price]]>=2000, "High Price") -> Medium Price
A87: SALE85 | B87: 45282 | C87: CUST1054 | D87: PROD88 | E87: STORE7 | F87: 4 | G87: 127.1 | H87: 0.24 | I87: COD | J87: 386.384 | O87: SALE85 | P87: 45282 | Q87: CUST1054 | R87: PROD88 | S87: STORE7 | T87: 4 | U87: 127.1 | V87: 0.24 | W87: COD | X87: 386.384 | Y87: 386.384 | Z87: =_xlfn.IFS(Table8_1[[#This Row],[Unit_Price]]<500,"Low Price",Table8_1[[#This Row],[Unit_Price]]<2000,"Medium Price",Table8_1[[#This Row],[Unit_Price]]>=2000, "High Price") -> Low Price
A88: SALE86 | B88: 45545 | C88: CUST1303 | D88: PROD20 | E88: STORE3 | F88: 3 | G88: 899.58 | H88: 0.28 | I88: PayPal | J88: 1943.0928 | O88: SALE86 | P88: 45545 | Q88: CUST1303 | R88: PROD20 | S88: STORE3 | T88: 3 | U88: 899.58 | V88: 0.28 | W88: PayPal | X88: 1943.0928 | Y88: 1943.0928 | Z88: =_xlfn.IFS(Table8_1[[#This Row],[Unit_Price]]<500,"Low Price",Table8_1[[#This Row],[Unit_Price]]<2000,"Medium Price",Table8_1[[#This Row],[Unit_Price]]>=2000, "High Price") -> Medium Price
A89: SALE87 | B89: 45755 | C89: CUST1327 | D89: PROD1 | E89: STORE10 | F89: 3 | G89: 964.39 | H89: 0.04 | I89: Credit Card | J89: 2777.4432 | O89: SALE87 | P89: 45755 | Q89: CUST1327 | R89: PROD1 | S89: STORE10 | T89: 3 | U89: 964.39 | V89: 0.04 | W89: Credit Card | X89: 2777.4432 | Y89: 2777.4432 | Z89: =_xlfn.IFS(Table8_1[[#This Row],[Unit_Price]]<500,"Low Price",Table8_1[[#This Row],[Unit_Price]]<2000,"Medium Price",Table8_1[[#This Row],[Unit_Price]]>=2000, "High Price") -> Medium Price
A90: SALE88 | B90: 45588 | C90: CUST1183 | D90: PROD38 | E90: STORE0 | F90: 2 | G90: 217.83 | H90: 0.14 | I90: PayPal | J90: 374.6676 | O90: SALE88 | P90: 45588 | Q90: CUST1183 | R90: PROD38 | S90: STORE0 | T90: 2 | U90: 217.83 | V90: 0.14 | W90: PayPal | X90: 374.6676 | Y90: 374.6676 | Z90: =_xlfn.IFS(Table8_1[[#This Row],[Unit_Price]]<500,"Low Price",Table8_1[[#This Row],[Unit_Price]]<2000,"Medium Price",Table8_1[[#This Row],[Unit_Price]]>=2000, "High Price") -> Low Price
A91: SALE89 | B91: 45848 | C91: CUST1143 | D91: PROD17 | E91: STORE1 | F91: 4 | G91: 187.71 | H91: 0.06 | I91: COD | J91: 705.7896 | O91: SALE89 | P91: 45848 | Q91: CUST1143 | R91: PROD17 | S91: STORE1 | T91: 4 | U91: 187.71 | V91: 0.06 | W91: COD | X91: 705.7896 | Y91: 705.7896 | Z91: =_xlfn.IFS(Table8_1[[#This Row],[Unit_Price]]<500,"Low Price",Table8_1[[#This Row],[Unit_Price]]<2000,"Medium Price",Table8_1[[#This Row],[Unit_Price]]>=2000, "High Price") -> Low Price
A92: SALE90 | B92: 45577 | C92: CUST1010 | D92: PROD33 | E92: STORE18 | F92: 2 | G92: 350.12 | H92: 0.12 | I92: COD | J92: 616.2112 | O92: SALE90 | P92: 45577 | Q92: CUST1010 | R92: PROD33 | S92: STORE18 | T92: 2 | U92: 350.12 | V92: 0.12 | W92: COD | X92: 616.2112 | Y92: 616.2112 | Z92: =_xlfn.IFS(Table8_1[[#This Row],[Unit_Price]]<500,"Low Price",Table8_1[[#This Row],[Unit_Price]]<2000,"Medium Price",Table8_1[[#This Row],[Unit_Price]]>=2000, "High Price") -> Low Price
A93: SALE91 | B93: 45312 | C93: CUST1406 | D93: PROD16 | E93: STORE1 | F93: 4 | G93: 102.19 | H93: 0.17 | I93: PayPal | J93: 339.2708 | O93: SALE91 | P93: 45312 | Q93: CUST1406 | R93: PROD16 | S93: STORE1 | T93: 4 | U93: 102.19 | V93: 0.17 | W93: PayPal | X93: 339.2708 | Y93: 339.2708 | Z93: =_xlfn.IFS(Table8_1[[#This Row],[Unit_Price]]<500,"Low Price",Table8_1[[#This Row],[Unit_Price]]<2000,"Medium Price",Table8_1[[#This Row],[Unit_Price]]>=2000, "High Price") -> Low Price
A94: SALE92 | B94: 45350 | C94: CUST1007 | D94: PROD86 | E94: STORE4 | F94: 1 | G94: 696.53 | H94: 0.17 | I94: Credit Card | J94: 578.1199 | O94: SALE92 | P94: 45350 | Q94: CUST1007 | R94: PROD86 | S94: STORE4 | T94: 1 | U94: 696.53 | V94: 0.17 | W94: Credit Card | X94: 578.1199 | Y94: 578.1199 | Z94: =_xlfn.IFS(Table8_1[[#This Row],[Unit_Price]]<500,"Low Price",Table8_1[[#This Row],[Unit_Price]]<2000,"Medium Price",Table8_1[[#This Row],[Unit_Price]]>=2000, "High Price") -> Medium Price
A95: SALE93 | B95: 45657 | C95: CUST1065 | D95: PROD19 | E95: STORE4 | F95: 2 | G95: 327.52 | H95: 0.15 | I95: PayPal | J95: 556.784 | O95: SALE93 | P95: 45657 | Q95: CUST1065 | R95: PROD19 | S95: STORE4 | T95: 2 | U95: 327.52 | V95: 0.15 | W95: PayPal | X95: 556.784 | Y95: 556.784 | Z95: =_xlfn.IFS(Table8_1[[#This Row],[Unit_Price]]<500,"Low Price",Table8_1[[#This Row],[Unit_Price]]<2000,"Medium Price",Table8_1[[#This Row],[Unit_Price]]>=2000, "High Price") -> Low Price
A96: SALE94 | B96: 45530 | C96: CUST1298 | D96: PROD97 | E96: STORE19 | F96: 2 | G96: 569.36 | H96: 0.01 | I96: PayPal | O96: SALE94 | P96: 45530 | Q96: CUST1298 | R96: PROD97 | S96: STORE19 | T96: 2 | U96: 569.36 | V96: 0.01 | W96: PayPal | X96: 1127.3328 | Y96: 1127.3328 | Z96: =_xlfn.IFS(Table8_1[[#This Row],[Unit_Price]]<500,"Low Price",Table8_1[[#This Row],[Unit_Price]]<2000,"Medium Price",Table8_1[[#This Row],[Unit_Price]]>=2000, "High Price") -> Medium Price
A97: SALE95 | B97: 45556 | C97: CUST1321 | D97: PROD99 | E97: STORE6 | F97: 2 | G97: 68.29 | H97: 0.14 | I97: COD | J97: 117.4588 | O97: SALE95 | P97: 45556 | Q97: CUST1321 | R97: PROD99 | S97: STORE6 | T97: 2 | U97: 68.29 | V97: 0.14 | W97: COD | X97: 117.4588 | Y97: 117.4588 | Z97: =_xlfn.IFS(Table8_1[[#This Row],[Unit_Price]]<500,"Low Price",Table8_1[[#This Row],[Unit_Price]]<2000,"Medium Price",Table8_1[[#This Row],[Unit_Price]]>=2000, "High Price") -> Low Price
A98: SALE96 | B98: 45523 | C98: CUST1244 | D98: PROD50 | E98: STORE10 | F98: 1 | G98: 842.9 | H98: 0.06 | I98: COD | J98: 792.326 | O98: SALE96 | P98: 45523 | Q98: CUST1244 | R98: PROD50 | S98: STORE10 | T98: 1 | U98: 842.9 | V98: 0.06 | W98: COD | X98: 792.326 | Y98: 792.326 | Z98: =_xlfn.IFS(Table8_1[[#This Row],[Unit_Price]]<500,"Low Price",Table8_1[[#This Row],[Unit_Price]]<2000,"Medium Price",Table8_1[[#This Row],[Unit_Price]]>=2000, "High Price") -> Medium Price
A99: SALE97 | B99: 45587 | C99: CUST1287 | D99: PROD3 | E99: STORE3 | F99: 3 | G99: 751.94 | H99: 0.26 | I99: PayPal | J99: 1669.3068 | O99: SALE97 | P99: 45587 | Q99: CUST1287 | R99: PROD3 | S99: STORE3 | T99: 3 | U99: 751.94 | V99: 0.26 | W99: PayPal | X99: 1669.3068 | Y99: 1669.3068 | Z99: =_xlfn.IFS(Table8_1[[#This Row],[Unit_Price]]<500,"Low Price",Table8_1[[#This Row],[Unit_Price]]<2000,"Medium Price",Table8_1[[#This Row],[Unit_Price]]>=2000, "High Price") -> Medium Price
A100: SALE98 | B100: 45580 | C100: CUST1131 | D100: PROD56 | E100: STORE7 | F100: 4 | G100: 476.28 | H100: 0.17 | I100: Credit Card | J100: 1581.2496 | O100: SALE98 | P100: 45580 | Q100: CUST1131 | R100: PROD56 | S100: STORE7 | T100: 4 | U100: 476.28 | V100: 0.17 | W100: Credit Card | X100: 1581.2496 | Y100: 1581.2496 | Z100: =_xlfn.IFS(Table8_1[[#This Row],[Unit_Price]]<500,"Low Price",Table8_1[[#This Row],[Unit_Price]]<2000,"Medium Price",Table8_1[[#This Row],[Unit_Price]]>=2000, "High Price") -> Low Price
...

Sheet VLOOKUP
A1: Sales_ID | B1: Order_Date | C1: Customer_ID | D1: Product_ID | E1: Store_ID | F1: Quantity | G1: Unit_Price | H1: Discount | I1: Payment_Type | J1: Total_Amount | K1: Amount_Paid | L1: Price Range | M1: Name | N1: Age | O1: Gender | P1: City | Q1: State | R1: Country | S1: Loyalty_Level | T1: Customer Level | U1: Product_Description | V1: Product Type | W1: Category | X1: Sub_Category | Y1: Brand | Z1: Cost | AA1: Stock | AB1: Store Name | AC1: Region | AD1: Store City | AE1: Store_Type | AF1: Store Category
A2: SALE0 | B2: 45480 | C2: CUST1409 | D2: PROD97 | E2: STORE3 | F2: 1 | G2: 218.04 | H2: 0.09 | I2: Credit Card | J2: 198.4164 | K2: 198.4164 | L2: =_xlfn.IFS(Table8_1[[#This Row],[Unit_Price]]<500,"Low Price",Table8_1[[#This Row],[Unit_Price]]<2000,"Medium Price",Table8_1[[#This Row],[Unit_Price]]>=2000, "High Price") -> Low Price | M2: =VLOOKUP(Table8_16[[#This Row],[Customer_ID]],Table1__2[],2,FALSE) -> Sarah Smith | N2: =VLOOKUP(Table8_16[[#This Row],[Customer_ID]],Table1__2[],3,FALSE) -> 55 | O2: =VLOOKUP(Table8_16[[#This Row],[Customer_ID]],Table1__2[],4,FALSE) -> Male | P2: =VLOOKUP(Table8_16[[#This Row],[Customer_ID]],Table1__2[],5,FALSE) -> Kathleenport | Q2: =VLOOKUP(Table8_16[[#This Row],[Customer_ID]],Table1__2[],6,FALSE) -> Wyoming | R2: =VLOOKUP(Table8_16[[#This Row],[Customer_ID]],Table1__2[],7,FALSE) -> USA | S2: =VLOOKUP(Table8_16[[#This Row],[Customer_ID]],Table1__2[],8,FALSE) -> Gold | T2: =VLOOKUP(Table8_16[[#This Row],[Customer_ID]],Table1__2[],9,FALSE) -> Experienced | U2: =VLOOKUP(Table8_16[[#This Row],[Product_ID]],Table3__211[],2,FALSE) -> Cricket | V2: =VLOOKUP(Table8_16[[#This Row],[Product_ID]],Table3__211[],3,FALSE) -> Bat | W2: =VLOOKUP(Table8_16[[#This Row],[Product_ID]],Table3__211[],4,FALSE) -> Sports | X2: =VLOOKUP(Table8_16[[#This Row],[Product_ID]],Table3__211[],5,FALSE) -> Team Sports | Y2: =VLOOKUP(Table8_16[[#This Row],[Product_ID]],Table3__211[],6,FALSE) -> Khan LLC | Z2: =VLOOKUP(Table8_16[[#This Row],[Product_ID]],Table3__211[],7,FALSE) -> 245.98 | AA2: =VLOOKUP(Table8_16[[#This Row],[Product_ID]],Table3__211[],8,FALSE) -> 471 | AB2: =VLOOKUP(Table8_16[[#This Row],[Store_ID]],Store!$A$2:$E$21,2,FALSE) -> Johnson-Wright | AC2: =VLOOKUP(Table8_16[[#This Row],[Store_ID]],Store!$A$2:$E$21,3,FALSE) -> North | AD2: =VLOOKUP(Table8_16[[#This Row],[Store_ID]],Store!$A$2:$E$21,4,FALSE) -> Hoodberg | AE2: =VLOOKUP(Table8_16[[#This Row],[Store_ID]],Store!$A$2:$E$21,5,FALSE) -> Outlet | AF2: =VLOOKUP(Table8_16[[#This Row],[Store_ID]],Store!$A$2:$F$21,6,FALSE) -> Physical Store
A3: SALE1 | B3: 45285 | C3: CUST1467 | D3: PROD74 | E3: STORE17 | F3: 3 | G3: 104.47 | H3: 0.27 | I3: PayPal | J3: 228.7893 | K3: 228.7893 | L3: =_xlfn.IFS(Table8_1[[#This Row],[Unit_Price]]<500,"Low Price",Table8_1[[#This Row],[Unit_Price]]<2000,"Medium Price",Table8_1[[#This Row],[Unit_Price]]>=2000, "High Price") -> Low Price | M3: =VLOOKUP(Table8_16[[#This Row],[Customer_ID]],Table1__2[],2,FALSE) -> Michael Foley | N3: =VLOOKUP(Table8_16[[#This Row],[Customer_ID]],Table1__2[],3,FALSE) -> 63 | O3: =VLOOKUP(Table8_16[[#This Row],[Customer_ID]],Table1__2[],4,FALSE) -> Female | P3: =VLOOKUP(Table8_16[[#This Row],[Customer_ID]],Table1__2[],5,FALSE) -> Oneillfurt | Q3: =VLOOKUP(Table8_16[[#This Row],[Customer_ID]],Table1__2[],6,FALSE) -> Vermont | R3: =VLOOKUP(Table8_16[[#This Row],[Customer_ID]],Table1__2[],7,FALSE) -> USA | S3: =VLOOKUP(Table8_16[[#This Row],[Customer_ID]],Table1__2[],8,FALSE) -> Gold | T3: =VLOOKUP(Table8_16[[#This Row],[Customer_ID]],Table1__2[],9,FALSE) -> Retired | U3: =VLOOKUP(Table8_16[[#This Row],[Product_ID]],Table3__211[],2,FALSE) -> Bluetooth Car Audio | V3: =VLOOKUP(Table8_16[[#This Row],[Product_ID]],Table3__211[],3,FALSE) -> System | W3: =VLOOKUP(Table8_16[[#This Row],[Product_ID]],Table3__211[],4,FALSE) -> Electronics | X3: =VLOOKUP(Table8_16[[#This Row],[Product_ID]],Table3__211[],5,FALSE) -> Audio | Y3: =VLOOKUP(Table8_16[[#This Row],[Product_ID]],Table3__211[],6,FALSE) -> Bruce-Bowen | Z3: =VLOOKUP(Table8_16[[#This Row],[Product_ID]],Table3__211[],7,FALSE) -> 403.71 | AA3: =VLOOKUP(Table8_16[[#This Row],[Product_ID]],Table3__211[],8,FALSE) -> 159 | AB3: =VLOOKUP(Table8_16[[#This Row],[Store_ID]],Store!$A$2:$E$21,2,FALSE) -> Holloway Ltd | AC3: =VLOOKUP(Table8_16[[#This Row],[Store_ID]],Store!$A$2:$E$21,3,FALSE) -> North | AD3: =VLOOKUP(Table8_16[[#This Row],[Store_ID]],Store!$A$2:$E$21,4,FALSE) -> Bensonhaven | AE3: =VLOOKUP(Table8_16[[#This Row],[Store_ID]],Store!$A$2:$E$21,5,FALSE) -> Flagship | AF3: =VLOOKUP(Table8_16[[#This Row],[Store_ID]],Store!$A$2:$F$21,6,FALSE) -> Physical Store
A4: SALE2 | B4: 45446 | C4: CUST1056 | D4: PROD49 | E4: STORE8 | F4: 4 | G4: 914.05 | H4: 0.25 | I4: Credit Card | J4: 2742.15 | K4: 2742.15 | L4: =_xlfn.IFS(Table8_1[[#This Row],[Unit_Price]]<500,"Low Price",Table8_1[[#This Row],[Unit_Price]]<2000,"Medium Price",Table8_1[[#This Row],[Unit_Price]]>=2000, "High Price") -> Medium Price | M4: =VLOOKUP(Table8_16[[#This Row],[Customer_ID]],Table1__2[],2,FALSE) -> Christopher Sutton | N4: =VLOOKUP(Table8_16[[#This Row],[Customer_ID]],Table1__2[],3,FALSE) -> 49 | O4: =VLOOKUP(Table8_16[[#This Row],[Customer_ID]],Table1__2[],4,FALSE) -> Female | P4: =VLOOKUP(Table8_16[[#This Row],[Customer_ID]],Table1__2[],5,FALSE) -> Deborahberg | Q4: =VLOOKUP(Table8_16[[#This Row],[Customer_ID]],Table1__2[],6,FALSE) -> Pennsylvania | R4: =VLOOKUP(Table8_16[[#This Row],[Customer_ID]],Table1__2[],7,FALSE) -> USA | S4: =VLOOKUP(Table8_16[[#This Row],[Customer_ID]],Table1__2[],8,FALSE) -> Gold | T4: =VLOOKUP(Table8_16[[#This Row],[Customer_ID]],Table1__2[],9,FALSE) -> Experienced | U4: =VLOOKUP(Table8_16[[#This Row],[Product_ID]],Table3__211[],2,FALSE) -> Men's Roll-On | V4: =VLOOKUP(Table8_16[[#This Row],[Product_ID]],Table3__211[],3,FALSE) -> Perfume | W4: =VLOOKUP(Table8_16[[#This Row],[Product_ID]],Table3__211[],4,FALSE) -> Beauty | X4: =VLOOKUP(Table8_16[[#This Row],[Product_ID]],Table3__211[],5,FALSE) -> Fragrance | Y4: =VLOOKUP(Table8_16[[#This Row],[Product_ID]],Table3__211[],6,FALSE) -> Sullivan and Sons | Z4: =VLOOKUP(Table8_16[[#This Row],[Product_ID]],Table3__211[],7,FALSE) -> 43.29 | AA4: =VLOOKUP(Table8_16[[#This Row],[Product_ID]],Table3__211[],8,FALSE) -> 267 | AB4: =VLOOKUP(Table8_16[[#This Row],[Store_ID]],Store!$A$2:$E$21,2,FALSE) -> Bean, Jones and Park | AC4: =VLOOKUP(Table8_16[[#This Row],[Store_ID]],Store!$A$2:$E$21,3,FALSE) -> West | AD4: =VLOOKUP(Table8_16[[#This Row],[Store_ID]],Store!$A$2:$E$21,4,FALSE) -> Thompsonborough | AE4: =VLOOKUP(Table8_16[[#This Row],[Store_ID]],Store!$A$2:$E$21,5,FALSE) -> Online | AF4: =VLOOKUP(Table8_16[[#This Row],[Store_ID]],Store!$A$2:$F$21,6,FALSE) -> Digital Store
A5: SALE3 | B5: 45259 | C5: CUST1346 | D5: PROD76 | E5: STORE8 | F5: 1 | G5: 921.51 | H5: 0.16 | I5: COD | J5: 774.0684 | K5: 774.0684 | L5: =_xlfn.IFS(Table8_1[[#This Row],[Unit_Price]]<500,"Low Price",Table8_1[[#This Row],[Unit_Price]]<2000,"Medium Price",Table8_1[[#This Row],[Unit_Price]]>=2000, "High Price") -> Medium Price | M5: =VLOOKUP(Table8_16[[#This Row],[Customer_ID]],Table1__2[],2,FALSE) -> John Jordan | N5: =VLOOKUP(Table8_16[[#This Row],[Customer_ID]],Table1__2[],3,FALSE) -> 58 | O5: =VLOOKUP(Table8_16[[#This Row],[Customer_ID]],Table1__2[],4,FALSE) -> Female | P5: =VLOOKUP(Table8_16[[#This Row],[Customer_ID]],Table1__2[],5,FALSE) -> Port Crystalberg | Q5: =VLOOKUP(Table8_16[[#This Row],[Customer_ID]],Table1__2[],6,FALSE) -> Tennessee | R5: =VLOOKUP(Table8_16[[#This Row],[Customer_ID]],Table1__2[],7,FALSE) -> USA | S5: =VLOOKUP(Table8_16[[#This Row],[Customer_ID]],Table1__2[],8,FALSE) -> Platinum | T5: =VLOOKUP(Table8_16[[#This Row],[Customer_ID]],Table1__2[],9,FALSE) -> Experienced | U5: =VLOOKUP(Table8_16[[#This Row],[Product_ID]],Table3__211[],2,FALSE) -> Wireless | V5: =VLOOKUP(Table8_16[[#This Row],[Product_ID]],Table3__211[],3,FALSE) -> Mouse | W5: =VLOOKUP(Table8_16[[#This Row],[Product_ID]],Table3__211[],4,FALSE) -> Electronics | X5: =VLOOKUP(Table8_16[[#This Row],[Product_ID]],Table3__211[],5,FALSE) -> Computer | Y5: =VLOOKUP(Table8_16[[#This Row],[Product_ID]],Table3__211[],6,FALSE) -> Larson Ltd | Z5: =VLOOKUP(Table8_16[[#This Row],[Product_ID]],Table3__211[],7,FALSE) -> 392.89 | AA5: =VLOOKUP(Table8_16[[#This Row],[Product_ID]],Table3__211[],8,FALSE) -> 320 | AB5: =VLOOKUP(Table8_16[[#This Row],[Store_ID]],Store!$A$2:$E$21,2,FALSE) -> Bean, Jones and Park | AC5: =VLOOKUP(Table8_16[[#This Row],[Store_ID]],Store!$A$2:$E$21,3,FALSE) -> West | AD5: =VLOOKUP(Table8_16[[#This Row],[Store_ID]],Store!$A$2:$E$21,4,FALSE) -> Thompsonborough | AE5: =VLOOKUP(Table8_16[[#This Row],[Store_ID]],Store!$A$2:$E$21,5,FALSE) -> Online | AF5: =VLOOKUP(Table8_16[[#This Row],[Store_ID]],Store!$A$2:$F$21,6,FALSE) -> Digital Store
A6: SALE4 | B6: 45297 | C6: CUST1493 | D6: PROD59 | E6: STORE5 | F6: 3 | G6: 745.3 | H6: 0.18 | I6: Credit Card | J6: 1833.438 | K6: 1833.438 | L6: =_xlfn.IFS(Table8_1[[#This Row],[Unit_Price]]<500,"Low Price",Table8_1[[#This Row],[Unit_Price]]<2000,"Medium Price",Table8_1[[#This Row],[Unit_Price]]>=2000, "High Price") -> Medium Price | M6: =VLOOKUP(Table8_16[[#This Row],[Customer_ID]],Table1__2[],2,FALSE) -> Amanda Powell | N6: =VLOOKUP(Table8_16[[#This Row],[Customer_ID]],Table1__2[],3,FALSE) -> 28 | O6: =VLOOKUP(Table8_16[[#This Row],[Customer_ID]],Table1__2[],4,FALSE) -> Male | P6: =VLOOKUP(Table8_16[[#This Row],[Customer_ID]],Table1__2[],5,FALSE) -> South William | Q6: =VLOOKUP(Table8_16[[#This Row],[Customer_ID]],Table1__2[],6,FALSE) -> Alabama | R6: =VLOOKUP(Table8_16[[#This Row],[Customer_ID]],Table1__2[],7,FALSE) -> USA | S6: =VLOOKUP(Table8_16[[#This Row],[Customer_ID]],Table1__2[],8,FALSE) -> Silver | T6: =VLOOKUP(Table8_16[[#This Row],[Customer_ID]],Table1__2[],9,FALSE) -> Entry level Professionel | U6: =VLOOKUP(Table8_16[[#This Row],[Product_ID]],Table3__211[],2,FALSE) -> Men's Hair Styling | V6: =VLOOKUP(Table8_16[[#This Row],[Product_ID]],Table3__211[],3,FALSE) -> Gel | W6: =VLOOKUP(Table8_16[[#This Row],[Product_ID]],Table3__211[],4,FALSE) -> Beauty | X6: =VLOOKUP(Table8_16[[#This Row],[Product_ID]],Table3__211[],5,FALSE) -> Haircare | Y6: =VLOOKUP(Table8_16[[#This Row],[Product_ID]],Table3__211[],6,FALSE) -> Cline-Mccarthy | Z6: =VLOOKUP(Table8_16[[#This Row],[Product_ID]],Table3__211[],7,FALSE) -> 17.31 | AA6: =VLOOKUP(Table8_16[[#This Row],[Product_ID]],Table3__211[],8,FALSE) -> 399 | AB6: =VLOOKUP(Table8_16[[#This Row],[Store_ID]],Store!$A$2:$E$21,2,FALSE) -> Gray Ltd | AC6: =VLOOKUP(Table8_16[[#This Row],[Store_ID]],Store!$A$2:$E$21,3,FALSE) -> North | AD6: =VLOOKUP(Table8_16[[#This Row],[Store_ID]],Store!$A$2:$E$21,4,FALSE) -> New Michaelchester | AE6: =VLOOKUP(Table8_16[[#This Row],[Store_ID]],Store!$A$2:$E$21,5,FALSE) -> Outlet | AF6: =VLOOKUP(Table8_16[[#This Row],[Store_ID]],Store!$A$2:$F$21,6,FALSE) -> Physical Store
A7: SALE5 | B7: 45499 | C7: CUST1116 | D7: PROD15 | E7: STORE7 | F7: 3 | G7: 147.01 | H7: 0.19 | I7: COD | J7: 357.2343 | K7: 357.2343 | L7: =_xlfn.IFS(Table8_1[[#This Row],[Unit_Price]]<500,"Low Price",Table8_1[[#This Row],[Unit_Price]]<2000,"Medium Price",Table8_1[[#This Row],[Unit_Price]]>=2000, "High Price") -> Low Price | M7: =VLOOKUP(Table8_16[[#This Row],[Customer_ID]],Table1__2[],2,FALSE) -> Anthony Phillips | N7: =VLOOKUP(Table8_16[[#This Row],[Customer_ID]],Table1__2[],3,FALSE) -> 18 | O7: =VLOOKUP(Table8_16[[#This Row],[Customer_ID]],Table1__2[],4,FALSE) -> Female | P7: =VLOOKUP(Table8_16[[#This Row],[Customer_ID]],Table1__2[],5,FALSE) -> North Davidport | Q7: =VLOOKUP(Table8_16[[#This Row],[Customer_ID]],Table1__2[],6,FALSE) -> Rhode Island | R7: =VLOOKUP(Table8_16[[#This Row],[Customer_ID]],Table1__2[],7,FALSE) -> USA | S7: =VLOOKUP(Table8_16[[#This Row],[Customer_ID]],Table1__2[],8,FALSE) -> Platinum | T7: =VLOOKUP(Table8_16[[#This Row],[Customer_ID]],Table1__2[],9,FALSE) -> Teenage | U7: =VLOOKUP(Table8_16[[#This Row],[Product_ID]],Table3__211[],2,FALSE) -> 4K Home | V7: =VLOOKUP(Table8_16[[#This Row],[Product_ID]],Table3__211[],3,FALSE) -> Projector | W7: =VLOOKUP(Table8_16[[#This Row],[Product_ID]],Table3__211[],4,FALSE) -> Electronics | X7: =VLOOKUP(Table8_16[[#This Row],[Product_ID]],Table3__211[],5,FALSE) -> Appliances | Y7: =VLOOKUP(Table8_16[[#This Row],[Product_ID]],Table3__211[],6,FALSE) -> Thomas LLC | Z7: =VLOOKUP(Table8_16[[#This Row],[Product_ID]],Table3__211[],7,FALSE) -> 465.34 | AA7: =VLOOKUP(Table8_16[[#This Row],[Product_ID]],Table3__211[],8,FALSE) -> 301 | AB7: =VLOOKUP(Table8_16[[#This Row],[Store_ID]],Store!$A$2:$E$21,2,FALSE) -> Martinez-Mullins | AC7: =VLOOKUP(Table8_16[[#This Row],[Store_ID]],Store!$A$2:$E$21,3,FALSE) -> South | AD7: =VLOOKUP(Table8_16[[#This Row],[Store_ID]],Store!$A$2:$E$21,4,FALSE) -> Williamsfurt | AE7: =VLOOKUP(Table8_16[[#This Row],[Store_ID]],Store!$A$2:$E$21,5,FALSE) -> Online | AF7: =VLOOKUP(Table8_16[[#This Row],[Store_ID]],Store!$A$2:$F$21,6,FALSE) -> Digital Store
A8: SALE6 | B8: 45850 | C8: CUST1016 | D8: PROD56 | E8: STORE4 | F8: 2 | G8: 785.31 | H8: 0.15 | I8: PayPal | J8: 1335.027 | K8: 1335.027 | L8: =_xlfn.IFS(Table8_1[[#This Row],[Unit_Price]]<500,"Low Price",Table8_1[[#This Row],[Unit_Price]]<2000,"Medium Price",Table8_1[[#This Row],[Unit_Price]]>=2000, "High Price") -> Medium Price | M8: =VLOOKUP(Table8_16[[#This Row],[Customer_ID]],Table1__2[],2,FALSE) -> John Scott | N8: =VLOOKUP(Table8_16[[#This Row],[Customer_ID]],Table1__2[],3,FALSE) -> 24 | O8: =VLOOKUP(Table8_16[[#This Row],[Customer_ID]],Table1__2[],4,FALSE) -> Female | P8: =VLOOKUP(Table8_16[[#This Row],[Customer_ID]],Table1__2[],5,FALSE) -> South Christopher | Q8: =VLOOKUP(Table8_16[[#This Row],[Customer_ID]],Table1__2[],6,FALSE) -> Pennsylvania | R8: =VLOOKUP(Table8_16[[#This Row],[Customer_ID]],Table1__2[],7,FALSE) -> USA | S8: =VLOOKUP(Table8_16[[#This Row],[Customer_ID]],Table1__2[],8,FALSE) -> Bronze | T8: =VLOOKUP(Table8_16[[#This Row],[Customer_ID]],Table1__2[],9,FALSE) -> Students | U8: =VLOOKUP(Table8_16[[#This Row],[Product_ID]],Table3__211[],2,FALSE) -> Premium Blanket | V8: =VLOOKUP(Table8_16[[#This Row],[Product_ID]],Table3__211[],3,FALSE) -> Throw | W8: =VLOOKUP(Table8_16[[#This Row],[Product_ID]],Table3__211[],4,FALSE) -> Home | X8: =VLOOKUP(Table8_16[[#This Row],[Product_ID]],Table3__211[],5,FALSE) -> Decor | Y8: =VLOOKUP(Table8_16[[#This Row],[Product_ID]],Table3__211[],6,FALSE) -> Hernandez, Kennedy and Porter | Z8: =VLOOKUP(Table8_16[[#This Row],[Product_ID]],Table3__211[],7,FALSE) -> 461.47 | AA8: =VLOOKUP(Table8_16[[#This Row],[Product_ID]],Table3__211[],8,FALSE) -> 190 | AB8: =VLOOKUP(Table8_16[[#This Row],[Store_ID]],Store!$A$2:$E$21,2,FALSE) -> Alexander Group | AC8: =VLOOKUP(Table8_16[[#This Row],[Store_ID]],Store!$A$2:$E$21,3,FALSE) -> South | AD8: =VLOOKUP(Table8_16[[#This Row],[Store_ID]],Store!$A$2:$E$21,4,FALSE) -> Port Sharon | AE8: =VLOOKUP(Table8_16[[#This Row],[Store_ID]],Store!$A$2:$E$21,5,FALSE) -> Online | AF8: =VLOOKUP(Table8_16[[#This Row],[Store_ID]],Store!$A$2:$F$21,6,FALSE) -> Digital Store
A9: SALE7 | B9: 45248 | C9: CUST1152 | D9: PROD70 | E9: STORE8 | F9: 4 | G9: 342.39 | H9: 0.23 | I9: PayPal | J9: 1054.5612 | K9: 1054.5612 | L9: =_xlfn.IFS(Table8_1[[#This Row],[Unit_Price]]<500,"Low Price",Table8_1[[#This Row],[Unit_Price]]<2000,"Medium Price",Table8_1[[#This Row],[Unit_Price]]>=2000, "High Price") -> Low Price | M9: =VLOOKUP(Table8_16[[#This Row],[Customer_ID]],Table1__2[],2,FALSE) -> Patrick Roberts | N9: =VLOOKUP(Table8_16[[#This Row],[Customer_ID]],Table1__2[],3,FALSE) -> 41 | O9: =VLOOKUP(Table8_16[[#This Row],[Customer_ID]],Table1__2[],4,FALSE) -> Female | P9: =VLOOKUP(Table8_16[[#This Row],[Customer_ID]],Table1__2[],5,FALSE) -> Jaredville | Q9: =VLOOKUP(Table8_16[[#This Row],[Customer_ID]],Table1__2[],6,FALSE) -> Missouri | R9: =VLOOKUP(Table8_16[[#This Row],[Customer_ID]],Table1__2[],7,FALSE) -> USA | S9: =VLOOKUP(Table8_16[[#This Row],[Customer_ID]],Table1__2[],8,FALSE) -> Platinum | T9: =VLOOKUP(Table8_16[[#This Row],[Customer_ID]],Table1__2[],9,FALSE) -> Experienced | U9: =VLOOKUP(Table8_16[[#This Row],[Product_ID]],Table3__211[],2,FALSE) -> Kitchen Storage | V9: =VLOOKUP(Table8_16[[#This Row],[Product_ID]],Table3__211[],3,FALSE) -> Rack | W9: =VLOOKUP(Table8_16[[#This Row],[Product_ID]],Table3__211[],4,FALSE) -> Home | X9: =VLOOKUP(Table8_16[[#This Row],[Product_ID]],Table3__211[],5,FALSE) -> Storage | Y9: =VLOOKUP(Table8_16[[#This Row],[Product_ID]],Table3__211[],6,FALSE) -> Duran Group | Z9: =VLOOKUP(Table8_16[[#This Row],[Product_ID]],Table3__211[],7,FALSE) -> 138.05 | AA9: =VLOOKUP(Table8_16[[#This Row],[Product_ID]],Table3__211[],8,FALSE) -> 89 | AB9: =VLOOKUP(Table8_16[[#This Row],[Store_ID]],Store!$A$2:$E$21,2,FALSE) -> Bean, Jones and Park | AC9: =VLOOKUP(Table8_16[[#This Row],[Store_ID]],Store!$A$2:$E$21,3,FALSE) -> West | AD9: =VLOOKUP(Table8_16[[#This Row],[Store_ID]],Store!$A$2:$E$21,4,FALSE) -> Thompsonborough | AE9: =VLOOKUP(Table8_16[[#This Row],[Store_ID]],Store!$A$2:$E$21,5,FALSE) -> Online | AF9: =VLOOKUP(Table8_16[[#This Row],[Store_ID]],Store!$A$2:$F$21,6,FALSE) -> Digital Store
A10: SALE8 | B10: 45781 | C10: CUST1187 | D10: PROD99 | E10: STORE5 | F10: 2 | G10: 448.25 | H10: 0.07 | I10: PayPal | J10: 1250.6175 | K10: 833.745 | L10: =_xlfn.IFS(Table8_1[[#This Row],[Unit_Price]]<500,"Low Price",Table8_1[[#This Row],[Unit_Price]]<2000,"Medium Price",Table8_1[[#This Row],[Unit_Price]]>=2000, "High Price") -> Low Price | M10: =VLOOKUP(Table8_16[[#This Row],[Customer_ID]],Table1__2[],2,FALSE) -> Dr. Suzanne Bullock | N10: =VLOOKUP(Table8_16[[#This Row],[Customer_ID]],Table1__2[],3,FALSE) -> 60 | O10: =VLOOKUP(Table8_16[[#This Row],[Customer_ID]],Table1__2[],4,FALSE) -> Female | P10: =VLOOKUP(Table8_16[[#This Row],[Customer_ID]],Table1__2[],5,FALSE) -> Lake Blaketon | Q10: =VLOOKUP(Table8_16[[#This Row],[Customer_ID]],Table1__2[],6,FALSE) -> Alabama | R10: =VLOOKUP(Table8_16[[#This Row],[Customer_ID]],Table1__2[],7,FALSE) -> USA | S10: =VLOOKUP(Table8_16[[#This Row],[Customer_ID]],Table1__2[],8,FALSE) -> Platinum | T10: =VLOOKUP(Table8_16[[#This Row],[Customer_ID]],Table1__2[],9,FALSE) -> Experienced | U10: =VLOOKUP(Table8_16[[#This Row],[Product_ID]],Table3__211[],2,FALSE) -> Stainless Steel Cookware | V10: =VLOOKUP(Table8_16[[#This Row],[Product_ID]],Table3__211[],3,FALSE) -> Set | W10: =VLOOKUP(Table8_16[[#This Row],[Product_ID]],Table3__211[],4,FALSE) -> Home | X10: =VLOOKUP(Table8_16[[#This Row],[Product_ID]],Table3__211[],5,FALSE) -> Kitchen | Y10: =VLOOKUP(Table8_16[[#This Row],[Product_ID]],Table3__211[],6,FALSE) -> Campbell Ltd | Z10: =VLOOKUP(Table8_16[[#This Row],[Product_ID]],Table3__211[],7,FALSE) -> 201.41 | AA10: =VLOOKUP(Table8_16[[#This Row],[Product_ID]],Table3__211[],8,FALSE) -> 146 | AB10: =VLOOKUP(Table8_16[[#This Row],[Store_ID]],Store!$A$2:$E$21,2,FALSE) -> Gray Ltd | AC10: =VLOOKUP(Table8_16[[#This Row],[Store_ID]],Store!$A$2:$E$21,3,FALSE) -> North | AD10: =VLOOKUP(Table8_16[[#This Row],[Store_ID]],Store!$A$2:$E$21,4,FALSE) -> New Michaelchester | AE10: =VLOOKUP(Table8_16[[#This Row],[Store_ID]],Store!$A$2:$E$21,5,FALSE) -> Outlet | AF10: =VLOOKUP(Table8_16[[#This Row],[Store_ID]],Store!$A$2:$F$21,6,FALSE) -> Physical Store
A11: SALE9 | B11: 45869 | C11: CUST1464 | D11: PROD33 | E11: STORE0 | F11: 2 | G11: 873.17 | H11: 0.23 | I11: PayPal | J11: 1344.6818 | K11: 1344.6818 | L11: =_xlfn.IFS(Table8_1[[#This Row],[Unit_Price]]<500,"Low Price",Table8_1[[#This Row],[Unit_Price]]<2000,"Medium Price",Table8_1[[#This Row],[Unit_Price]]>=2000, "High Price") -> Medium Price | M11: =VLOOKUP(Table8_16[[#This Row],[Customer_ID]],Table1__2[],2,FALSE) -> David Pierce | N11: =VLOOKUP(Table8_16[[#This Row],[Customer_ID]],Table1__2[],3,FALSE) -> 45 | O11: =VLOOKUP(Table8_16[[#This Row],[Customer_ID]],Table1__2[],4,FALSE) -> Female | P11: =VLOOKUP(Table8_16[[#This Row],[Customer_ID]],Table1__2[],5,FALSE) -> Grayland | Q11: =VLOOKUP(Table8_16[[#This Row],[Customer_ID]],Table1__2[],6,FALSE) -> Washington | R11: =VLOOKUP(Table8_16[[#This Row],[Customer_ID]],Table1__2[],7,FALSE) -> USA | S11: =VLOOKUP(Table8_16[[#This Row],[Customer_ID]],Table1__2[],8,FALSE) -> Platinum | T11: =VLOOKUP(Table8_16[[#This Row],[Customer_ID]],Table1__2[],9,FALSE) -> Experienced | U11: =VLOOKUP(Table8_16[[#This Row],[Product_ID]],Table3__211[],2,FALSE) -> Modern Wall | V11: =VLOOKUP(Table8_16[[#This Row],[Product_ID]],Table3__211[],3,FALSE) -> Clock | W11: =VLOOKUP(Table8_16[[#This Row],[Product_ID]],Table3__211[],4,FALSE) -> Home | X11: =VLOOKUP(Table8_16[[#This Row],[Product_ID]],Table3__211[],5,FALSE) -> Decor | Y11: =VLOOKUP(Table8_16[[#This Row],[Product_ID]],Table3__211[],6,FALSE) -> Weiss-Watson | Z11: =VLOOKUP(Table8_16[[#This Row],[Product_ID]],Table3__211[],7,FALSE) -> 179.77 | AA11: =VLOOKUP(Table8_16[[#This Row],[Product_ID]],Table3__211[],8,FALSE) -> 305 | AB11: =VLOOKUP(Table8_16[[#This Row],[Store_ID]],Store!$A$2:$E$21,2,FALSE) -> Rivera-Warner | AC11: =VLOOKUP(Table8_16[[#This Row],[Store_ID]],Store!$A$2:$E$21,3,FALSE) -> East | AD11: =VLOOKUP(Table8_16[[#This Row],[Store_ID]],Store!$A$2:$E$21,4,FALSE) -> Washingtonfurt | AE11: =VLOOKUP(Table8_16[[#This Row],[Store_ID]],Store!$A$2:$E$21,5,FALSE) -> Flagship | AF11: =VLOOKUP(Table8_16[[#This Row],[Store_ID]],Store!$A$2:$F$21,6,FALSE) -> Physical Store
A12: SALE10 | B12: 45335 | C12: CUST1065 | D12: PROD24 | E12: STORE14 | F12: 1 | G12: 278.63 | H12: 0.07 | I12: Credit Card | J12: 259.1259 | K12: 259.1259 | L12: =_xlfn.IFS(Table8_1[[#This Row],[Unit_Price]]<500,"Low Price",Table8_1[[#This Row],[Unit_Price]]<2000,"Medium Price",Table8_1[[#This Row],[Unit_Price]]>=2000, "High Price") -> Low Price | M12: =VLOOKUP(Table8_16[[#This Row],[Customer_ID]],Table1__2[],2,FALSE) -> Michael Thomas | N12: =VLOOKUP(Table8_16[[#This Row],[Customer_ID]],Table1__2[],3,FALSE) -> 21 | O12: =VLOOKUP(Table8_16[[#This Row],[Customer_ID]],Table1__2[],4,FALSE) -> Female | P12: =VLOOKUP(Table8_16[[#This Row],[Customer_ID]],Table1__2[],5,FALSE) -> Woodmouth | Q12: =VLOOKUP(Table8_16[[#This Row],[Customer_ID]],Table1__2[],6,FALSE) -> Nevada | R12: =VLOOKUP(Table8_16[[#This Row],[Customer_ID]],Table1__2[],7,FALSE) -> USA | S12: =VLOOKUP(Table8_16[[#This Row],[Customer_ID]],Table1__2[],8,FALSE) -> Silver | T12: =VLOOKUP(Table8_16[[#This Row],[Customer_ID]],Table1__2[],9,FALSE) -> Students | U12: =VLOOKUP(Table8_16[[#This Row],[Product_ID]],Table3__211[],2,FALSE) -> Foldable Camping | V12: =VLOOKUP(Table8_16[[#This Row],[Product_ID]],Table3__211[],3,FALSE) -> Chair | W12: =VLOOKUP(Table8_16[[#This Row],[Product_ID]],Table3__211[],4,FALSE) -> Sports | X12: =VLOOKUP(Table8_16[[#This Row],[Product_ID]],Table3__211[],5,FALSE) -> Outdoor | Y12: =VLOOKUP(Table8_16[[#This Row],[Product_ID]],Table3__211[],6,FALSE) -> Cook Ltd | Z12: =VLOOKUP(Table8_16[[#This Row],[Product_ID]],Table3__211[],7,FALSE) -> 166.06 | AA12: =VLOOKUP(Table8_16[[#This Row],[Product_ID]],Table3__211[],8,FALSE) -> 340 | AB12: =VLOOKUP(Table8_16[[#This Row],[Store_ID]],Store!$A$2:$E$21,2,FALSE) -> Mcdonald Inc | AC12: =VLOOKUP(Table8_16[[#This Row],[Store_ID]],Store!$A$2:$E$21,3,FALSE) -> South | AD12: =VLOOKUP(Table8_16[[#This Row],[Store_ID]],Store!$A$2:$E$21,4,FALSE) -> Christopherland | AE12: =VLOOKUP(Table8_16[[#This Row],[Store_ID]],Store!$A$2:$E$21,5,FALSE) -> Outlet | AF12: =VLOOKUP(Table8_16[[#This Row],[Store_ID]],Store!$A$2:$F$21,6,FALSE) -> Physical Store
A13: SALE11 | B13: 45801 | C13: CUST1320 | D13: PROD39 | E13: STORE1 | F13: 4 | G13: 286.92 | H13: 0.17 | I13: Credit Card | J13: 952.5744 | K13: 952.5744 | L13: =_xlfn.IFS(Table8_1[[#This Row],[Unit_Price]]<500,"Low Price",Table8_1[[#This Row],[Unit_Price]]<2000,"Medium Price",Table8_1[[#This Row],[Unit_Price]]>=2000, "High Price") -> Low Price | M13: =VLOOKUP(Table8_16[[#This Row],[Customer_ID]],Table1__2[],2,FALSE) -> Jessica Gonzalez | N13: =VLOOKUP(Table8_16[[#This Row],[Customer_ID]],Table1__2[],3,FALSE) -> 34 | O13: =VLOOKUP(Table8_16[[#This Row],[Customer_ID]],Table1__2[],4,FALSE) -> Female | P13: =VLOOKUP(Table8_16[[#This Row],[Customer_ID]],Table1__2[],5,FALSE) -> South Darrenland | Q13: =VLOOKUP(Table8_16[[#This Row],[Customer_ID]],Table1__2[],6,FALSE) -> Iowa | R13: =VLOOKUP(Table8_16[[#This Row],[Customer_ID]],Table1__2[],7,FALSE) -> USA | S13: =VLOOKUP(Table8_16[[#This Row],[Customer_ID]],Table1__2[],8,FALSE) -> Bronze | T13: =VLOOKUP(Table8_16[[#This Row],[Customer_ID]],Table1__2[],9,FALSE) -> Experienced | U13: =VLOOKUP(Table8_16[[#This Row],[Product_ID]],Table3__211[],2,FALSE) -> Portable Power | V13: =VLOOKUP(Table8_16[[#This Row],[Product_ID]],Table3__211[],3,FALSE) -> Bank | W13: =VLOOKUP(Table8_16[[#This Row],[Product_ID]],Table3__211[],4,FALSE) -> Electronics | X13: =VLOOKUP(Table8_16[[#This Row],[Product_ID]],Table3__211[],5,FALSE) -> Mobile | Y13: =VLOOKUP(Table8_16[[#This Row],[Product_ID]],Table3__211[],6,FALSE) -> Cummings and Sons | Z13: =VLOOKUP(Table8_16[[#This Row],[Product_ID]],Table3__211[],7,FALSE) -> 326.06 | AA13: =VLOOKUP(Table8_16[[#This Row],[Product_ID]],Table3__211[],8,FALSE) -> 301 | AB13: =VLOOKUP(Table8_16[[#This Row],[Store_ID]],Store!$A$2:$E$21,2,FALSE) -> Martinez, Adkins and Johnson | AC13: =VLOOKUP(Table8_16[[#This Row],[Store_ID]],Store!$A$2:$E$21,3,FALSE) -> North | AD13: =VLOOKUP(Table8_16[[#This Row],[Store_ID]],Store!$A$2:$E$21,4,FALSE) -> Danielmouth | AE13: =VLOOKUP(Table8_16[[#This Row],[Store_ID]],Store!$A$2:$E$21,5,FALSE) -> Flagship | AF13: =VLOOKUP(Table8_16[[#This Row],[Store_ID]],Store!$A$2:$F$21,6,FALSE) -> Physical Store
... A65: SALE63 | B65: 45927 | C65: CUST1126 | D65: PROD89 | E65: STORE12 | F65: 2 | G65: 121.37 | H65: 0.05 | I65: Credit Card | J65: 230.603 | K65: 230.603 | L65: =_xlfn.IFS(Table8_1[[#This Row],[Unit_Price]]<500,"Low Price",Table8_1[[#This Row],[Unit_Price]]<2000,"Medium Price",Table8_1[[#This Row],[Unit_Price]]>=2000, "High Price") -> Low Price | M65: =VLOOKUP(Table8_16[[#This Row],[Customer_ID]],Table1__2[],2,FALSE) -> James Wolfe | N65: =VLOOKUP(Table8_16[[#This Row],[Customer_ID]],Table1__2[],3,FALSE) -> 62 | O65: =VLOOKUP(Table8_16[[#This Row],[Customer_ID]],Table1__2[],4,FALSE) -> Female | P65: =VLOOKUP(Table8_16[[#This Row],[Customer_ID]],Table1__2[],5,FALSE) -> Benjaminton | Q65: =VLOOKUP(Table8_16[[#This Row],[Customer_ID]],Table1__2[],6,FALSE) -> Arizona | R65: =VLOOKUP(Table8_16[[#This Row],[Customer_ID]],Table1__2[],7,FALSE) -> USA | S65: =VLOOKUP(Table8_16[[#This Row],[Customer_ID]],Table1__2[],8,FALSE) -> Gold | T65: =VLOOKUP(Table8_16[[#This Row],[Customer_ID]],Table1__2[],9,FALSE) -> Retired | U65: =VLOOKUP(Table8_16[[#This Row],[Product_ID]],Table3__211[],2,FALSE) -> Face Foundation | V65: =VLOOKUP(Table8_16[[#This Row],[Product_ID]],Table3__211[],3,FALSE) -> Kit | W65: =VLOOKUP(Table8_16[[#This Row],[Product_ID]],Table3__211[],4,FALSE) -> Beauty | X65: =VLOOKUP(Table8_16[[#This Row],[Product_ID]],Table3__211[],5,FALSE) -> Makeup | Y65: =VLOOKUP(Table8_16[[#This Row],[Product_ID]],Table3__211[],6,FALSE) -> Taylor-Elliott | Z65: =VLOOKUP(Table8_16[[#This Row],[Product_ID]],Table3__211[],7,FALSE) -> 183.04 | AA65: =VLOOKUP(Table8_16[[#This Row],[Product_ID]],Table3__211[],8,FALSE) -> 457 | AB65: =VLOOKUP(Table8_16[[#This Row],[Store_ID]],Store!$A$2:$E$21,2,FALSE) -> Thomas, Bridges and Harris | AC65: =VLOOKUP(Table8_16[[#This Row],[Store_ID]],Store!$A$2:$E$21,3,FALSE) -> North | AD65: =VLOOKUP(Table8_16[[#This Row],[Store_ID]],Store!$A$2:$E$21,4,FALSE) -> Sabrinatown | AE65: =VLOOKUP(Table8_16[[#This Row],[Store_ID]],Store!$A$2:$E$21,5,FALSE) -> Online | AF65: =VLOOKUP(Table8_16[[#This Row],[Store_ID]],Store!$A$2:$F$21,6,FALSE) -> Digital Store
A66: SALE64 | B66: 45914 | C66: CUST1255 | D66: PROD53 | E66: STORE10 | F66: 3 | G66: 480.06 | H66: 0.01 | I66: Credit Card | K66: 1425.7782 | L66: =_xlfn.IFS(Table8_1[[#This Row],[Unit_Price]]<500,"Low Price",Table8_1[[#This Row],[Unit_Price]]<2000,"Medium Price",Table8_1[[#This Row],[Unit_Price]]>=2000, "High Price") -> Low Price | M66: =VLOOKUP(Table8_16[[#This Row],[Customer_ID]],Table1__2[],2,FALSE) -> Damon Perez | N66: =VLOOKUP(Table8_16[[#This Row],[Customer_ID]],Table1__2[],3,FALSE) -> 21 | O66: =VLOOKUP(Table8_16[[#This Row],[Customer_ID]],Table1__2[],4,FALSE) -> Male | P66: =VLOOKUP(Table8_16[[#This Row],[Customer_ID]],Table1__2[],5,FALSE) -> Jasonton | Q66: =VLOOKUP(Table8_16[[#This Row],[Customer_ID]],Table1__2[],6,FALSE) -> Ohio | R66: =VLOOKUP(Table8_16[[#This Row],[Customer_ID]],Table1__2[],7,FALSE) -> USA | S66: =VLOOKUP(Table8_16[[#This Row],[Customer_ID]],Table1__2[],8,FALSE) -> Gold | T66: =VLOOKUP(Table8_16[[#This Row],[Customer_ID]],Table1__2[],9,FALSE) -> Students | U66: =VLOOKUP(Table8_16[[#This Row],[Product_ID]],Table3__211[],2,FALSE) -> Men's Track | V66: =VLOOKUP(Table8_16[[#This Row],[Product_ID]],Table3__211[],3,FALSE) -> Pants | W66: =VLOOKUP(Table8_16[[#This Row],[Product_ID]],Table3__211[],4,FALSE) -> Clothing | X66: =VLOOKUP(Table8_16[[#This Row],[Product_ID]],Table3__211[],5,FALSE) -> Bottoms | Y66: =VLOOKUP(Table8_16[[#This Row],[Product_ID]],Table3__211[],6,FALSE) -> Hamilton, Woods and Walker | Z66: =VLOOKUP(Table8_16[[#This Row],[Product_ID]],Table3__211[],7,FALSE) -> 386.56 | AA66: =VLOOKUP(Table8_16[[#This Row],[Product_ID]],Table3__211[],8,FALSE) -> 125 | AB66: =VLOOKUP(Table8_16[[#This Row],[Store_ID]],Store!$A$2:$E$21,2,FALSE) -> Hill, Wagner and Ballard | AC66: =VLOOKUP(Table8_16[[#This Row],[Store_ID]],Store!$A$2:$E$21,3,FALSE) -> East | AD66: =VLOOKUP(Table8_16[[#This Row],[Store_ID]],Store!$A$2:$E$21,4,FALSE) -> East Davidville | AE66: =VLOOKUP(Table8_16[[#This Row],[Store_ID]],Store!$A$2:$E$21,5,FALSE) -> Online | AF66: =VLOOKUP(Table8_16[[#This Row],[Store_ID]],Store!$A$2:$F$21,6,FALSE) -> Digital Store
A67: SALE65 | B67: 45290 | C67: CUST1162 | D67: PROD99 | E67: STORE17 | F67: 2 | G67: 856.57 | H67: 0.24 | I67: Credit Card | J67: 1301.9864 | K67: 1301.9864 | L67: =_xlfn.IFS(Table8_1[[#This Row],[Unit_Price]]<500,"Low Price",Table8_1[[#This Row],[Unit_Price]]<2000,"Medium Price",Table8_1[[#This Row],[Unit_Price]]>=2000, "High Price") -> Medium Price | M67: =VLOOKUP(Table8_16[[#This Row],[Customer_ID]],Table1__2[],2,FALSE) -> Mariah Brown | N67: =VLOOKUP(Table8_16[[#This Row],[Customer_ID]],Table1__2[],3,FALSE) -> 37 | O67: =VLOOKUP(Table8_16[[#This Row],[Customer_ID]],Table1__2[],4,FALSE) -> Male | P67: =VLOOKUP(Table8_16[[#This Row],[Customer_ID]],Table1__2[],5,FALSE) -> Palmerbury | Q67: =VLOOKUP(Table8_16[[#This Row],[Customer_ID]],Table1__2[],6,FALSE) -> Tennessee | R67: =VLOOKUP(Table8_16[[#This Row],[Customer_ID]],Table1__2[],7,FALSE) -> USA | S67: =VLOOKUP(Table8_16[[#This Row],[Customer_ID]],Table1__2[],8,FALSE) -> Silver | T67: =VLOOKUP(Table8_16[[#This Row],[Customer_ID]],Table1__2[],9,FALSE) -> Experienced | U67: =VLOOKUP(Table8_16[[#This Row],[Product_ID]],Table3__211[],2,FALSE) -> Stainless Steel Cookware | V67: =VLOOKUP(Table8_16[[#This Row],[Product_ID]],Table3__211[],3,FALSE) -> Set | W67: =VLOOKUP(Table8_16[[#This Row],[Product_ID]],Table3__211[],4,FALSE) -> Home | X67: =VLOOKUP(Table8_16[[#This Row],[Product_ID]],Table3__211[],5,FALSE) -> Kitchen | Y67: =VLOOKUP(Table8_16[[#This Row],[Product_ID]],Table3__211[],6,FALSE) -> Campbell Ltd | Z67: =VLOOKUP(Table8_16[[#This Row],[Product_ID]],Table3__211[],7,FALSE) -> 201.41 | AA67: =VLOOKUP(Table8_16[[#This Row],[Product_ID]],Table3__211[],8,FALSE) -> 146 | AB67: =VLOOKUP(Table8_16[[#This Row],[Store_ID]],Store!$A$2:$E$21,2,FALSE) -> Holloway Ltd | AC67: =VLOOKUP(Table8_16[[#This Row],[Store_ID]],Store!$A$2:$E$21,3,FALSE) -> North | AD67: =VLOOKUP(Table8_16[[#This Row],[Store_ID]],Store!$A$2:$E$21,4,FALSE) -> Bensonhaven | AE67: =VLOOKUP(Table8_16[[#This Row],[Store_ID]],Store!$A$2:$E$21,5,FALSE) -> Flagship | AF67: =VLOOKUP(Table8_16[[#This Row],[Store_ID]],Store!$A$2:$F$21,6,FALSE) -> Physical Store
A68: SALE66 | B68: 45213 | C68: CUST1269 | D68: PROD77 | E68: STORE2 | F68: 4 | G68: 814.25 | H68: 0.18 | I68: Credit Card | J68: 2670.74 | K68: 2670.74 | L68: =_xlfn.IFS(Table8_1[[#This Row],[Unit_Price]]<500,"Low Price",Table8_1[[#This Row],[Unit_Price]]<2000,"Medium Price",Table8_1[[#This Row],[Unit_Price]]>=2000, "High Price") -> Medium Price | M68: =VLOOKUP(Table8_16[[#This Row],[Customer_ID]],Table1__2[],2,FALSE) -> Tyrone Olson | N68: =VLOOKUP(Table8_16[[#This Row],[Customer_ID]],Table1__2[],3,FALSE) -> 45 | O68: =VLOOKUP(Table8_16[[#This Row],[Customer_ID]],Table1__2[],4,FALSE) -> Female | P68: =VLOOKUP(Table8_16[[#This Row],[Customer_ID]],Table1__2[],5,FALSE) -> Emilytown | Q68: =VLOOKUP(Table8_16[[#This Row],[Customer_ID]],Table1__2[],6,FALSE) -> California | R68: =VLOOKUP(Table8_16[[#This Row],[Customer_ID]],Table1__2[],7,FALSE) -> USA | S68: =VLOOKUP(Table8_16[[#This Row],[Customer_ID]],Table1__2[],8,FALSE) -> Silver | T68: =VLOOKUP(Table8_16[[#This Row],[Customer_ID]],Table1__2[],9,FALSE) -> Experienced | U68: =VLOOKUP(Table8_16[[#This Row],[Product_ID]],Table3__211[],2,FALSE) -> WiFi Mesh | V68: =VLOOKUP(Table8_16[[#This Row],[Product_ID]],Table3__211[],3,FALSE) -> Router | W68: =VLOOKUP(Table8_16[[#This Row],[Product_ID]],Table3__211[],4,FALSE) -> Electronics | X68: =VLOOKUP(Table8_16[[#This Row],[Product_ID]],Table3__211[],5,FALSE) -> Appliances | Y68: =VLOOKUP(Table8_16[[#This Row],[Product_ID]],Table3__211[],6,FALSE) -> White, Reeves and Woods | Z68: =VLOOKUP(Table8_16[[#This Row],[Product_ID]],Table3__211[],7,FALSE) -> 480.9 | AA68: =VLOOKUP(Table8_16[[#This Row],[Product_ID]],Table3__211[],8,FALSE) -> 104 | AB68: =VLOOKUP(Table8_16[[#This Row],[Store_ID]],Store!$A$2:$E$21,2,FALSE) -> Black-Horn | AC68: =VLOOKUP(Table8_16[[#This Row],[Store_ID]],Store!$A$2:$E$21,3,FALSE) -> South | AD68: =VLOOKUP(Table8_16[[#This Row],[Store_ID]],Store!$A$2:$E$21,4,FALSE) -> North Nancyview | AE68: =VLOOKUP(Table8_16[[#This Row],[Store_ID]],Store!$A$2:$E$21,5,FALSE) -> Outlet | AF68: =VLOOKUP(Table8_16[[#This Row],[Store_ID]],Store!$A$2:$F$21,6,FALSE) -> Physical Store
A69: SALE67 | B69: 45255 | C69: CUST1483 | D69: PROD12 | E69: STORE2 | F69: 1 | G69: 989.17 | H69: 0.2 | I69: PayPal | J69: 791.336 | K69: 791.336 | L69: =_xlfn.IFS(Table8_1[[#This Row],[Unit_Price]]<500,"Low Price",Table8_1[[#This Row],[Unit_Price]]<2000,"Medium Price",Table8_1[[#This Row],[Unit_Price]]>=2000, "High Price") -> Medium Price | M69: =VLOOKUP(Table8_16[[#This Row],[Customer_ID]],Table1__2[],2,FALSE) -> Sarah Smith | N69: =VLOOKUP(Table8_16[[#This Row],[Customer_ID]],Table1__2[],3,FALSE) -> 48 | O69: =VLOOKUP(Table8_16[[#This Row],[Customer_ID]],Table1__2[],4,FALSE) -> Male | P69: =VLOOKUP(Table8_16[[#This Row],[Customer_ID]],Table1__2[],5,FALSE) -> East Rodney | Q69: =VLOOKUP(Table8_16[[#This Row],[Customer_ID]],Table1__2[],6,FALSE) -> Nevada | R69: =VLOOKUP(Table8_16[[#This Row],[Customer_ID]],Table1__2[],7,FALSE) -> USA | S69: =VLOOKUP(Table8_16[[#This Row],[Customer_ID]],Table1__2[],8,FALSE) -> Gold | T69: =VLOOKUP(Table8_16[[#This Row],[Customer_ID]],Table1__2[],9,FALSE) -> Experienced | U69: =VLOOKUP(Table8_16[[#This Row],[Product_ID]],Table3__211[],2,FALSE) -> Hair Strengthening | V69: =VLOOKUP(Table8_16[[#This Row],[Product_ID]],Table3__211[],3,FALSE) -> Shampoo | W69: =VLOOKUP(Table8_16[[#This Row],[Product_ID]],Table3__211[],4,FALSE) -> Beauty | X69: =VLOOKUP(Table8_16[[#This Row],[Product_ID]],Table3__211[],5,FALSE) -> Haircare | Y69: =VLOOKUP(Table8_16[[#This Row],[Product_ID]],Table3__211[],6,FALSE) -> Rice LLC | Z69: =VLOOKUP(Table8_16[[#This Row],[Product_ID]],Table3__211[],7,FALSE) -> 115.82 | AA69: =VLOOKUP(Table8_16[[#This Row],[Product_ID]],Table3__211[],8,FALSE) -> 460 | AB69: =VLOOKUP(Table8_16[[#This Row],[Store_ID]],Store!$A$2:$E$21,2,FALSE) -> Black-Horn | AC69: =VLOOKUP(Table8_16[[#This Row],[Store_ID]],Store!$A$2:$E$21,3,FALSE) -> South | AD69: =VLOOKUP(Table8_16[[#This Row],[Store_ID]],Store!$A$2:$E$21,4,FALSE) -> North Nancyview | AE69: =VLOOKUP(Table8_16[[#This Row],[Store_ID]],Store!$A$2:$E$21,5,FALSE) -> Outlet | AF69: =VLOOKUP(Table8_16[[#This Row],[Store_ID]],Store!$A$2:$F$21,6,FALSE) -> Physical Store
A70: SALE68 | B70: 45270 | C70: CUST1372 | D70: PROD72 | E70: STORE10 | F70: 4 | G70: 62.48 | H70: 0.18 | I70: Credit Card | J70: 204.9344 | K70: 204.9344 | L70: =_xlfn.IFS(Table8_1[[#This Row],[Unit_Price]]<500,"Low Price",Table8_1[[#This Row],[Unit_Price]]<2000,"Medium Price",Table8_1[[#This Row],[Unit_Price]]>=2000, "High Price") -> Low Price | M70: =VLOOKUP(Table8_16[[#This Row],[Customer_ID]],Table1__2[],2,FALSE) -> Jacqueline Anthony | N70: =VLOOKUP(Table8_16[[#This Row],[Customer_ID]],Table1__2[],3,FALSE) -> 28 | O70: =VLOOKUP(Table8_16[[#This Row],[Customer_ID]],Table1__2[],4,FALSE) -> Male | P70: =VLOOKUP(Table8_16[[#This Row],[Customer_ID]],Table1__2[],5,FALSE) -> Vincentside | Q70: =VLOOKUP(Table8_16[[#This Row],[Customer_ID]],Table1__2[],6,FALSE) -> Ohio | R70: =VLOOKUP(Table8_16[[#This Row],[Customer_ID]],Table1__2[],7,FALSE) -> USA | S70: =VLOOKUP(Table8_16[[#This Row],[Customer_ID]],Table1__2[],8,FALSE) -> Bronze | T70: =VLOOKUP(Table8_16[[#This Row],[Customer_ID]],Table1__2[],9,FALSE) -> Entry level Professionel | U70: =VLOOKUP(Table8_16[[#This Row],[Product_ID]],Table3__211[],2,FALSE) -> Professional Jump | V70: =VLOOKUP(Table8_16[[#This Row],[Product_ID]],Table3__211[],3,FALSE) -> Rope | W70: =VLOOKUP(Table8_16[[#This Row],[Product_ID]],Table3__211[],4,FALSE) -> Sports | X70: =VLOOKUP(Table8_16[[#This Row],[Product_ID]],Table3__211[],5,FALSE) -> Fitness | Y70: =VLOOKUP(Table8_16[[#This Row],[Product_ID]],Table3__211[],6,FALSE) -> Davis PLC | Z70: =VLOOKUP(Table8_16[[#This Row],[Product_ID]],Table3__211[],7,FALSE) -> 477.61 | AA70: =VLOOKUP(Table8_16[[#This Row],[Product_ID]],Table3__211[],8,FALSE) -> 300 | AB70: =VLOOKUP(Table8_16[[#This Row],[Store_ID]],Store!$A$2:$E$21,2,FALSE) -> Hill, Wagner and Ballard | AC70: =VLOOKUP(Table8_16[[#This Row],[Store_ID]],Store!$A$2:$E$21,3,FALSE) -> East | AD70: =VLOOKUP(Table8_16[[#This Row],[Store_ID]],Store!$A$2:$E$21,4,FALSE) -> East Davidville | AE70: =VLOOKUP(Table8_16[[#This Row],[Store_ID]],Store!$A$2:$E$21,5,FALSE) -> Online | AF70: =VLOOKUP(Table8_16[[#This Row],[Store_ID]],Store!$A$2:$F$21,6,FALSE) -> Digital Store
A71: SALE69 | B71: 45897 | C71: CUST1423 | D71: PROD13 | E71: STORE16 | F71: 4 | G71: 561.24 | H71: 0.24 | I71: Credit Card | J71: 1706.1696 | K71: 1706.1696 | L71: =_xlfn.IFS(Table8_1[[#This Row],[Unit_Price]]<500,"Low Price",Table8_1[[#This Row],[Unit_Price]]<2000,"Medium Price",Table8_1[[#This Row],[Unit_Price]]>=2000, "High Price") -> Medium Price | M71: =VLOOKUP(Table8_16[[#This Row],[Customer_ID]],Table1__2[],2,FALSE) -> Rebecca Baker | N71: =VLOOKUP(Table8_16[[#This Row],[Customer_ID]],Table1__2[],3,FALSE) -> 35 | O71: =VLOOKUP(Table8_16[[#This Row],[Customer_ID]],Table1__2[],4,FALSE) -> Male | P71: =VLOOKUP(Table8_16[[#This Row],[Customer_ID]],Table1__2[],5,FALSE) -> New Katherine | Q71: =VLOOKUP(Table8_16[[#This Row],[Customer_ID]],Table1__2[],6,FALSE) -> Kansas | R71: =VLOOKUP(Table8_16[[#This Row],[Customer_ID]],Table1__2[],7,FALSE) -> USA | S71: =VLOOKUP(Table8_16[[#This Row],[Customer_ID]],Table1__2[],8,FALSE) -> Silver | T71: =VLOOKUP(Table8_16[[#This Row],[Customer_ID]],Table1__2[],9,FALSE) -> Experienced | U71: =VLOOKUP(Table8_16[[#This Row],[Product_ID]],Table3__211[],2,FALSE) -> USB-C Fast | V71: =VLOOKUP(Table8_16[[#This Row],[Product_ID]],Table3__211[],3,FALSE) -> Charger | W71: =VLOOKUP(Table8_16[[#This Row],[Product_ID]],Table3__211[],4,FALSE) -> Electronics | X71: =VLOOKUP(Table8_16[[#This Row],[Product_ID]],Table3__211[],5,FALSE) -> Accessories | Y71: =VLOOKUP(Table8_16[[#This Row],[Product_ID]],Table3__211[],6,FALSE) -> Dawson-Perkins | Z71: =VLOOKUP(Table8_16[[#This Row],[Product_ID]],Table3__211[],7,FALSE) -> 242.23 | AA71: =VLOOKUP(Table8_16[[#This Row],[Product_ID]],Table3__211[],8,FALSE) -> 453 | AB71: =VLOOKUP(Table8_16[[#This Row],[Store_ID]],Store!$A$2:$E$21,2,FALSE) -> Frederick-Wright | AC71: =VLOOKUP(Table8_16[[#This Row],[Store_ID]],Store!$A$2:$E$21,3,FALSE) -> West | AD71: =VLOOKUP(Table8_16[[#This Row],[Store_ID]],Store!$A$2:$E$21,4,FALSE) -> New Jimmymouth | AE71: =VLOOKUP(Table8_16[[#This Row],[Store_ID]],Store!$A$2:$E$21,5,FALSE) -> Flagship | AF71: =VLOOKUP(Table8_16[[#This Row],[Store_ID]],Store!$A$2:$F$21,6,FALSE) -> Physical Store
A72: SALE70 | B72: 45849 | C72: CUST1058 | D72: PROD60 | E72: STORE5 | F72: 3 | G72: 92.24 | H72: 0.28 | I72: COD | K72: 199.2384 | L72: =_xlfn.IFS(Table8_1[[#This Row],[Unit_Price]]<500,"Low Price",Table8_1[[#This Row],[Unit_Price]]<2000,"Medium Price",Table8_1[[#This Row],[Unit_Price]]>=2000, "High Price") -> Low Price | M72: =VLOOKUP(Table8_16[[#This Row],[Customer_ID]],Table1__2[],2,FALSE) -> Cheryl Copeland | N72: =VLOOKUP(Table8_16[[#This Row],[Customer_ID]],Table1__2[],3,FALSE) -> 51 | O72: =VLOOKUP(Table8_16[[#This Row],[Customer_ID]],Table1__2[],4,FALSE) -> Male | P72: =VLOOKUP(Table8_16[[#This Row],[Customer_ID]],Table1__2[],5,FALSE) -> Snowmouth | Q72: =VLOOKUP(Table8_16[[#This Row],[Customer_ID]],Table1__2[],6,FALSE) -> Maryland | R72: =VLOOKUP(Table8_16[[#This Row],[Customer_ID]],Table1__2[],7,FALSE) -> USA | S72: =VLOOKUP(Table8_16[[#This Row],[Customer_ID]],Table1__2[],8,FALSE) -> Platinum | T72: =VLOOKUP(Table8_16[[#This Row],[Customer_ID]],Table1__2[],9,FALSE) -> Experienced | U72: =VLOOKUP(Table8_16[[#This Row],[Product_ID]],Table3__211[],2,FALSE) -> Luxury Perfume | V72: =VLOOKUP(Table8_16[[#This Row],[Product_ID]],Table3__211[],3,FALSE) -> Spray | W72: =VLOOKUP(Table8_16[[#This Row],[Product_ID]],Table3__211[],4,FALSE) -> Beauty | X72: =VLOOKUP(Table8_16[[#This Row],[Product_ID]],Table3__211[],5,FALSE) -> Fragrance | Y72: =VLOOKUP(Table8_16[[#This Row],[Product_ID]],Table3__211[],6,FALSE) -> Gibson, Green and Lopez | Z72: =VLOOKUP(Table8_16[[#This Row],[Product_ID]],Table3__211[],7,FALSE) -> 482.75 | AA72: =VLOOKUP(Table8_16[[#This Row],[Product_ID]],Table3__211[],8,FALSE) -> 444 | AB72: =VLOOKUP(Table8_16[[#This Row],[Store_ID]],Store!$A$2:$E$21,2,FALSE) -> Gray Ltd | AC72: =VLOOKUP(Table8_16[[#This Row],[Store_ID]],Store!$A$2:$E$21,3,FALSE) -> North | AD72: =VLOOKUP(Table8_16[[#This Row],[Store_ID]],Store!$A$2:$E$21,4,FALSE) -> New Michaelchester | AE72: =VLOOKUP(Table8_16[[#This Row],[Store_ID]],Store!$A$2:$E$21,5,FALSE) -> Outlet | AF72: =VLOOKUP(Table8_16[[#This Row],[Store_ID]],Store!$A$2:$F$21,6,FALSE) -> Physical Store
A73: SALE71 | B73: 45889 | C73: CUST1168 | D73: PROD72 | E73: STORE1 | F73: 2 | G73: 668.3 | H73: 0.07 | I73: Credit Card | J73: 1243.038 | K73: 1243.038 | L73: =_xlfn.IFS(Table8_1[[#This Row],[Unit_Price]]<500,"Low Price",Table8_1[[#This Row],[Unit_Price]]<2000,"Medium Price",Table8_1[[#This Row],[Unit_Price]]>=2000, "High Price") -> Medium Price | M73: =VLOOKUP(Table8_16[[#This Row],[Customer_ID]],Table1__2[],2,FALSE) -> Daniel Contreras | N73: =VLOOKUP(Table8_16[[#This Row],[Customer_ID]],Table1__2[],3,FALSE) -> 36 | O73: =VLOOKUP(Table8_16[[#This Row],[Customer_ID]],Table1__2[],4,FALSE) -> Female | P73: =VLOOKUP(Table8_16[[#This Row],[Customer_ID]],Table1__2[],5,FALSE) -> Robertview | Q73: =VLOOKUP(Table8_16[[#This Row],[Customer_ID]],Table1__2[],6,FALSE) -> Florida | R73: =VLOOKUP(Table8_16[[#This Row],[Customer_ID]],Table1__2[],7,FALSE) -> USA | S73: =VLOOKUP(Table8_16[[#This Row],[Customer_ID]],Table1__2[],8,FALSE) -> Platinum | T73: =VLOOKUP(Table8_16[[#This Row],[Customer_ID]],Table1__2[],9,FALSE) -> Experienced | U73: =VLOOKUP(Table8_16[[#This Row],[Product_ID]],Table3__211[],2,FALSE) -> Professional Jump | V73: =VLOOKUP(Table8_16[[#This Row],[Product_ID]],Table3__211[],3,FALSE) -> Rope | W73: =VLOOKUP(Table8_16[[#This Row],[Product_ID]],Table3__211[],4,FALSE) -> Sports | X73: =VLOOKUP(Table8_16[[#This Row],[Product_ID]],Table3__211[],5,FALSE) -> Fitness | Y73: =VLOOKUP(Table8_16[[#This Row],[Product_ID]],Table3__211[],6,FALSE) -> Davis PLC | Z73: =VLOOKUP(Table8_16[[#This Row],[Product_ID]],Table3__211[],7,FALSE) -> 477.61 | AA73: =VLOOKUP(Table8_16[[#This Row],[Product_ID]],Table3__211[],8,FALSE) -> 300 | AB73: =VLOOKUP(Table8_16[[#This Row],[Store_ID]],Store!$A$2:$E$21,2,FALSE) -> Martinez, Adkins and Johnson | AC73: =VLOOKUP(Table8_16[[#This Row],[Store_ID]],Store!$A$2:$E$21,3,FALSE) -> North | AD73: =VLOOKUP(Table8_16[[#This Row],[Store_ID]],Store!$A$2:$E$21,4,FALSE) -> Danielmouth | AE73: =VLOOKUP(Table8_16[[#This Row],[Store_ID]],Store!$A$2:$E$21,5,FALSE) -> Flagship | AF73: =VLOOKUP(Table8_16[[#This Row],[Store_ID]],Store!$A$2:$F$21,6,FALSE) -> Physical Store
A74: SALE72 | B74: 45533 | C74: CUST1409 | D74: PROD38 | E74: STORE5 | F74: 1 | G74: 553.82 | H74: 0.09 | I74: Credit Card | J74: 503.9762 | K74: 503.9762 | L74: =_xlfn.IFS(Table8_1[[#This Row],[Unit_Price]]<500,"Low Price",Table8_1[[#This Row],[Unit_Price]]<2000,"Medium Price",Table8_1[[#This Row],[Unit_Price]]>=2000, "High Price") -> Medium Price | M74: =VLOOKUP(Table8_16[[#This Row],[Customer_ID]],Table1__2[],2,FALSE) -> Sarah Smith | N74: =VLOOKUP(Table8_16[[#This Row],[Customer_ID]],Table1__2[],3,FALSE) -> 55 | O74: =VLOOKUP(Table8_16[[#This Row],[Customer_ID]],Table1__2[],4,FALSE) -> Male | P74: =VLOOKUP(Table8_16[[#This Row],[Customer_ID]],Table1__2[],5,FALSE) -> Kathleenport | Q74: =VLOOKUP(Table8_16[[#This Row],[Customer_ID]],Table1__2[],6,FALSE) -> Wyoming | R74: =VLOOKUP(Table8_16[[#This Row],[Customer_ID]],Table1__2[],7,FALSE) -> USA | S74: =VLOOKUP(Table8_16[[#This Row],[Customer_ID]],Table1__2[],8,FALSE) -> Gold | T74: =VLOOKUP(Table8_16[[#This Row],[Customer_ID]],Table1__2[],9,FALSE) -> Experienced | U74: =VLOOKUP(Table8_16[[#This Row],[Product_ID]],Table3__211[],2,FALSE) -> Sports Water Hydration | V74: =VLOOKUP(Table8_16[[#This Row],[Product_ID]],Table3__211[],3,FALSE) -> Pack | W74: =VLOOKUP(Table8_16[[#This Row],[Product_ID]],Table3__211[],4,FALSE) -> Sports | X74: =VLOOKUP(Table8_16[[#This Row],[Product_ID]],Table3__211[],5,FALSE) -> Outdoor | Y74: =VLOOKUP(Table8_16[[#This Row],[Product_ID]],Table3__211[],6,FALSE) -> Sims-Smith | Z74: =VLOOKUP(Table8_16[[#This Row],[Product_ID]],Table3__211[],7,FALSE) -> 135.61 | AA74: =VLOOKUP(Table8_16[[#This Row],[Product_ID]],Table3__211[],8,FALSE) -> 394 | AB74: =VLOOKUP(Table8_16[[#This Row],[Store_ID]],Store!$A$2:$E$21,2,FALSE) -> Gray Ltd | AC74: =VLOOKUP(Table8_16[[#This Row],[Store_ID]],Store!$A$2:$E$21,3,FALSE) -> North | AD74: =VLOOKUP(Table8_16[[#This Row],[Store_ID]],Store!$A$2:$E$21,4,FALSE) -> New Michaelchester | AE74: =VLOOKUP(Table8_16[[#This Row],[Store_ID]],Store!$A$2:$E$21,5,FALSE) -> Outlet | AF74: =VLOOKUP(Table8_16[[#This Row],[Store_ID]],Store!$A$2:$F$21,6,FALSE) -> Physical Store
A75: SALE73 | B75: 45626 | C75: CUST1037 | D75: PROD45 | E75: STORE11 | F75: 2 | G75: 556.43 | H75: 0.13 | I75: Credit Card | J75: 968.1882 | K75: 968.1882 | L75: =_xlfn.IFS(Table8_1[[#This Row],[Unit_Price]]<500,"Low Price",Table8_1[[#This Row],[Unit_Price]]<2000,"Medium Price",Table8_1[[#This Row],[Unit_Price]]>=2000, "High Price") -> Medium Price | M75: =VLOOKUP(Table8_16[[#This Row],[Customer_ID]],Table1__2[],2,FALSE) -> Christopher Carter | N75: =VLOOKUP(Table8_16[[#This Row],[Customer_ID]],Table1__2[],3,FALSE) -> 27 | O75: =VLOOKUP(Table8_16[[#This Row],[Customer_ID]],Table1__2[],4,FALSE) -> Female | P75: =VLOOKUP(Table8_16[[#This Row],[Customer_ID]],Table1__2[],5,FALSE) -> Brendastad | Q75: =VLOOKUP(Table8_16[[#This Row],[Customer_ID]],Table1__2[],6,FALSE) -> South Dakota | R75: =VLOOKUP(Table8_16[[#This Row],[Customer_ID]],Table1__2[],7,FALSE) -> USA | S75: =VLOOKUP(Table8_16[[#This Row],[Customer_ID]],Table1__2[],8,FALSE) -> unknown | T75: =VLOOKUP(Table8_16[[#This Row],[Customer_ID]],Table1__2[],9,FALSE) -> Entry level Professionel | U75: =VLOOKUP(Table8_16[[#This Row],[Product_ID]],Table3__211[],2,FALSE) -> High-Grip | V75: =VLOOKUP(Table8_16[[#This Row],[Product_ID]],Table3__211[],3,FALSE) -> Football | W75: =VLOOKUP(Table8_16[[#This Row],[Product_ID]],Table3__211[],4,FALSE) -> Sports | X75: =VLOOKUP(Table8_16[[#This Row],[Product_ID]],Table3__211[],5,FALSE) -> Team Sports | Y75: =VLOOKUP(Table8_16[[#This Row],[Product_ID]],Table3__211[],6,FALSE) -> Bridges, Banks and Cummings | Z75: =VLOOKUP(Table8_16[[#This Row],[Product_ID]],Table3__211[],7,FALSE) -> 318.91 | AA75: =VLOOKUP(Table8_16[[#This Row],[Product_ID]],Table3__211[],8,FALSE) -> 114 | AB75: =VLOOKUP(Table8_16[[#This Row],[Store_ID]],Store!$A$2:$E$21,2,FALSE) -> Aguirre-Keller | AC75: =VLOOKUP(Table8_16[[#This Row],[Store_ID]],Store!$A$2:$E$21,3,FALSE) -> South | AD75: =VLOOKUP(Table8_16[[#This Row],[Store_ID]],Store!$A$2:$E$21,4,FALSE) -> Lake Michael | AE75: =VLOOKUP(Table8_16[[#This Row],[Store_ID]],Store!$A$2:$E$21,5,FALSE) -> Online | AF75: =VLOOKUP(Table8_16[[#This Row],[Store_ID]],Store!$A$2:$F$21,6,FALSE) -> Digital Store
A76: SALE74 | B76: 45942 | C76: CUST1273 | D76: PROD20 | E76: STORE8 | F76: 1 | G76: 184.98 | H76: 0.1 | I76: COD | J76: 166.482 | K76: 166.482 | L76: =_xlfn.IFS(Table8_1[[#This Row],[Unit_Price]]<500,"Low Price",Table8_1[[#This Row],[Unit_Price]]<2000,"Medium Price",Table8_1[[#This Row],[Unit_Price]]>=2000, "High Price") -> Low Price | M76: =VLOOKUP(Table8_16[[#This Row],[Customer_ID]],Table1__2[],2,FALSE) -> Samantha Robinson | N76: =VLOOKUP(Table8_16[[#This Row],[Customer_ID]],Table1__2[],3,FALSE) -> 23 | O76: =VLOOKUP(Table8_16[[#This Row],[Customer_ID]],Table1__2[],4,FALSE) -> Male | P76: =VLOOKUP(Table8_16[[#This Row],[Customer_ID]],Table1__2[],5,FALSE) -> North Roy | Q76: =VLOOKUP(Table8_16[[#This Row],[Customer_ID]],Table1__2[],6,FALSE) -> Mississippi | R76: =VLOOKUP(Table8_16[[#This Row],[Customer_ID]],Table1__2[],7,FALSE) -> USA | S76: =VLOOKUP(Table8_16[[#This Row],[Customer_ID]],Table1__2[],8,FALSE) -> Bronze | T76: =VLOOKUP(Table8_16[[#This Row],[Customer_ID]],Table1__2[],9,FALSE) -> Students | U76: =VLOOKUP(Table8_16[[#This Row],[Product_ID]],Table3__211[],2,FALSE) -> Outdoor Sports Water | V76: =VLOOKUP(Table8_16[[#This Row],[Product_ID]],Table3__211[],3,FALSE) -> Bottle | W76: =VLOOKUP(Table8_16[[#This Row],[Product_ID]],Table3__211[],4,FALSE) -> Sports | X76: =VLOOKUP(Table8_16[[#This Row],[Product_ID]],Table3__211[],5,FALSE) -> Accessories | Y76: =VLOOKUP(Table8_16[[#This Row],[Product_ID]],Table3__211[],6,FALSE) -> Soto-Ellis | Z76: =VLOOKUP(Table8_16[[#This Row],[Product_ID]],Table3__211[],7,FALSE) -> 131.51 | AA76: =VLOOKUP(Table8_16[[#This Row],[Product_ID]],Table3__211[],8,FALSE) -> 273 | AB76: =VLOOKUP(Table8_16[[#This Row],[Store_ID]],Store!$A$2:$E$21,2,FALSE) -> Bean, Jones and Park | AC76: =VLOOKUP(Table8_16[[#This Row],[Store_ID]],Store!$A$2:$E$21,3,FALSE) -> West | AD76: =VLOOKUP(Table8_16[[#This Row],[Store_ID]],Store!$A$2:$E$21,4,FALSE) -> Thompsonborough | AE76: =VLOOKUP(Table8_16[[#This Row],[Store_ID]],Store!$A$2:$E$21,5,FALSE) -> Online | AF76: =VLOOKUP(Table8_16[[#This Row],[Store_ID]],Store!$A$2:$F$21,6,FALSE) -> Digital Store
A77: SALE75 | B77: 45500 | C77: CUST1035 | D77: PROD97 | E77: STORE12 | F77: 4 | G77: 700.18 | H77: 0.23 | I77: Credit Card | J77: 2156.5544 | K77: 2156.5544 | L77: =_xlfn.IFS(Table8_1[[#This Row],[Unit_Price]]<500,"Low Price",Table8_1[[#This Row],[Unit_Price]]<2000,"Medium Price",Table8_1[[#This Row],[Unit_Price]]>=2000, "High Price") -> Medium Price | M77: =VLOOKUP(Table8_16[[#This Row],[Customer_ID]],Table1__2[],2,FALSE) -> Rachel Myers | N77: =VLOOKUP(Table8_16[[#This Row],[Customer_ID]],Table1__2[],3,FALSE) -> 52 | O77: =VLOOKUP(Table8_16[[#This Row],[Customer_ID]],Table1__2[],4,FALSE) -> Male | P77: =VLOOKUP(Table8_16[[#This Row],[Customer_ID]],Table1__2[],5,FALSE) -> Robertberg | Q77: =VLOOKUP(Table8_16[[#This Row],[Customer_ID]],Table1__2[],6,FALSE) -> North Dakota | R77: =VLOOKUP(Table8_16[[#This Row],[Customer_ID]],Table1__2[],7,FALSE) -> USA | S77: =VLOOKUP(Table8_16[[#This Row],[Customer_ID]],Table1__2[],8,FALSE) -> Silver | T77: =VLOOKUP(Table8_16[[#This Row],[Customer_ID]],Table1__2[],9,FALSE) -> Experienced | U77: =VLOOKUP(Table8_16[[#This Row],[Product_ID]],Table3__211[],2,FALSE) -> Cricket | V77: =VLOOKUP(Table8_16[[#This Row],[Product_ID]],Table3__211[],3,FALSE) -> Bat | W77: =VLOOKUP(Table8_16[[#This Row],[Product_ID]],Table3__211[],4,FALSE) -> Sports | X77: =VLOOKUP(Table8_16[[#This Row],[Product_ID]],Table3__211[],5,FALSE) -> Team Sports | Y77: =VLOOKUP(Table8_16[[#This Row],[Product_ID]],Table3__211[],6,FALSE) -> Khan LLC | Z77: =VLOOKUP(Table8_16[[#This Row],[Product_ID]],Table3__211[],7,FALSE) -> 245.98 | AA77: =VLOOKUP(Table8_16[[#This Row],[Product_ID]],Table3__211[],8,FALSE) -> 471 | AB77: =VLOOKUP(Table8_16[[#This Row],[Store_ID]],Store!$A$2:$E$21,2,FALSE) -> Thomas, Bridges and Harris | AC77: =VLOOKUP(Table8_16[[#This Row],[Store_ID]],Store!$A$2:$E$21,3,FALSE) -> North | AD77: =VLOOKUP(Table8_16[[#This Row],[Store_ID]],Store!$A$2:$E$21,4,FALSE) -> Sabrinatown | AE77: =VLOOKUP(Table8_16[[#This Row],[Store_ID]],Store!$A$2:$E$21,5,FALSE) -> Online | AF77: =VLOOKUP(Table8_16[[#This Row],[Store_ID]],Store!$A$2:$F$21,6,FALSE) -> Digital Store
A78: SALE76 | B78: 45285 | C78: CUST1019 | D78: PROD76 | E78: STORE10 | F78: 2 | G78: 686.31 | H78: 0.25 | I78: Credit Card | J78: 1029.465 | K78: 1029.465 | L78: =_xlfn.IFS(Table8_1[[#This Row],[Unit_Price]]<500,"Low Price",Table8_1[[#This Row],[Unit_Price]]<2000,"Medium Price",Table8_1[[#This Row],[Unit_Price]]>=2000, "High Price") -> Medium Price | M78: =VLOOKUP(Table8_16[[#This Row],[Customer_ID]],Table1__2[],2,FALSE) -> Michael Torres | N78: =VLOOKUP(Table8_16[[#This Row],[Customer_ID]],Table1__2[],3,FALSE) -> 46 | O78: =VLOOKUP(Table8_16[[#This Row],[Customer_ID]],Table1__2[],4,FALSE) -> Female | P78: =VLOOKUP(Table8_16[[#This Row],[Customer_ID]],Table1__2[],5,FALSE) -> Gonzalezfort | Q78: =VLOOKUP(Table8_16[[#This Row],[Customer_ID]],Table1__2[],6,FALSE) -> New Jersey | R78: =VLOOKUP(Table8_16[[#This Row],[Customer_ID]],Table1__2[],7,FALSE) -> USA | S78: =VLOOKUP(Table8_16[[#This Row],[Customer_ID]],Table1__2[],8,FALSE) -> Platinum | T78: =VLOOKUP(Table8_16[[#This Row],[Customer_ID]],Table1__2[],9,FALSE) -> Experienced | U78: =VLOOKUP(Table8_16[[#This Row],[Product_ID]],Table3__211[],2,FALSE) -> Wireless | V78: =VLOOKUP(Table8_16[[#This Row],[Product_ID]],Table3__211[],3,FALSE) -> Mouse | W78: =VLOOKUP(Table8_16[[#This Row],[Product_ID]],Table3__211[],4,FALSE) -> Electronics | X78: =VLOOKUP(Table8_16[[#This Row],[Product_ID]],Table3__211[],5,FALSE) -> Computer | Y78: =VLOOKUP(Table8_16[[#This Row],[Product_ID]],Table3__211[],6,FALSE) -> Larson Ltd | Z78: =VLOOKUP(Table8_16[[#This Row],[Product_ID]],Table3__211[],7,FALSE) -> 392.89 | AA78: =VLOOKUP(Table8_16[[#This Row],[Product_ID]],Table3__211[],8,FALSE) -> 320 | AB78: =VLOOKUP(Table8_16[[#This Row],[Store_ID]],Store!$A$2:$E$21,2,FALSE) -> Hill, Wagner and Ballard | AC78: =VLOOKUP(Table8_16[[#This Row],[Store_ID]],Store!$A$2:$E$21,3,FALSE) -> East | AD78: =VLOOKUP(Table8_16[[#This Row],[Store_ID]],Store!$A$2:$E$21,4,FALSE) -> East Davidville | AE78: =VLOOKUP(Table8_16[[#This Row],[Store_ID]],Store!$A$2:$E$21,5,FALSE) -> Online | AF78: =VLOOKUP(Table8_16[[#This Row],[Store_ID]],Store!$A$2:$F$21,6,FALSE) -> Digital Store
A79: SALE77 | B79: 45800 | C79: CUST1007 | D79: PROD67 | E79: STORE15 | F79: 1 | G79: 687.82 | H79: 0.27 | I79: COD | J79: 502.1086 | K79: 502.1086 | L79: =_xlfn.IFS(Table8_1[[#This Row],[Unit_Price]]<500,"Low Price",Table8_1[[#This Row],[Unit_Price]]<2000,"Medium Price",Table8_1[[#This Row],[Unit_Price]]>=2000, "High Price") -> Medium Price | M79: =VLOOKUP(Table8_16[[#This Row],[Customer_ID]],Table1__2[],2,FALSE) -> Daniel Boyd | N79: =VLOOKUP(Table8_16[[#This Row],[Customer_ID]],Table1__2[],3,FALSE) -> 29 | O79: =VLOOKUP(Table8_16[[#This Row],[Customer_ID]],Table1__2[],4,FALSE) -> Female | P79: =VLOOKUP(Table8_16[[#This Row],[Customer_ID]],Table1__2[],5,FALSE) -> West Pamelafurt | Q79: =VLOOKUP(Table8_16[[#This Row],[Customer_ID]],Table1__2[],6,FALSE) -> West Virginia | R79: =VLOOKUP(Table8_16[[#This Row],[Customer_ID]],Table1__2[],7,FALSE) -> USA | S79: =VLOOKUP(Table8_16[[#This Row],[Customer_ID]],Table1__2[],8,FALSE) -> Bronze | T79: =VLOOKUP(Table8_16[[#This Row],[Customer_ID]],Table1__2[],9,FALSE) -> Entry level Professionel | U79: =VLOOKUP(Table8_16[[#This Row],[Product_ID]],Table3__211[],2,FALSE) -> Smart LED Light | V79: =VLOOKUP(Table8_16[[#This Row],[Product_ID]],Table3__211[],3,FALSE) -> Strip | W79: =VLOOKUP(Table8_16[[#This Row],[Product_ID]],Table3__211[],4,FALSE) -> Electronics | X79: =VLOOKUP(Table8_16[[#This Row],[Product_ID]],Table3__211[],5,FALSE) -> Accessories | Y79: =VLOOKUP(Table8_16[[#This Row],[Product_ID]],Table3__211[],6,FALSE) -> Flores-Davis | Z79: =VLOOKUP(Table8_16[[#This Row],[Product_ID]],Table3__211[],7,FALSE) -> 349.17 | AA79: =VLOOKUP(Table8_16[[#This Row],[Product_ID]],Table3__211[],8,FALSE) -> 476 | AB79: =VLOOKUP(Table8_16[[#This Row],[Store_ID]],Store!$A$2:$E$21,2,FALSE) -> Shelton PLC | AC79: =VLOOKUP(Table8_16[[#This Row],[Store_ID]],Store!$A$2:$E$21,3,FALSE) -> North | AD79: =VLOOKUP(Table8_16[[#This Row],[Store_ID]],Store!$A$2:$E$21,4,FALSE) -> East Jenniferstad | AE79: =VLOOKUP(Table8_16[[#This Row],[Store_ID]],Store!$A$2:$E$21,5,FALSE) -> Flagship | AF79: =VLOOKUP(Table8_16[[#This Row],[Store_ID]],Store!$A$2:$F$21,6,FALSE) -> Physical Store
A80: SALE78 | B80: 45609 | C80: CUST1221 | D80: PROD83 | E80: STORE8 | F80: 2 | G80: 900.55 | H80: 0.16 | I80: Credit Card | J80: 1512.924 | K80: 1512.924 | L80: =_xlfn.IFS(Table8_1[[#This Row],[Unit_Price]]<500,"Low Price",Table8_1[[#This Row],[Unit_Price]]<2000,"Medium Price",Table8_1[[#This Row],[Unit_Price]]>=2000, "High Price") -> Medium Price | M80: =VLOOKUP(Table8_16[[#This Row],[Customer_ID]],Table1__2[],2,FALSE) -> Lisa Young | N80: =VLOOKUP(Table8_16[[#This Row],[Customer_ID]],Table1__2[],3,FALSE) -> 38 | O80: =VLOOKUP(Table8_16[[#This Row],[Customer_ID]],Table1__2[],4,FALSE) -> Male | P80: =VLOOKUP(Table8_16[[#This Row],[Customer_ID]],Table1__2[],5,FALSE) -> Maybury | Q80: =VLOOKUP(Table8_16[[#This Row],[Customer_ID]],Table1__2[],6,FALSE) -> Georgia | R80: =VLOOKUP(Table8_16[[#This Row],[Customer_ID]],Table1__2[],7,FALSE) -> USA | S80: =VLOOKUP(Table8_16[[#This Row],[Customer_ID]],Table1__2[],8,FALSE) -> Platinum | T80: =VLOOKUP(Table8_16[[#This Row],[Customer_ID]],Table1__2[],9,FALSE) -> Experienced | U80: =VLOOKUP(Table8_16[[#This Row],[Product_ID]],Table3__211[],2,FALSE) -> Hydrating Face | V80: =VLOOKUP(Table8_16[[#This Row],[Product_ID]],Table3__211[],3,FALSE) -> Cleanser | W80: =VLOOKUP(Table8_16[[#This Row],[Product_ID]],Table3__211[],4,FALSE) -> Beauty | X80: =VLOOKUP(Table8_16[[#This Row],[Product_ID]],Table3__211[],5,FALSE) -> Skincare | Y80: =VLOOKUP(Table8_16[[#This Row],[Product_ID]],Table3__211[],6,FALSE) -> Butler Group | Z80: =VLOOKUP(Table8_16[[#This Row],[Product_ID]],Table3__211[],7,FALSE) -> 254.04 | AA80: =VLOOKUP(Table8_16[[#This Row],[Product_ID]],Table3__211[],8,FALSE) -> 159 | AB80: =VLOOKUP(Table8_16[[#This Row],[Store_ID]],Store!$A$2:$E$21,2,FALSE) -> Bean, Jones and Park | AC80: =VLOOKUP(Table8_16[[#This Row],[Store_ID]],Store!$A$2:$E$21,3,FALSE) -> West | AD80: =VLOOKUP(Table8_16[[#This Row],[Store_ID]],Store!$A$2:$E$21,4,FALSE) -> Thompsonborough | AE80: =VLOOKUP(Table8_16[[#This Row],[Store_ID]],Store!$A$2:$E$21,5,FALSE) -> Online | AF80: =VLOOKUP(Table8_16[[#This Row],[Store_ID]],Store!$A$2:$F$21,6,FALSE) -> Digital Store
A81: SALE79 | B81: 45268 | C81: CUST1115 | D81: PROD21 | E81: STORE2 | F81: 1 | G81: 341.17 | H81: 0.15 | I81: Credit Card | J81: 289.9945 | K81: 289.9945 | L81: =_xlfn.IFS(Table8_1[[#This Row],[Unit_Price]]<500,"Low Price",Table8_1[[#This Row],[Unit_Price]]<2000,"Medium Price",Table8_1[[#This Row],[Unit_Price]]>=2000, "High Price") -> Low Price | M81: =VLOOKUP(Table8_16[[#This Row],[Customer_ID]],Table1__2[],2,FALSE) -> Tyler Conrad | N81: =VLOOKUP(Table8_16[[#This Row],[Customer_ID]],Table1__2[],3,FALSE) -> 53 | O81: =VLOOKUP(Table8_16[[#This Row],[Customer_ID]],Table1__2[],4,FALSE) -> Female | P81: =VLOOKUP(Table8_16[[#This Row],[Customer_ID]],Table1__2[],5,FALSE) -> North Curtischester | Q81: =VLOOKUP(Table8_16[[#This Row],[Customer_ID]],Table1__2[],6,FALSE) -> North Dakota | R81: =VLOOKUP(Table8_16[[#This Row],[Customer_ID]],Table1__2[],7,FALSE) -> USA | S81: =VLOOKUP(Table8_16[[#This Row],[Customer_ID]],Table1__2[],8,FALSE) -> Platinum | T81: =VLOOKUP(Table8_16[[#This Row],[Customer_ID]],Table1__2[],9,FALSE) -> Experienced | U81: =VLOOKUP(Table8_16[[#This Row],[Product_ID]],Table3__211[],2,FALSE) -> Multi-Purpose Storage | V81: =VLOOKUP(Table8_16[[#This Row],[Product_ID]],Table3__211[],3,FALSE) -> Box | W81: =VLOOKUP(Table8_16[[#This Row],[Product_ID]],Table3__211[],4,FALSE) -> Home | X81: =VLOOKUP(Table8_16[[#This Row],[Product_ID]],Table3__211[],5,FALSE) -> Storage | Y81: =VLOOKUP(Table8_16[[#This Row],[Product_ID]],Table3__211[],6,FALSE) -> Gardner-Montes | Z81: =VLOOKUP(Table8_16[[#This Row],[Product_ID]],Table3__211[],7,FALSE) -> 123.46 | AA81: =VLOOKUP(Table8_16[[#This Row],[Product_ID]],Table3__211[],8,FALSE) -> 76 | AB81: =VLOOKUP(Table8_16[[#This Row],[Store_ID]],Store!$A$2:$E$21,2,FALSE) -> Black-Horn | AC81: =VLOOKUP(Table8_16[[#This Row],[Store_ID]],Store!$A$2:$E$21,3,FALSE) -> South | AD81: =VLOOKUP(Table8_16[[#This Row],[Store_ID]],Store!$A$2:$E$21,4,FALSE) -> North Nancyview | AE81: =VLOOKUP(Table8_16[[#This Row],[Store_ID]],Store!$A$2:$E$21,5,FALSE) -> Outlet | AF81: =VLOOKUP(Table8_16[[#This Row],[Store_ID]],Store!$A$2:$F$21,6,FALSE) -> Physical Store
A82: SALE80 | B82: 45885 | C82: CUST1176 | D82: PROD52 | E82: STORE8 | F82: 1 | G82: 442.27 | H82: 0.06 | I82: COD | J82: 415.7338 | K82: 415.7338 | L82: =_xlfn.IFS(Table8_1[[#This Row],[Unit_Price]]<500,"Low Price",Table8_1[[#This Row],[Unit_Price]]<2000,"Medium Price",Table8_1[[#This Row],[Unit_Price]]>=2000, "High Price") -> Low Price | M82: =VLOOKUP(Table8_16[[#This Row],[Customer_ID]],Table1__2[],2,FALSE) -> John Bradford | N82: =VLOOKUP(Table8_16[[#This Row],[Customer_ID]],Table1__2[],3,FALSE) -> 48 | O82: =VLOOKUP(Table8_16[[#This Row],[Customer_ID]],Table1__2[],4,FALSE) -> Male | P82: =VLOOKUP(Table8_16[[#This Row],[Customer_ID]],Table1__2[],5,FALSE) -> Anabury | Q82: =VLOOKUP(Table8_16[[#This Row],[Customer_ID]],Table1__2[],6,FALSE) -> Vermont | R82: =VLOOKUP(Table8_16[[#This Row],[Customer_ID]],Table1__2[],7,FALSE) -> USA | S82: =VLOOKUP(Table8_16[[#This Row],[Customer_ID]],Table1__2[],8,FALSE) -> Silver | T82: =VLOOKUP(Table8_16[[#This Row],[Customer_ID]],Table1__2[],9,FALSE) -> Experienced | U82: =VLOOKUP(Table8_16[[#This Row],[Product_ID]],Table3__211[],2,FALSE) -> Rugby | V82: =VLOOKUP(Table8_16[[#This Row],[Product_ID]],Table3__211[],3,FALSE) -> Ball | W82: =VLOOKUP(Table8_16[[#This Row],[Product_ID]],Table3__211[],4,FALSE) -> Sports | X82: =VLOOKUP(Table8_16[[#This Row],[Product_ID]],Table3__211[],5,FALSE) -> Team Sports | Y82: =VLOOKUP(Table8_16[[#This Row],[Product_ID]],Table3__211[],6,FALSE) -> Harris Inc | Z82: =VLOOKUP(Table8_16[[#This Row],[Product_ID]],Table3__211[],7,FALSE) -> 212.26 | AA82: =VLOOKUP(Table8_16[[#This Row],[Product_ID]],Table3__211[],8,FALSE) -> 82 | AB82: =VLOOKUP(Table8_16[[#This Row],[Store_ID]],Store!$A$2:$E$21,2,FALSE) -> Bean, Jones and Park | AC82: =VLOOKUP(Table8_16[[#This Row],[Store_ID]],Store!$A$2:$E$21,3,FALSE) -> West | AD82: =VLOOKUP(Table8_16[[#This Row],[Store_ID]],Store!$A$2:$E$21,4,FALSE) -> Thompsonborough | AE82: =VLOOKUP(Table8_16[[#This Row],[Store_ID]],Store!$A$2:$E$21,5,FALSE) -> Online | AF82: =VLOOKUP(Table8_16[[#This Row],[Store_ID]],Store!$A$2:$F$21,6,FALSE) -> Digital Store
A83: SALE81 | B83: 45616 | C83: CUST1253 | D83: PROD71 | E83: STORE9 | F83: 1 | G83: 363.73 | H83: 0.25 | I83: PayPal | J83: 272.7975 | K83: 272.7975 | L83: =_xlfn.IFS(Table8_1[[#This Row],[Unit_Price]]<500,"Low Price",Table8_1[[#This Row],[Unit_Price]]<2000,"Medium Price",Table8_1[[#This Row],[Unit_Price]]>=2000, "High Price") -> Low Price | M83: =VLOOKUP(Table8_16[[#This Row],[Customer_ID]],Table1__2[],2,FALSE) -> Dr. Ashley Yates Md | N83: =VLOOKUP(Table8_16[[#This Row],[Customer_ID]],Table1__2[],3,FALSE) -> 32 | O83: =VLOOKUP(Table8_16[[#This Row],[Customer_ID]],Table1__2[],4,FALSE) -> Male | P83: =VLOOKUP(Table8_16[[#This Row],[Customer_ID]],Table1__2[],5,FALSE) -> New Maria | Q83: =VLOOKUP(Table8_16[[#This Row],[Customer_ID]],Table1__2[],6,FALSE) -> Wisconsin | R83: =VLOOKUP(Table8_16[[#This Row],[Customer_ID]],Table1__2[],7,FALSE) -> USA | S83: =VLOOKUP(Table8_16[[#This Row],[Customer_ID]],Table1__2[],8,FALSE) -> Bronze | T83: =VLOOKUP(Table8_16[[#This Row],[Customer_ID]],Table1__2[],9,FALSE) -> Experienced | U83: =VLOOKUP(Table8_16[[#This Row],[Product_ID]],Table3__211[],2,FALSE) -> Hair Repair Oil | V83: =VLOOKUP(Table8_16[[#This Row],[Product_ID]],Table3__211[],3,FALSE) -> Treatment | W83: =VLOOKUP(Table8_16[[#This Row],[Product_ID]],Table3__211[],4,FALSE) -> Beauty | X83: =VLOOKUP(Table8_16[[#This Row],[Product_ID]],Table3__211[],5,FALSE) -> Haircare | Y83: =VLOOKUP(Table8_16[[#This Row],[Product_ID]],Table3__211[],6,FALSE) -> Hopkins Ltd | Z83: =VLOOKUP(Table8_16[[#This Row],[Product_ID]],Table3__211[],7,FALSE) -> 214.32 | AA83: =VLOOKUP(Table8_16[[#This Row],[Product_ID]],Table3__211[],8,FALSE) -> 383 | AB83: =VLOOKUP(Table8_16[[#This Row],[Store_ID]],Store!$A$2:$E$21,2,FALSE) -> Moore, Padilla and Butler | AC83: =VLOOKUP(Table8_16[[#This Row],[Store_ID]],Store!$A$2:$E$21,3,FALSE) -> South | AD83: =VLOOKUP(Table8_16[[#This Row],[Store_ID]],Store!$A$2:$E$21,4,FALSE) -> East Johnstad | AE83: =VLOOKUP(Table8_16[[#This Row],[Store_ID]],Store!$A$2:$E$21,5,FALSE) -> Flagship | AF83: =VLOOKUP(Table8_16[[#This Row],[Store_ID]],Store!$A$2:$F$21,6,FALSE) -> Physical Store
A84: SALE82 | B84: 45518 | C84: CUST1378 | D84: PROD91 | E84: STORE17 | F84: 2 | G84: 601.33 | H84: 0.16 | I84: PayPal | J84: 1010.2344 | K84: 1010.2344 | L84: =_xlfn.IFS(Table8_1[[#This Row],[Unit_Price]]<500,"Low Price",Table8_1[[#This Row],[Unit_Price]]<2000,"Medium Price",Table8_1[[#This Row],[Unit_Price]]>=2000, "High Price") -> Medium Price | M84: =VLOOKUP(Table8_16[[#This Row],[Customer_ID]],Table1__2[],2,FALSE) -> Frank Stewart | N84: =VLOOKUP(Table8_16[[#This Row],[Customer_ID]],Table1__2[],3,FALSE) -> 44 | O84: =VLOOKUP(Table8_16[[#This Row],[Customer_ID]],Table1__2[],4,FALSE) -> Female | P84: =VLOOKUP(Table8_16[[#This Row],[Customer_ID]],Table1__2[],5,FALSE) -> Fischerborough | Q84: =VLOOKUP(Table8_16[[#This Row],[Customer_ID]],Table1__2[],6,FALSE) -> Delaware | R84: =VLOOKUP(Table8_16[[#This Row],[Customer_ID]],Table1__2[],7,FALSE) -> USA | S84: =VLOOKUP(Table8_16[[#This Row],[Customer_ID]],Table1__2[],8,FALSE) -> Bronze | T84: =VLOOKUP(Table8_16[[#This Row],[Customer_ID]],Table1__2[],9,FALSE) -> Experienced | U84: =VLOOKUP(Table8_16[[#This Row],[Product_ID]],Table3__211[],2,FALSE) -> Women's High | V84: =VLOOKUP(Table8_16[[#This Row],[Product_ID]],Table3__211[],3,FALSE) -> Heels | W84: =VLOOKUP(Table8_16[[#This Row],[Product_ID]],Table3__211[],4,FALSE) -> Clothing | X84: =VLOOKUP(Table8_16[[#This Row],[Product_ID]],Table3__211[],5,FALSE) -> Footwear | Y84: =VLOOKUP(Table8_16[[#This Row],[Product_ID]],Table3__211[],6,FALSE) -> Smith-Charles | Z84: =VLOOKUP(Table8_16[[#This Row],[Product_ID]],Table3__211[],7,FALSE) -> 438.25 | AA84: =VLOOKUP(Table8_16[[#This Row],[Product_ID]],Table3__211[],8,FALSE) -> 496 | AB84: =VLOOKUP(Table8_16[[#This Row],[Store_ID]],Store!$A$2:$E$21,2,FALSE) -> Holloway Ltd | AC84: =VLOOKUP(Table8_16[[#This Row],[Store_ID]],Store!$A$2:$E$21,3,FALSE) -> North | AD84: =VLOOKUP(Table8_16[[#This Row],[Store_ID]],Store!$A$2:$E$21,4,FALSE) -> Bensonhaven | AE84: =VLOOKUP(Table8_16[[#This Row],[Store_ID]],Store!$A$2:$E$21,5,FALSE) -> Flagship | AF84: =VLOOKUP(Table8_16[[#This Row],[Store_ID]],Store!$A$2:$F$21,6,FALSE) -> Physical Store
A85: SALE83 | B85: 45427 | C85: CUST1403 | D85: PROD17 | E85: STORE18 | F85: 4 | G85: 34.39 | H85: 0.03 | I85: PayPal | J85: 133.4332 | K85: 133.4332 | L85: =_xlfn.IFS(Table8_1[[#This Row],[Unit_Price]]<500,"Low Price",Table8_1[[#This Row],[Unit_Price]]<2000,"Medium Price",Table8_1[[#This Row],[Unit_Price]]>=2000, "High Price") -> Low Price | M85: =VLOOKUP(Table8_16[[#This Row],[Customer_ID]],Table1__2[],2,FALSE) -> Justin Ingram | N85: =VLOOKUP(Table8_16[[#This Row],[Customer_ID]],Table1__2[],3,FALSE) -> 34 | O85: =VLOOKUP(Table8_16[[#This Row],[Customer_ID]],Table1__2[],4,FALSE) -> Male | P85: =VLOOKUP(Table8_16[[#This Row],[Customer_ID]],Table1__2[],5,FALSE) -> Lake Lisaland | Q85: =VLOOKUP(Table8_16[[#This Row],[Customer_ID]],Table1__2[],6,FALSE) -> Louisiana | R85: =VLOOKUP(Table8_16[[#This Row],[Customer_ID]],Table1__2[],7,FALSE) -> USA | S85: =VLOOKUP(Table8_16[[#This Row],[Customer_ID]],Table1__2[],8,FALSE) -> Bronze | T85: =VLOOKUP(Table8_16[[#This Row],[Customer_ID]],Table1__2[],9,FALSE) -> Experienced | U85: =VLOOKUP(Table8_16[[#This Row],[Product_ID]],Table3__211[],2,FALSE) -> Soccer Training Cone | V85: =VLOOKUP(Table8_16[[#This Row],[Product_ID]],Table3__211[],3,FALSE) -> Set | W85: =VLOOKUP(Table8_16[[#This Row],[Product_ID]],Table3__211[],4,FALSE) -> Sports | X85: =VLOOKUP(Table8_16[[#This Row],[Product_ID]],Table3__211[],5,FALSE) -> Accessories | Y85: =VLOOKUP(Table8_16[[#This Row],[Product_ID]],Table3__211[],6,FALSE) -> Ford, Murphy and Wilson | Z85: =VLOOKUP(Table8_16[[#This Row],[Product_ID]],Table3__211[],7,FALSE) -> 144.53 | AA85: =VLOOKUP(Table8_16[[#This Row],[Product_ID]],Table3__211[],8,FALSE) -> 367 | AB85: =VLOOKUP(Table8_16[[#This Row],[Store_ID]],Store!$A$2:$E$21,2,FALSE) -> Guerrero-Schmitt | AC85: =VLOOKUP(Table8_16[[#This Row],[Store_ID]],Store!$A$2:$E$21,3,FALSE) -> East | AD85: =VLOOKUP(Table8_16[[#This Row],[Store_ID]],Store!$A$2:$E$21,4,FALSE) -> East Stevechester | AE85: =VLOOKUP(Table8_16[[#This Row],[Store_ID]],Store!$A$2:$E$21,5,FALSE) -> Flagship | AF85: =VLOOKUP(Table8_16[[#This Row],[Store_ID]],Store!$A$2:$F$21,6,FALSE) -> Physical Store
